Workbook

Sheet Инструкция по перечислению КУ
A2: 🧾 Инструкция по перечислению коммунальных услуг (КУ)
A3: ✅ Шаг 1. Установите приложение Bank of Georgia
A5: Скачать для Android
A7: Скачать для iPhone
A8: ✅ Шаг 2. Подключение к бизнес-счету
A10: Мы подключим вас к бизнес-счету BOG
A11: ✅ Шаг 3. Оплата коммунальных до 5 числа каждого месяца
A13: Пошаговая инструкция:
A15: Откройте приложение BOG.
A17: Нажмите на значок лари (₾) внизу посередине.
A19: Перейдите в раздел Payments.
A21: Выберите нужную категорию:
... A36: В случае вопросов обращайтесь к ФД.
A39: Вода - 4 строка | C39: Газ - 4 строка | E39: Электричество -2 строка

Sheet 1. Справочник
A1: =F1 | H1: =SUM(H2:H135) -> 157 | I1: =SUM(I2:I135) -> 10070000
A2: 1 | B2: Марина | C2: WS В 503 | D2: WS | E2: Качи | F2: 1+1 | G2: https://airbnb.com/h/wsb503 | H2: 2 | I2: 130000
A3: =A2+1 -> 2 | B3: Марина | C3: WS F 907 | D3: WS | E3: Качи | F3: Студия | G3: https://airbnb.com/h/wsf907 | H3: 1 | I3: 70000
A4: =A3+1 -> 3 | B4: Марина | C4: WS В 212 | D4: WS | E4: Качи | F4: 1+2 | G4: https://airbnb.com/h/wsb212 | H4: 3 | I4: 130000
A5: =A4+1 -> 4 | B5: Марина | C5: WS В 1510 | D5: WS | E5: Качи | F5: Студия | G5: https://airbnb.com/h/wsb1510 | H5: 1 | I5: 70000
A6: =A5+1 -> 5 | B6: Марина | C6: WS В 807 | D6: WS | E6: Качи | F6: Студия | G6: airbnb.com/h/wsb807 | H6: 1 | I6: 70000
A7: =A6+1 -> 6 | B7: Марина | C7: WS E 1202 | D7: WS | E7: Качи | F7: 1+1 | G7: https://airbnb.com/h/wse1202 | H7: 2 | I7: 130000
A8: =A7+1 -> 7 | B8: Марина | C8: WS A 409 | D8: WS | E8: Качи | F8: Студия | G8: https://airbnb.com/h/wsa409 | H8: 1 | I8: 70000
A9: =A8+1 -> 8 | B9: Марина | C9: WS A 608 | D9: WS | E9: Качи | F9: Студия | G9: https://airbnb.com/h/wsa608 | H9: 1 | I9: 70000
A10: =A9+1 -> 9 | B10: Марина | C10: WS A907 | D10: WS | E10: Качи | F10: Студия/твин | G10: https://airbnb.com/h/wsa907 | H10: 1 | I10: 70000
A11: =A10+1 -> 10 | B11: Марина | C11: WS Е804 | D11: WS | E11: Качи | F11: Студия/твин | G11: https://airbnb.com/h/wse804 | H11: 1 | I11: 70000
A12: =A11+1 -> 11 | B12: Марина | C12: WS E704 | D12: WS | E12: Качи | F12: Студия | G12: https://airbnb.com/h/wse704 | H12: 1 | I12: 70000
A13: =A12+1 -> 12 | B13: Марина | C13: WS A805 | D13: WS | E13: Качи | F13: Студия | G13: https://airbnb.com/h/wsa805 | H13: 1 | I13: 70000
A14: =A13+1 -> 13 | B14: Марина | C14: WS F1103 | D14: WS | E14: Качи | F14: 1+1 | G14: https://airbnb.com/h/wsf1103 | H14: 2 | I14: 130000
... A32: =A31+1 -> 31 | B32: Светлана | C32: BV C 0505 | D32: BV | E32: Качи | F32: Студия | G32: http://airbnb.com/h/bvc0505 | H32: 1 | I32: 100000
A33: =A32+1 -> 32 | B33: Светлана | C33: MC A 708 | D33: MC | E33: Качи | F33: Студия | G33: airbnb.com/h/mca708 | H33: 1
A34: =A33+1 -> 33 | B34: Борис | C34: С 1125 | D34: Orbi | E34: Шартава | F34: Студия | G34: https://airbnb.com/h/c1125 | H34: 1 | I34: 50000
A35: =A34+1 -> 34 | B35: Борис | C35: С 1443 | D35: Orbi | E35: Шартава | F35: 1+1 | G35: https://airbnb.com/h/orbic1443 | H35: 2 | I35: 70000
A36: =A35+1 -> 35 | B36: Борис | C36: C 4245 | D36: Orbi | E36: Шартава | F36: 1+1 | G36: https://airbnb.com/h/orbic4245 | H36: 2 | I36: 70000
A37: =A36+1 -> 36 | B37: Борис | C37: А 4049 | D37: Orbi | E37: Шартава | F37: Студия | G37: https://airbnb.com/h/orbia4049 | H37: 1 | I37: 50000
A38: =A37+1 -> 37 | B38: Борис | C38: C 732 | D38: Orbi | E38: Шартава | F38: Студия | H38: 1 | I38: 50000
A39: =A38+1 -> 38 | B39: Борис | C39: С 2756 | D39: Orbi | E39: Шартава | F39: Студия | G39: https://airbnb.com/h/orbic2756 | H39: 1 | I39: 50000
A40: =A39+1 -> 39 | B40: Борис | C40: D 1321 | D40: Orbi | E40: Шартава | F40: Студия | G40: https://airbnb.com/h/orbid1321 | H40: 1 | I40: 50000
A41: =A40+1 -> 40 | B41: Борис | C41: D2 1625 | D41: Orbi | E41: Шартава | F41: 1+1 | G41: https://airbnb.com/h/orbid21625 | H41: 2 | I41: 70000
A42: =A41+1 -> 41 | B42: Борис | C42: D2 3216 | D42: Orbi | E42: Шартава | F42: 1+1 | G42: https://airbnb.com/h/orbid23216 | H42: 2 | I42: 70000
A43: =A42+1 -> 42 | B43: Борис | C43: D1 3902 | D43: Orbi | E43: Шартава | F43: 1+1 | G43: https://airbnb.com/h/orbid1-3902 | H43: 2 | I43: 100000
A44: =A43+1 -> 43 | B44: Борис | C44: D2 503 | D44: Orbi | E44: Шартава | F44: 1+1 | G44: https://airbnb.com/h/orbid2503 | H44: 2 | I44: 70000
A45: =A44+1 -> 44 | B45: Дина | C45: CM 1604 | D45: CM | E45: Шартава | F45: 1+1 | G45: https://airbnb.com/h/m1604 | H45: 2 | I45: 130000
A46: =A45+1 -> 45 | B46: Дина | C46: CM 1606 | D46: CM | E46: Шартава | F46: Студия | G46: https://airbnb.com/h/m1606 | H46: 1 | I46: 80000
A47: =A46+1 -> 46 | B47: Дина | C47: CM 1931 | D47: CM | E47: Шартава | F47: Студия | G47: https://airbnb.com/h/mar1931 | H47: 1 | I47: 80000
A48: =A47+1 -> 47 | B48: Дина | C48: CM 1304 | D48: CM | E48: Шартава | F48: 1+1 | G48: http://airbnb.com/h/cm1304 | H48: 2 | I48: 130000
A49: =A48+1 -> 48 | B49: Дина | C49: CM 1327 | D49: CM | E49: Шартава | F49: 1+1 | G49: http://airbnb.com/h/cm1327 | H49: 2 | I49: 130000
A50: =A49+1 -> 49 | B50: Дина | C50: Int 2905 | D50: Int | E50: Шартава | F50: 1+1 | G50: https://airbnb.com/h/inta2905 | H50: 2 | I50: 100000
... A52: =A51+1 -> 51 | B52: Дина | C52: Шар 2505 | D52: АГ | E52: Шартава | F52: Студия | G52: https://airbnb.com/h/sh8 | H52: 1 | I52: 70000
A53: =A52+1 -> 52 | B53: Дина | C53: Шар 2708 | D53: АГ | E53: Шартава | F53: 1+1 | H53: 2 | I53: 110000
A54: =A53+1 -> 53 | B54: Дина | C54: Багратиони | D54: АГ | E54: Шартава | F54: 1+2 | G54: https://airbnb.com/h/bg227 | H54: 3 | I54: 110000
A55: =A54+1 -> 54 | B55: Юлия | C55: Думбадзе | E55: Старый город | F55: 1+1 | G55: https://airbnb.com/h/dz12-17 | H55: 2 | I55: 150000
A56: =A55+1 -> 55 | B56: Юлия | C56: 26 мая 52 - 813 | E56: Старый город | F56: 1+1 | G56: airbnb.com/h/26m813 | H56: 2 | I56: 110000
A57: =A56+1 -> 56 | B57: Юлия | C57: PT2604 | E57: Старый город | F57: Студия | G57: https://airbnb.com/h/porta2604 | H57: 1 | I57: 130000
A58: =A57+1 -> 57 | B58: Юлия | C58: PT2704 | E58: Старый город | F58: Студия | G58: https://airbnb.com/h/porta2704 | H58: 1 | I58: 130000
A59: =A58+1 -> 58 | B59: Юлия | C59: PT3604 | E59: Старый город | F59: Студия | H59: 1 | I59: 130000
A60: =A59+1 -> 59 | B60: Дина | C60: NW 2-5 | D60: NW | E60: Некст | F60: 1+1 | G60: https://airbnb.com/h/nw205 | H60: 2 | I60: 170000
A61: =A60+1 -> 60 | B61: Дина | C61: NW 3-7 | D61: NW | E61: Некст | F61: Студия | G61: https://airbnb.com/h/nw3-7 | H61: 1 | I61: 60000
A62: =A61+1 -> 61 | B62: Дина | C62: NA 3-16 | D62: NA | E62: Некст | F62: Студия | H62: 1 | I62: 60000
A63: =A62+1 -> 62 | B63: Юлия | C63: MZ 718 | D63: MZ | E63: Мзиури | F63: Студия | G63: https://airbnb.com/h/mz718 | H63: 1 | I63: 80000
A64: =A63+1 -> 63 | B64: Юлия | C64: MZ 913 | D64: MZ | E64: Мзиури | F64: Студия | G64: https://airbnb.com/h/mz913 | H64: 1 | I64: 80000
A65: =A64+1 -> 64 | B65: Юлия | C65: MZ 1408 | D65: MZ | E65: Мзиури | F65: 1+1 | G65: https://airbnb.com/h/mzc1408 | H65: 2 | I65: 120000
A66: =A65+1 -> 65 | B66: Юлия | C66: MZ А 1113 | D66: MZ | E66: Мзиури | F66: 1+1 | G66: http://airbnb.com/h/mza1113 | H66: 2 | I66: 120000
A67: =A66+1 -> 66 | B67: Юлия | C67: MZ C 511 | D67: MZ | E67: Мзиури | F67: Студия | G67: http://airbnb.com/h/mz511 | H67: 1 | I67: 80000
A68: =A67+1 -> 67 | B68: Дарья | C68: Пиросмани 162 | D68: PIR | E68: Ост | F68: Студия | H68: 1 | I68: 80000
A69: =A68+1 -> 68 | B69: Дарья | C69: Пиросмани 181 | D69: PIR | E69: Ост | F69: 1+2 | G69: https://airbnb.com/h/pr181 | H69: 3 | I69: 120000
A70: =A69+1 -> 69 | B70: Юлия | C70: Pollo 2-2 | D70: Villa | E70: Ост | F70: Дом | H70: 4 | I70: 250000
A71: =A70+1 -> 70 | B71: Юлия | C71: Pollo 3-5 | D71: Villa | E71: Ост | F71: Дом | G71: http://airbnb.com/h/polo2-2 | H71: 4 | I71: 250000
A72: =A71+1 -> 71 | B72: Юлия | C72: Polo 4-12 | D72: Villa | E72: Ост | F72: Дом | H72: 4 | I72: 250000
A73: =A72+1 -> 72 | B73: Юлия | C73: Вилла Ева | D73: Villa | F73: Дом | G73: https://airbnb.com/h/eva155 | H73: 3
A74: =A73+1 -> 73 | B74: Юлия | C74: шартава 16/18 | D74: АГ | E74: Шартава | F74: Студия | H74: 1
A75: =A74+1 -> 74 | C75: DL 11-1112 | D75: DL | F75: Студия | G75: https://airbnb.com/h/dl-11-1112 | H75: 1 | I75: 80000
A76: =A75+1 -> 75 | C76: DL 11-1305 | D76: DL | F76: 1+1 | G76: https://airbnb.com/h/dl1305 | H76: 2 | I76: 160000
A77: =A76+1 -> 76 | C77: DL 14-516 | D77: DL | F77: 1+1 | G77: https://airbnb.com/h/dl14-516 | H77: 2 | I77: 160000
A78: =A77+1 -> 77 | C78: DL 14-702 | D78: DL | F78: 1+1 | G78: https://airbnb.com/h/dl14-702 | H78: 2 | I78: 160000
A79: =A78+1 -> 78 | C79: DL 14-1214 | D79: DL | F79: Студия | G79: https://airbnb.com/h/dl14-1214 | H79: 1 | I79: 80000
A80: =A79+1 -> 79 | C80: 14-411 | D80: DL | F80: Студия/твин | G80: https://airbnb.com/h/DL-14-411 | H80: 1 | I80: 80000
A81: =A80+1 -> 80 | C81: DL 4-09 | D81: DL | F81: Студия | G81: https://airbnb.com/h/dl4-09 | H81: 1 | I81: 80000
A82: =A81+1 -> 81 | C82: DL14-518 | D82: DL | F82: Студия | G82: https://airbnb.com/h/dl14-518 | H82: 1 | I82: 80000
A83: =A82+1 -> 82 | C83: DL14-1405 | D83: DL | F83: 1+1 | G83: https://airbnb.com/h/dl14-1405 | H83: 2 | I83: 160000
A84: =A83+1 -> 83 | C84: DL 14-505 | D84: DL | F84: Студия/твин | G84: https://airbnb.com/h/dl14-505 | H84: 1 | I84: 80000
A85: =A84+1 -> 84 | C85: DL 14-1614 | D85: DL | F85: Студия | H85: 1 | I85: 80000
A86: =A85+1 -> 85 | C86: DL 14-1710 | D86: DL | F86: Студия | G86: https://airbnb.com/h/dl14-1710 | H86: 1 | I86: 80000
A87: =A86+1 -> 86 | C87: DL14-305 | D87: DL | F87: Студия | G87: https://airbnb.com/h/dl14-305 | H87: 1 | I87: 80000
A88: =A87+1 -> 87 | C88: DL14-501-502 | D88: DL | F88: 1+1 | G88: https://airbnb.com/h/dl501-502 | H88: 2 | I88: 160000
A89: =A88+1 -> 88 | C89: DL7-16 | D89: DL | F89: 1+2 с террасой | G89: https://airbnb.com/h/dl7-16 | H89: 3 | I89: 250000
A90: =A89+1 -> 89 | C90: DL 13-206 | D90: DL | F90: Студия на 4х | G90: https://airbnb.com/h/dl13-206 | H90: 1 | I90: 140000
A91: =A90+1 -> 90 | C91: DL 13-201 | D91: DL | F91: Студия на 4х | H91: 1 | I91: 140000
A92: =A91+1 -> 91 | C92: DL 13-709 | D92: DL | F92: Студия на 4х | G92: https://airbnb.com/h/dl13-709 | H92: 1 | I92: 140000
A93: =A92+1 -> 92 | C93: DL 13-703 | D93: DL | F93: 1+1 | G93: https://airbnb.com/h/dl13-703 | H93: 2 | I93: 160000
A94: =A93+1 -> 93 | C94: DL 13-1006 | D94: DL | F94: 1+1 | H94: 2 | I94: 160000
A95: =A94+1 -> 94 | C95: DL 13-1106 | D95: DL | F95: 1+1 | H95: 2 | I95: 160000
A96: =A95+1 -> 95 | C96: DL 14-506 | D96: DL | F96: Студия | G96: https://airbnb.com/h/dl14-506 | H96: 1 | I96: 160000
A97: =A96+1 -> 96 | B97: Светлана | C97: TGB195 | D97: TG | F97: 1+1 | G97: https://airbnb.com/h/tgb195 | H97: 2 | I97: 90000
A98: =A97+1 -> 97 | B98: Светлана | C98: TGA2 | D98: TG | F98: 1+1 | G98: https://airbnb.com/h/tg-2a | H98: 2 | I98: 90000
A99: =A98+1 -> 98 | B99: Светлана | C99: TGA9 | D99: TG | F99: 1+1 | G99: https://airbnb.com/h/tg-9a | H99: 2 | I99: 90000
A100: =A99+1 -> 99 | B100: Светлана | C100: TGB3 | D100: TG | F100: Студия | G100: https://airbnb.com/h/tg-b3 | H100: 1 | I100: 60000
A136: =A60+1 -> 60 | B136: Дина | C136: NW 4-9 | D136: NW | E136: Некст | F136: Студия | G136: https://airbnb.com/h/nw409 | H136: 1 | I136: 60000
A137: =A136+1 -> 61 | B137: Дина | C137: NW 4-10 | D137: NW | E137: Некст | F137: Студия | G137: https://airbnb.com/h/nw410 | H137: 1 | I137: 60000
A138: =A137+1 -> 62 | B138: Дина | C138: NW 10-6 | D138: NW | E138: Некст | F138: Студия | G138: https://airbnb.com/h/nw10-6 | H138: 1 | I138: 60000
A140: =#REF!+1 -> #REF! | C140: TGA1 | D140: TG | F140: 1+2 | G140: https://airbnb.com/h/tg-1a | H140: 3 | I140: 120000
A141: =A98+1 -> 98 | C141: TGA3 | D141: TG | F141: Студия | G141: https://airbnb.com/h/tg-3a | H141: 1 | I141: 60000
A142: =A141+1 -> 99 | C142: TGA4 | D142: TG | F142: 1+1 | G142: https://airbnb.com/h/tg-4a | H142: 2 | I142: 90000
A143: =A142+1 -> 100 | C143: TGA5 | D143: TG | F143: Студия | G143: https://airbnb.com/h/tg-5a | H143: 1 | I143: 60000
A144: =A143+1 -> 101 | C144: TGA6 | D144: TG | F144: Студия | G144: https://airbnb.com/h/tg-6a | H144: 1 | I144: 60000
A145: =A144+1 -> 102 | C145: TGA7 | D145: TG | F145: 1+1 | G145: https://airbnb.com/h/tg-7a | H145: 2 | I145: 90000
A146: =A145+1 -> 103 | C146: TGA8 | D146: TG | F146: Студия | G146: https://airbnb.com/h/tg-8a | H146: 1 | I146: 60000
A147: =A99+1 -> 99 | C147: TGA10 | D147: TG | F147: 1+2 | G147: https://airbnb.com/h/tg-10a | H147: 3 | I147: 120000
A148: =A147+1 -> 100 | C148: TGB1 | D148: TG | F148: 1+1 | G148: https://airbnb.com/h/tg-1b | H148: 2 | I148: 90000
A149: =A148+1 -> 101 | C149: TGB2 | D149: TG | F149: Студия | G149: https://airbnb.com/h/tg-2b | H149: 1 | I149: 60000
A150: =A100+1 -> 100 | C150: TGB4 | D150: TG | F150: Студия | G150: https://airbnb.com/h/tg-4b | H150: 1 | I150: 60000
A151: =A150+1 -> 101 | C151: TGB5 | D151: TG | F151: 1+1 | G151: https://airbnb.com/h/tg-5b | H151: 2 | I151: 90000
A152: =A151+1 -> 102 | C152: TGB6 | D152: TG | F152: 1+1 | G152: https://airbnb.com/h/tg-6b | H152: 2 | I152: 90000
A153: =A152+1 -> 103 | C153: TGB7 | D153: TG | F153: 1+1 | G153: https://airbnb.com/h/tg-7b | H153: 2 | I153: 90000
A154: =A153+1 -> 104 | C154: TGB8 | D154: TG | F154: 1+1 | G154: https://airbnb.com/h/tg-8b | H154: 2 | I154: 90000
...

Sheet план 
D1: оборот по юниту
D2: 2026 год | E2: янв. | F2: февр. | G2: мар. | H2: апр. | I2: мая | J2: июн. | K2: июл. | L2: авг. | M2: сент. | N2: окт. | O2: нояб. | P2: дек.
A3: ='1. Справочник'!C2 -> WS В 503 | B3: ='1. Справочник'!D2 -> WS | C3: ='1. Справочник'!F2 -> 1+1
A4: ='1. Справочник'!C3 -> WS F 907 | B4: ='1. Справочник'!D3 -> WS | C4: ='1. Справочник'!F3 -> Студия
A5: ='1. Справочник'!C4 -> WS В 212 | B5: ='1. Справочник'!D4 -> WS | C5: ='1. Справочник'!F4 -> 1+2
A6: ='1. Справочник'!C5 -> WS В 1510 | B6: ='1. Справочник'!D5 -> WS | C6: ='1. Справочник'!F5 -> Студия
A7: ='1. Справочник'!C6 -> WS В 807 | B7: ='1. Справочник'!D6 -> WS | C7: ='1. Справочник'!F6 -> Студия
A8: ='1. Справочник'!C7 -> WS E 1202 | B8: ='1. Справочник'!D7 -> WS | C8: ='1. Справочник'!F7 -> 1+1
A9: ='1. Справочник'!C8 -> WS A 409 | B9: ='1. Справочник'!D8 -> WS | C9: ='1. Справочник'!F8 -> Студия
A10: ='1. Справочник'!C9 -> WS A 608 | B10: ='1. Справочник'!D9 -> WS | C10: ='1. Справочник'!F9 -> Студия
A11: ='1. Справочник'!C10 -> WS A907 | B11: ='1. Справочник'!D10 -> WS | C11: ='1. Справочник'!F10 -> Студия/твин
A12: ='1. Справочник'!C11 -> WS Е804 | B12: ='1. Справочник'!D11 -> WS | C12: ='1. Справочник'!F11 -> Студия/твин
A13: ='1. Справочник'!C12 -> WS E704 | B13: ='1. Справочник'!D12 -> WS | C13: ='1. Справочник'!F12 -> Студия
A14: ='1. Справочник'!C13 -> WS A805 | B14: ='1. Справочник'!D13 -> WS | C14: ='1. Справочник'!F13 -> Студия
... A119: ='1. Справочник'!C118 | B119: ='1. Справочник'!D118 | C119: ='1. Справочник'!F118
A120: ='1. Справочник'!C119
A121: ='1. Справочник'!C120
A122: ='1. Справочник'!C121
A123: ='1. Справочник'!C122
A124: ='1. Справочник'!C123
A125: ='1. Справочник'!C124
A126: ='1. Справочник'!C125
A127: ='1. Справочник'!C126
A128: ='1. Справочник'!C127
A129: ='1. Справочник'!C128
A130: ='1. Справочник'!C129

Sheet 3. Инфо
A1: менеджер ответственный | C1: номер | D1: тип апартамента | E1: Стратегия | F1: Комплектация | G1: "Как добраться" | H1: airbnb | I1: букинг | J1: суточно | K1: Островок | L1: Газ | M1: Элек-во | N1: Вода | O1: Интернет | P1: Тариф | R1: р/с для перевода ДС | S1: Last First Name | T1: Банк / Крипта
A2: ='1. Справочник'!B2 -> Марина | B2: 1 | C2: ='1. Справочник'!C2 -> WS В 503 | D2: ='1. Справочник'!F2 -> 1+1 | E2: 70/30 | G2: How to find White Sails В503 and rules.docx | H2: https://www.airbnb.ru/rooms/941249668263786208?guests=1&adults=1&s=67&unique_share_id=6a551af0-04fb-44fa-b61c-716ede11e4e8 | I2: https://www.booking.com/Share-xqLLfZL | J2: https://sutochno.ru/front/searchapp/detail/1590689?guests_adults=2&id=1&SW.lat=55.142221&SW.lng=36.803259&NE.lat=56.021281&NE.lng=37.96779 | K2: https://ostrovok.ru/hotel/georgia/batumi/mid13343877/white_sails_b_503_apartments/ | L2: - | M2: 6011234992 | N2: 292/5b-503 | O2: 422209727 | P2: 33 | Q2: 51895127 | R2: GE93BG0000000594027233 | S2: Vladimir Kirakosyan | T2: BOG | Y2: минус | Z2: крипта | AA2: минус
A3: ='1. Справочник'!B3 -> Марина | B3: =B2+1 -> 2 | C3: ='1. Справочник'!C3 -> WS F 907 | D3: ='1. Справочник'!F3 -> Студия | E3: 70/30 | G3: How to find White Sails F907 and rules | H3: https://airbnb.ru/h/wsf907 | I3: https://www.booking.com/Share-xqLLfZL | J3: https://sutochno.ru/front/searchapp/detail/1597202?host_id=11237896&host_device=app&guest_id=6765771&guests_adults=2&id=1&SW.lat=41.619609051039355&SW.lng=41.589027934829936&NE.lat=41.627530522283585&NE.lng=41.605979495804036 | K3: https://ostrovok.ru/hotel/georgia/batumi/mid13343890/white_sails_f_907_apartments/ | L3: - | M3: 6011094930 | N3: 292/5F-907 | O3: 422589587 | P3: 42 | Q3: 76054799 | R3: GE49BG0000000540073812USD | S3: HAIM ZADEH KEREN | T3: BOG | AA3: 330.45
A4: ='1. Справочник'!B4 -> Марина | B4: =B3+1 -> 3 | C4: ='1. Справочник'!C4 -> WS В 212 | D4: 1+1 | E4: 70/30 | G4: How to find White Sails B212 and rules.docx | H4: https://www.airbnb.ru/rooms/951438840662298607 | I4: https://www.booking.com/Share-xqLLfZL | J4: https://sutochno.ru/front/searchapp/detail/1597785?host_id=11237896&host_device=app&guest_id=6765771&guests_adults=2&id=1&SW.lat=41.62003661276085&SW.lng=41.590182840373934&NE.lat=41.62795803108765&NE.lng=41.607134401348034 | K4: https://ostrovok.ru/hotel/georgia/batumi/mid13343892/white_sails_b_212_apartments/ | L4: - | M4: 6011469600 | N4: 292-5B212 | O4: 422898373 | P4: 38 | Q4: 81875641 | R4: GE35BG0000000538344748USD | S4: KOTLYAROVA EKATERINA | T4: BOG | AA4: 378.4
A5: ='1. Справочник'!B5 -> Марина | B5: =B4+1 -> 4 | C5: ='1. Справочник'!C5 -> WS В 1510 | D5: ='1. Справочник'!F5 -> Студия | E5: 70/30 | G5: How to find White Sails B1510 and rules.docx | H5: https://airbnb.ru/h/wsb1510 | I5: https://www.booking.com/Share-xqLLfZL | J5: https://sutochno.ru/front/searchapp/detail/1651312?guests_adults=2&id=1&SW.lat=41.62003661276085&SW.lng=41.590182840373934&NE.lat=41.62795803108765&NE.lng=41.607134401348034 | K5: https://ostrovok.ru/hotel/georgia/batumi/mid13343884/white_sails_b_1510_apartments/ | L5: - | M5: 6011333411 6011093992 | N5: 292/5b-1510 | O5: 422454408 | P5: 47 | Q5: 76429460 | R5: GE86BG0000000534160414USD | S5: GALKIN DENIS | T5: BOG | AA5: 324.76
A6: ='1. Справочник'!B6 -> Марина | B6: =B5+1 -> 5 | C6: ='1. Справочник'!C6 -> WS В 807 | D6: ='1. Справочник'!F6 -> Студия | E6: 70/30 | F6: В 807. Чек-лист комплектации апартаментов | G6: How to find White Sails B807 and rules | H6: https://ru.airbnb.com/hosting/listings/editor/1557162624121179819/view-your-space | I6: https://www.booking.com/Share-xqLLfZL | L6: - | M6: 6011554481 | N6: 292/5b-807 | O6: 422958722 | P6: 42 | Q6: 76101652 | R6: GE42TB7245045068100007 | T6: ТВС | X6: нет дохода | Y6: нет дохода | Z6: нет дохода | AA6: минус
A7: ='1. Справочник'!B7 -> Марина | B7: =B6+1 -> 6 | C7: ='1. Справочник'!C7 -> WS E 1202 | D7: ='1. Справочник'!F7 -> 1+1 | E7: 70/30 | G7: How to find White Sails E1202 and rules.docx | H7: https://airbnb.com/h/wse1202 | I7: https://www.booking.com/Share-xqLLfZL | J7: https://sutochno.ru/front/searchapp/detail/1778923?guests_adults=2&id=1&SW.lat=41.61946982597882&SW.lng=41.58957055946391&NE.lat=41.62739131445426&NE.lng=41.606522120438036 | K7: https://ostrovok.ru/hotel/georgia/batumi/mid13343880/white_sails_e_1202_apartments/ | L7: - | M7: 6011366441 | N7: 292-5E1202 | O7: 422609023 | P7: 42 | Q7: 49453499 | R7: AE870230000002002749576 | S7: Marcin Szwedzicki | T7: COMMERCIAL BANK OF DUBAI | W7: депозит | Y7: депозит | Z7: депозит | AA7: депозит
A8: ='1. Справочник'!B8 -> Марина | B8: =B7+1 -> 7 | C8: ='1. Справочник'!C8 -> WS A 409 | D8: ='1. Справочник'!F8 -> Студия | E8: 70/30 | G8: How to find White Sails A409 and rules.docx | H8: https://airbnb.ru/h/wsa409 | I8: https://www.booking.com/Share-xqLLfZL | J8: https://sutochno.ru/front/searchapp/detail/1766637?guests_adults=2&id=1&SW.lat=41.6206702075146&SW.lng=41.58953121951294&NE.lat=41.62859154742334&NE.lng=41.60648278048706 | K8: https://ostrovok.ru/hotel/georgia/batumi/mid13343888/white_sails_a_409_apartments/ | L8: - | M8: 6011394071 | N8: 292/5a-409 | O8: 422464178 | P8: 42 | Q8: 24980033 | R8: GE19BG0000000538726828USD | S8: ALEKSANIAN DAVID | T8: BOG | AA8: 308.79
A9: ='1. Справочник'!B9 -> Марина | B9: =B8+1 -> 8 | C9: ='1. Справочник'!C9 -> WS A 608 | D9: Студия | E9: 70/30 | G9: How to find White Sails A608 and rules.docx | H9: https://airbnb.com/h/wsa608 | I9: https://www.booking.com/hotel/ge/batumi-boulevard-resort.html | J9: https://sutochno.ru/front/searchapp/detail/1803934?guests_adults=2&occupied=2024-06-25;2024-06-26&id=1&term=%D0%A7%D0%B0%D0%BA%D0%B2%D0%B8&SW.lat=41.62026684936153&SW.lng=41.58997825523394&NE.lat=41.62818823919277&NE.lng=41.606929816208066 | K9: https://ostrovok.ru/hotel/georgia/batumi/mid13343889/white_sails_a_608_apartments/ | L9: - | M9: 6011095331 | N9: 292/5a-608 | O9: 422373250 | P9: 42 | Q9: 58567815 | R9: GE30TB7746745064400002 | S9: IRINA POTRIASAEVA | T9: ТВС | Y9: минус | AA9: нет дохода
A10: ='1. Справочник'!B10 -> Марина | B10: =B9+1 -> 9 | C10: ='1. Справочник'!C10 -> WS A907 | D10: ='1. Справочник'!F10 -> Студия/твин | E10: 70/30 | G10: How to find White Sails A907 and rules.docx | H10: https://airbnb.com/h/wsa907 | I10: https://www.booking.com/hotel/ge/batumi-boulevard-resort.html | J10: https://sutochno.ru/front/searchapp/detail/1803966?guests_adults=2&occupied=2024-06-25;2024-06-26&id=1&term=%D0%A7%D0%B0%D0%BA%D0%B2%D0%B8&SW.lat=41.62026684936153&SW.lng=41.58997825523394&NE.lat=41.62818823919277&NE.lng=41.606929816208066 | K10: https://ostrovok.ru/hotel/georgia/batumi/mid13343891/white_sails_a_907_apartments/ | L10: - | M10: 6011092200 | N10: 292/5a-907 | O10: 422355072 | P10: 42 | Q10: 86197762 | R10: GE45TB7927545064400004 | S10: Semen Vesterman | T10: TBC | AA10: депозит
A11: ='1. Справочник'!B11 -> Марина | B11: =B10+1 -> 10 | C11: ='1. Справочник'!C11 -> WS Е804 | D11: ='1. Справочник'!F11 -> Студия/твин | E11: 70/30 | G11: https://docs.google.com/document/d/1ac2Gc2NDkT8_9VcbV86ujTo33jBEP-25WiW8o3YOKZw/edit?tab=t.0 | H11: https://airbnb.com/h/wse804 | I11: https://www.booking.com/hotel/ge/batumi-boulevard-resort.html | J11: https://sutochno.ru/front/searchapp/detail/1804205?guests_adults=2&occupied=2024-06-25;2024-06-26&id=1&term=%D0%A7%D0%B0%D0%BA%D0%B2%D0%B8&SW.lat=41.62026684936153&SW.lng=41.58997825523394&NE.lat=41.62818823919277&NE.lng=41.606929816208066 | K11: https://ostrovok.ru/hotel/georgia/batumi/mid13343885/white_sails_e_804_apartments/ | L11: - | M11: 6011093302 | N11: 292/5е-804 | O11: 422681834 | P11: 42 | Q11: 22139297 | R11: GE76BG0000000161495421USD | S11: TELESHEVA ANTONINA | T11: BOG | AA11: минус
A12: ='1. Справочник'!B12 -> Марина | B12: =B11+1 -> 11 | C12: ='1. Справочник'!C12 -> WS E704 | D12: ='1. Справочник'!F12 -> Студия | E12: 70/30 | G12: How to find White Sails E704 and rules.docx | H12: https://airbnb.com/h/wse704 | I12: https://www.booking.com/hotel/ge/batumi-boulevard-resort.html | J12: https://sutochno.ru/front/searchapp/detail/1804231?guests_adults=2&occupied=2024-06-25;2024-06-26&id=1&term=%D0%A7%D0%B0%D0%BA%D0%B2%D0%B8&SW.lat=41.62026684936153&SW.lng=41.58997825523394&NE.lat=41.62818823919277&NE.lng=41.6069298162080660 | K12: https://ostrovok.ru/hotel/georgia/batumi/mid13343894/white_saile_e_704_apartments/ | L12: - | M12: 6011320361 | N12: 292-5e704 | O12: 422450253 | P12: 42 | Q12: 45539364 | R12: крипта / рубли | Z12: минус | AA12: депозит
A13: ='1. Справочник'!B13 -> Марина | B13: =B12+1 -> 12 | C13: ='1. Справочник'!C13 -> WS A805 | D13: ='1. Справочник'!F13 -> Студия | E13: 70/30 | G13: How to find White Sails A805 and rules | H13: https://ru.airbnb.com/hosting/listings/editor/1445607361971672990/view-your-space | I13: https://www.booking.com/hotel/ge/batumi-boulevard-resort.html | J13: https://sutochno.ru/front/searchapp/detail/2084488?price_per=1&guests_adults=2&id=1&SW.lat=41.61985615713882&SW.lng=41.58907721951295&NE.lat=41.627777597799884&NE.lng=41.60602878048705 | L13: - | M13: 6011182890 | N13: 292-5a805 | O13: 422532923 | P13: 42 | Q13: 41406017 | R13: наличные | V13: депозит | W13: депозит | X13: кэш | Y13: депозит | Z13: депозит | AA13: депозит
A14: ='1. Справочник'!B14 -> Марина | B14: =B13+1 -> 13 | C14: ='1. Справочник'!C14 -> WS F1103 | D14: ='1. Справочник'!F14 -> 1+1 | E14: 70/30 | G14: How to find White Sails F1103 and rules | H14: https://ru.airbnb.com/hosting/listings/editor/1448295525878557615/view-your-space | I14: https://www.booking.com/hotel/ge/batumi-boulevard-resort.html | J14: https://sutochno.ru/front/searchapp/detail/2091761?price_per=1&guests_adults=2&id=1&SW.lat=55.142221&SW.lng=36.803259&NE.lat=56.021281&NE.lng=37.96779 | L14: - | M14: 6011093692 | N14: 292/5F-1103 | O14: 422094809 | P14: 42 | Q14: 72724508 | R14: GE36BG0000000103039770 | S14: EGORENKOV IGOR | T14: BOG | Z14: минус | AA14: 464.94
A15: ='1. Справочник'!B15 -> Марина | B15: =B14+1 -> 14 | C15: ='1. Справочник'!C15 -> WS F1008 | D15: ='1. Справочник'!F15 -> Студия | E15: 70/30 | F15: F 1008. Чек-лист комплектации апартаментов | G15: How to find White Sails F1008 and rules | H15: https://ru.airbnb.com/hosting/listings/editor/1568661924032989113/view-your-space | I15: https://www.booking.com/hotel/ge/batumi-boulevard-resort.html | J15: https://sutochno.ru/front/searchapp/detail/2209519?host_id=11237896&host_device=PC&guest_id= | L15: - | M15: 6011093471 | N15: 292/5F-1008 | O15: 422284141 | P15: 42 | Q15: 69056665 | R15: GE34BG0000000607885133 | S15: HAKMON MOSHE | T15: BOG | Z15: минус | AA15: 103.25 | AB15: 103.25
A16: ='1. Справочник'!B16 -> Светлана | B16: =B15+1 -> 15 | C16: ='1. Справочник'!C16 -> BV1318 | D16: ='1. Справочник'!F16 -> Студия | E16: 70/30 | G16: How to find BV B 1318 and rules | H16: https://airbnb.ru/h/bvb1318 | I16: https://www.booking.com/hotel/ge/batumi-view-first-line.html | J16: https://sutochno.ru/front/searchapp/detail/1917618?host_id=11237896&host_device=PC&guest_id= | K16: https://ostrovok.ru/hotel/georgia/batumi/mid13343883/batumi_view_1318_apartments/ | L16: - | R16: GE66BG0000000540007934USD | S16: SLEPAK DMITRI | T16: BOG | AA16: 125.65
A17: ='1. Справочник'!B17 -> Светлана | B17: =B16+1 -> 16 | C17: ='1. Справочник'!C17 -> BV A 100 | D17: Студия | E17: 70/30 | F17: Чек-лист комплектации апартаментов BV A 100 | G17: How to find BV A 0514 and rules | H17: airbnb.ru/h/bv0514 | I17: https://www.booking.com/hotel/ge/batumi-view-first-line.ru.html?label=gen173nr-10CAsoUkIWYmF0dW1pLXZpZXctZmlyc3QtbGluZUgzWARoUogBAZgBM7gBF8gBDNgBA-gBAfgBAYgCAagCAbgCpqTdxwbAAgHSAiQ5OGI5MGE5OS04MzhkLTRjNTctOTUzNC05MTRmYTU3MDU3OTPYAgHgAgE&sid=a1de48d8e17c657d54e265ede55366e1&dist=0&keep_landing=1&sb_price_type=total&type=total& | J17: https://sutochno.ru/front/searchapp/detail/2180915 | L17: - | M17: 6011364450 | N17: 292/8a-100 | O17: 422313986 | P17: 33 | R17: GE72CD0360000033931999 | S17: MiIKHAIL POPOV | T17: Кредо | Y17: минус | AA17: 545.43 | AB17: 545.43
A18: ='1. Справочник'!B18 -> Светлана | B18: =B17+1 -> 17 | C18: ='1. Справочник'!C18 -> Steps1123 | D18: ='1. Справочник'!F18 -> Студия | E18: 70/30 | G18: How to find Steps (apart 1123) | H18: http://airbnb.com/h/steps1123 | I18: https://www.booking.com/Share-KnAK8p2 | J18: https://sutochno.ru/front/searchapp/detail/1960399?host_id=11237896&host_device=app&guest_id= | L18: - | M18: 6011507471 | N18: 594/2-1123 | O18: 307469420 | R18: наличные | U18: депозит | V18: депозит | W18: депозит | X18: депозит | Y18: депозит | Z18: депозит | AA18: депозит
A19: ='1. Справочник'!B20 -> Светлана | B19: =B18+1 -> 18 | C19: ='1. Справочник'!C19 -> WH 176 | D19: ='1. Справочник'!F19 -> Студия | E19: 70/30 | F19: WH 176. Чек-лист комплектации апартаментов | G19: How to find White Houth 176 .docx | H19: https://ru.airbnb.com/hosting/listings/editor/1558574343606488996/details/photo-tour | J19: https://sutochno.ru/front/searchapp/detail/2197711? | L19: 2117437984 | M19: 6011510141 | N19: 578-82176a | O19: 309596293 | Q19: 79222959246 | R19: GE79CD0360000037266442 | S19: PETROV EVGENII | T19: Credo Bank | Z19: депозит | AB19: 476.31
A20: ='1. Справочник'!B21 -> Светлана | B20: =B19+1 -> 19 | C20: ='1. Справочник'!C20 -> OBT 2906 | D20: ='1. Справочник'!F20 -> Студия | E20: 70/30 | F20: OBT. Чек-лист комплектации апартаментов | G20: How to find OBT 2906 .docx | H20: airbnb.ru/h/obt2906 | I20: https://www.booking.com/hotel/ge/beach-tower-app-montreux.ru.html?label=gen173nr-10CAsoUkIYYmVhY2gtdG93ZXItYXBwLW1vbnRyZXV4SDNYBGhSiAEBmAEzuAEXyAEM2AED6AEB-AEBiAIBqAIBuALnnIDKBsACAdICJDE5ZGY4NDQ5LTgyMDMtNGFhYi1hODYzLTgwYTllZDUyODVlZtgCAeACAQ&sid=a1de48d8e17c657d54e265ede55366e1&dist=0&keep_landing=1&sb_price_type=total&type=total& | J20: https://sutochno.ru/front/searchapp/detail/2246324? | M20: 6010924680 | N20: 291/57-2906 | O20: 422124810 | P20: 47 | R20: GE35BG0000000609340697 | S20: Stanislav Kogan | T20: BOG | AA20: минус
A21: ='1. Справочник'!B22 -> Светлана | B21: =B20+1 -> 20 | C21: ='1. Справочник'!C21 -> OBT 2908 | D21: ='1. Справочник'!F21 -> Студия | E21: 70/30 | G21: How to find OBT 2908 .docx | H21: airbnb.ru/h/obt2908 | J21: https://sutochno.ru/front/searchapp/detail/2247029? | M21: 6010924822 | N21: 291/57-2908 | O21: 422556559 | P21: 42 | AA21: минус
A22: ='1. Справочник'!B23 -> Светлана | B22: =B21+1 -> 21 | C22: ='1. Справочник'!C22 -> OBT 2910 | D22: ='1. Справочник'!F22 -> Студия | E22: 70/30 | G22: How to find OBT 2910 .docx | H22: airbnb.ru/h/obt2910 | M22: 6010924972 | N22: 291/57-2910 | O22: 422196746 | P22: 50 | AA22: минус
A23: ='1. Справочник'!B24 -> Светлана | B23: =B22+1 -> 22 | C23: ='1. Справочник'!C23 -> BV A 133 (0715) | D23: ='1. Справочник'!F23 -> 1+1 | E23: 70/30 | F23: ОБЩИЙ. Чек-лист комплектации апартаментов | G23: How to find BV A 133 and rules.docx | H23: airbnb.ru/h/bva134 | I23: https://www.booking.com/hotel/ge/batumi-view-first-line.html | J23: https://sutochno.ru/front/searchapp/detail/2239413? | M23: 6011385862 | N23: 292-8a133 | O23: 422424820 | P23: 42 | T23: TBC | AA23: нет дохода
A24: ='1. Справочник'!B25 -> Светлана | B24: =B23+1 -> 23 | C24: ='1. Справочник'!C24 -> BV A 134 (0713) | D24: ='1. Справочник'!F24 -> 1+1 | E24: 70/30 | G24: How to find BV А 134 and rules.docx | H24: airbnb.ru/h/bva134 | J24: https://sutochno.ru/front/searchapp/detail/2239413 | M24: 6011385011 | N24: 292/8a-134 | O24: 422860425 | P24: 33 | R24: GE67BG0000000537963544 | S24: Bar genkin | T24: BOG | AA24: нет дохода
A25: ='1. Справочник'!B26 -> Светлана | B25: =B24+1 -> 24 | C25: ='1. Справочник'!C25 -> BV A 144 (0708) | D25: ='1. Справочник'!F25 -> 1+1 | E25: 70/30 | G25: How to find BV A144 and rules.docx | H25: airbnb.ru/h/bva144 | J25: https://sutochno.ru/front/searchapp/detail/2226291 | M25: 6011384782 | N25: 292/8a-144 | O25: 422288011 | P25: 33 | R25: GE30BG0000000538167328 | S25: DMITRI KORYTNYI | T25: BOG | AA25: нет дохода
A26: ='1. Справочник'!B27 -> Светлана | B26: =B25+1 -> 25 | C26: ='1. Справочник'!C26 -> BV A 145 (0710) | D26: ='1. Справочник'!F26 -> 1+1 | E26: 70/30 | G26: How to find BV A145 and rules.docx | H26: airbnb.ru/h/bva145 | J26: https://sutochno.ru/front/searchapp/detail/2226325 | M26: 6011385142 | O26: 422452474 | P26: 33 | R26: GE49BG0000000538297063 | S26: TOMER EZRA | T26: BOG | AA26: нет дохода
A27: ='1. Справочник'!B28 -> Светлана | B27: =B26+1 -> 26 | C27: ='1. Справочник'!C27 -> BV A 147 (0714) | D27: ='1. Справочник'!F27 -> 1+1 | E27: 70/30 | G27: How to find BV A147 and rules.docx | H27: airbnb.ru/h/bva147 | J27: https://sutochno.ru/front/searchapp/detail/2226311 | M27: 6011384741 | N27: 292/8a-147 | O27: 422911036 | P27: 40 | R27: GE82TB7829645068100030 | S27: YOAV EZRA | T27: TBC | AA27: нет дохода
A28: ='1. Справочник'!B29 -> Светлана | B28: =B27+1 -> 27 | C28: ='1. Справочник'!C28 -> BV A 164 (0804) | D28: ='1. Справочник'!F28 -> 1+1 | E28: 70/30 | G28: How to find BV А 164 and rules.docx | H28: airbnb.ru/h/bva164 | J28: https://sutochno.ru/front/searchapp/detail/2242628? | M28: 6011385082 | N28: 292-8a164 | O28: 422242569 | P28: 40 | AA28: нет дохода
A29: ='1. Справочник'!B31 -> Светлана | B29: =B28+1 -> 28 | C29: ='1. Справочник'!C29 -> BV A 225 (1106) | D29: ='1. Справочник'!F29 -> 1+1 | E29: 70/30 | G29: How to find BV А 225 and rules.docx | H29: airbnb.ru/h/bva225 | J29: https://sutochno.ru/front/searchapp/detail/2243833? | M29: 6011384820 | N29: 292/8a-225 | O29: 422638910 | P29: 33 | AA29: нет дохода
A30: ='1. Справочник'!B32 -> Светлана | B30: =B29+1 -> 29 | C30: ='1. Справочник'!C30 -> BV A 210 (1014) | D30: 1+1 | E30: 70/30 | G30: How to find BV А 210 and rules.docx | H30: airbnb.com/h/bva210 | J30: https://sutochno.ru/front/searchapp/detail/2243654? | M30: 6011385172 | N30: 292-8а210 | O30: 422203124 | P30: 33 | R30: GE67BG0000000537963544 | S30: Bar genkin | T30: BOG
A31: ='1. Справочник'!B32 -> Светлана | B31: =B30+1 -> 30 | C31: ='1. Справочник'!C31 -> BV C 137 (0707) | D31: ='1. Справочник'!F31 -> Студия | E31: 70/30 | G31: How to find BV C137 and rules.docx | H31: airbnb.ru/h/bvc137 | J31: https://sutochno.ru/front/searchapp/detail/2226306 | M31: 6011432891 | N31: 292/8g-137 | O31: 422954682 | P31: 33 | R31: GE67BG0000000537963544 | S31: Bar genkin | T31: BOG | AA31: депозит
A32: ='1. Справочник'!B32 -> Светлана | B32: =B31+1 -> 31 | C32: ='1. Справочник'!C32 -> BV C 0505 | D32: Студия | E32: 70/30 | F32: С 0505. Чек-лист комплектации апартаментов | G32: How to find BV C 0505 and rules.docx | H32: airbnb.com/h/bvc0505 | J32: https://sutochno.ru/front/searchapp/detail/2245011? | M32: 6011372062 | N32: 292/8g-91 | O32: 422988423 | P32: 33 | R32: GE39CD0360000055892617 | S32: DENIS SHMYGLENKO | T32: Кредо
A33: ='1. Справочник'!B33 -> Светлана | B33: =B32+1 -> 32 | C33: ='1. Справочник'!C33 -> MC A 708 | D33: Студия | E33: 70/30 | F33: A 708 Metro Чек-лист комплектации апартаментов | G33: How to find MC A 708 and rules.docx | H33: airbnb.com/h/mca708
A34: ='1. Справочник'!B69 -> Дарья | B34: =B33+1 -> 33 | C34: ='1. Справочник'!C69 -> Пиросмани 181 | D34: ='1. Справочник'!F69 -> 1+2 | E34: 80/20 | G34: How to find Pirosmani 18d (apart 181) | H34: https://airbnb.ru/h/pr181 | K34: https://ostrovok.ru/hotel/georgia/batumi/mid13343964/pirosmani_181_apartments/ | L34: 1114390195 | M34: 6010839262 | N34: 222/18d-181 | O34: 91433115 | Q34: 013525 | R34: GE31TB7881545061200004 | S34: Silin Konstantin | T34: TBC | W34: кэш | AA34: 2573.79 | AB34: 2573.79
A35: ='1. Справочник'!B70 -> Юлия | B35: =B34+1 -> 34 | C35: ='1. Справочник'!C70 -> Pollo 2-2 | D35: ='1. Справочник'!F70 -> Дом | E35: 70/30 | G35: How to find Polo Villas 2-2 and rules | H35: http://airbnb.com/h/polo2-2 | J35: https://sutochno.ru/front/searchapp/detail/1988547?price_per=1&guests_adults=2&id=1&SW.lat=41.60788298563873&SW.lng=41.596723453628925&NE.lat=41.615805907996766&NE.lng=41.613675014603054 | L35: 002117363394 | M35: 6011482811 | N35: 610/30-2 | O35: 422793459 | P35: 59 | R35: GE90BG0000000539650445USD | S35: POPOV EVGENY | T35: BOG | AA35: 2333
A36: ='1. Справочник'!B71 -> Юлия | B36: =B35+1 -> 35 | C36: ='1. Справочник'!C71 -> Pollo 3-5 | D36: ='1. Справочник'!F71 -> Дом | E36: 70/30 | G36: How to find Polo Villas 3-5 and rules | L36: 002117363429 | M36: 6011482800 | N36: 610/30-5 | O36: 422524555 | P36: 91
A37: ='1. Справочник'!B72 -> Юлия | B37: =B36+1 -> 36 | C37: ='1. Справочник'!C72 -> Polo 4-12 | D37: ='1. Справочник'!F72 -> Дом | E37: 70/30 | G37: How to find Polo Villas 4-12 and rules | J37: https://sutochno.ru/front/searchapp/detail/1988659?price_per=1&guests_adults=2&id=1&SW.lat=41.60772999273338&SW.lng=41.597023861037925&NE.lat=41.6156529340223&NE.lng=41.613975422012025 | L37: 002117363500 | M37: 6011482991 | N37: 610/30-12 | O37: 422431356 | P37: 99
B38: =B37+1 -> 37 | C38: ='1. Справочник'!C34 -> С 1125 | D38: ='1. Справочник'!F34 -> Студия | E38: 70/30 | F38: Копия Чек-лист комплектации апартаментов | G38: Копия How to find Orbi studio C 11-25.docx | H38: https://airbnb.ru/h/c1125 | I38: https://www.booking.com/Share-LndsVCR | J38: https://sutochno.ru/front/searchapp/detail/1590760?host_id=11237896&host_device=app&guest_id=6765771&guests_adults=2&guests_childrens=7&id=1&SW.lat=55.142221&SW.lng=36.803259&NE.lat=56.021281&NE.lng=37.96779 | K38: https://ostrovok.ru/hotel/georgia/batumi/mid13343905/orbi_c_1125_apartments/ | L38: - | N38: 291-7c1125 | R38: депозит | U38: депозит | V38: депозит | W38: депозит | X38: депозит | Y38: депозит | Z38: депозит | AA38: депозит
B39: =B38+1 -> 38 | C39: ='1. Справочник'!C35 -> С 1443 | D39: ='1. Справочник'!F35 -> 1+1 | E39: 70/30 | F39: Копия Чек-лист комплектации апартаментов | G39: Копия How to find Bonita 1+1 in Orbi C.docx | H39: https://airbnb.ru/h/orbic1443 | I39: https://www.booking.com/Share-LndsVCR | J39: https://sutochno.ru/front/searchapp/detail/2017711? | K39: https://ostrovok.ru/hotel/georgia/batumi/mid13343911/orbi_c_1443_apartments/ | L39: - | N39: 291-7с1443 | R39: депозит | U39: депозит | V39: депозит | W39: депозит | X39: депозит | Y39: депозит | Z39: депозит | AA39: депозит
B40: =B39+1 -> 39 | C40: ='1. Справочник'!C36 -> C 4245 | D40: ='1. Справочник'!F36 -> 1+1 | E40: 70/30 | F40: Чек-лист комплектации апартаментов | G40: How to find Orbi Block C 4245.docx | H40: https://airbnb.ru/h/orbic4245 | I40: https://www.booking.com/Share-LndsVCR | J40: https://sutochno.ru/front/searchapp/detail/1637940?guests_adults=2&id=1&SW.lat=41.63618916802409&SW.lng=41.6055252195129&NE.lat=41.64410858689991&NE.lng=41.62247678048703 | L40: - | N40: 291-7c4245 | R40: депозит | U40: депозит | V40: депозит | W40: депозит | X40: депозит | Y40: депозит | Z40: депозит | AA40: депозит
B41: =B40+1 -> 40 | C41: ='1. Справочник'!C37 -> А 4049 | D41: ='1. Справочник'!F37 -> Студия | E41: 70/30 | F41: Чек-лист комплектации апартаментов | G41: How to find Orbi City block A - 4049.docx | H41: https://airbnb.ru/h/orbia4049 | I41: https://www.booking.com/Share-LndsVCR | J41: https://sutochno.ru/front/searchapp/detail/1616526?guests_adults=2&id=1&SW.lat=41.63547812400941&SW.lng=41.60529721951294&NE.lat=41.6433976309152&NE.lng=41.62224878048706 | K41: https://ostrovok.ru/hotel/georgia/batumi/mid13343899/orbi_a_4049_apartments/ | L41: - | N41: 291/7-4049 | R41: GE55TB7761845068100026 | S41: Igor Chupin | T41: TBC | U41: депозит | V41: депозит | X41: депозит | Y41: депозит | Z41: депозит | AA41: депозит
B42: =B41+1 -> 41 | C42: ='1. Справочник'!C39 -> С 2756 | D42: ='1. Справочник'!F39 -> Студия | E42: 90/10 | G42: 📍Orbi City block С - 2756.docx | H42: https://airbnb.ru/h/orbic2756 | I42: https://www.booking.com/Share-LndsVCR | J42: https://sutochno.ru/front/searchapp/detail/2023390?detail/2023463detail/1924300guests_adults=2&id=1&SW.lat=41.63547812400941&SW.lng=41.60529721951294&NE.lat=41.6433976309152&NE.lng=41.62224878048706 | L42: - | N42: 291-7c2756 | R42: депозит / рубли | W42: депозит | X42: депозит | Y42: депозит | Z42: депозит | AA42: рубли
B43: =B42+1 -> 42 | C43: ='1. Справочник'!C40 -> D 1321 | D43: ='1. Справочник'!F40 -> Студия | E43: 70/30 | F43: Чек-лист комплектации апартаментов | G43: Копия How to find Orbi City Block D 13-21.docx | H43: https://airbnb.ru/h/orbid1321 | I43: https://www.booking.com/Share-LndsVCR | J43: https://sutochno.ru/front/searchapp/detail/1608136?guests_adults=2&id=1&SW.lat=41.634966092314265&SW.lng=41.60474921951293&NE.lat=41.64288566261085&NE.lng=41.62170078048704 | K43: https://ostrovok.ru/hotel/georgia/batumi/mid13343963/orbi_d_1321_apartments/ | L43: - | N43: 291-7d1321 | R43: GE78TB7396345063400001 | S43: Alexander Lisitsyn | T43: TBC | Z43: минус | AA43: минус
B44: =B43+1 -> 43 | C44: ='1. Справочник'!C41 -> D2 1625 | D44: ='1. Справочник'!F41 -> 1+1 | E44: 70/30 | F44: Чек-лист комплектации апартаментов | G44: How to find Orbi City Block D2 16-25.docx | H44: https://airbnb.ru/h/orbid21625 | I44: https://www.booking.com/Share-LndsVCR | J44: https://sutochno.ru/front/searchapp/detail/1924300?detail/1924300guests_adults=2&id=1&SW.lat=41.63547812400941&SW.lng=41.60529721951294&NE.lat=41.6433976309152&NE.lng=41.62224878048706 | K44: https://ostrovok.ru/hotel/georgia/batumi/mid13343950/orbi_d2_1625_apartments/ | L44: - | N44: 291-7e1625 | R44: 79103631404 | S44: рубли Таисия | T44: Сбер | Z44: рубли | AA44: рубли
B45: =B44+1 -> 44 | C45: ='1. Справочник'!C42 -> D2 3216 | D45: ='1. Справочник'!F42 -> 1+1 | E45: 70/30 | F45: Чек-лист комплектации апартаментов | G45: How to find Orbi City Block D2 32-16.docx | H45: https://airbnb.ru/h/orbid23216 | I45: https://www.booking.com/Share-LndsVCR | J45: https://sutochno.ru/front/searchapp/detail/2023317?detail/1924300guests_adults=2&id=1&SW.lat=41.63547812400941&SW.lng=41.60529721951294&NE.lat=41.6433976309152&NE.lng=41.62224878048706 | L45: - | R45: GE70CD0360000046056841 | S45: ANASTASIIA RYBINA | T45: Кредо | AA45: 971.06 | AB45: 971.06
B46: =B45+1 -> 45 | C46: ='1. Справочник'!C43 -> D1 3902 | D46: ='1. Справочник'!F43 -> 1+1 | E46: 70/30 | F46: Orbi D 3902. Чек-лист комплектации апартаментов | G46: How to find Orbi City Block D 3902.docx | H46: https://www.airbnb.ru/rooms/1467484612623509970?guests=1&adults=1&s=67&unique_share_id=e04fe84a-158e-4849-a2e7-b27931b5e7e5 | I46: https://www.booking.com/Share-LndsVCR | J46: https://sutochno.ru/front/searchapp/detail/2119377?host_id=11237896&host_device=PC&guest_id= | L46: - | N46: 291-7d1321 | R46: GE73TB7229936010100039 | S46: Vasyl Kharchuk | T46: TBC | V46: минус | AA46: депозит на хоум
B47: =B46+1 -> 46 | C47: C732 | D47: Студия | L47: - | R47: GE73TB7354745168200001 | S47: LIUDMYLA STETSIUK | T47: TBC | AB47: 473.5
B48: =B47+1 -> 47 | C48: ='1. Справочник'!C44 -> D2 503 | D48: ='1. Справочник'!F44 -> 1+1 | E48: 70/30 | F48: 503. Чек-лист комплектации апартаментов | G48: How to find Orbi City Block D2 503.docx | H48: https://www.airbnb.ru/rooms/1461444074801437384?guests=1&adults=1&s=67&unique_share_id=9fe3a0a2-856f-4570-befe-3db2641294d3 | I48: https://www.booking.com/Share-LndsVCR | J48: https://sutochno.ru/front/searchapp/detail/2111017?price_per=1&guests_adults=2&id=1&SW.lat=55.142221&SW.lng=36.803259&NE.lat=56.021281&NE.lng=37.96779 | L48: - | R48: GE50CD0360000038170422 | S48: Lukoyanov Sergey | T48: Кредо | Y48: минус | AB48: 878.72
A49: Дина | B49: =B48+1 -> 48 | C49: ='1. Справочник'!C45 -> CM 1604 | D49: ='1. Справочник'!F45 -> 1+1 | E49: 70/30 | F49: Чек-лист комплектации апартаментов | G49: How to find Marriott 1604 | H49: https://airbnb.com/h/m1604 | J49: https://sutochno.ru/front/searchapp/detail/2028842?price_per=1&guests_adults=2&id=1&SW.lat=41.63776226540329&SW.lng=41.6075522195129&NE.lat=41.645681489519276&NE.lng=41.624503780487025 | K49: https://ostrovok.ru/hotel/georgia/batumi/mid13343895/courtyard_by_marriott_1604_apartments/?dateless_form=yes | L49: - | M49: 6011026852 | N49: 291/5-1604 | O49: 11604 | P49: 10$ | R49: депозит | V49: депозит | W49: депозит | X49: депозит | Y49: депозит | Z49: депозит | AA49: депозит
A50: Дина | B50: =B49+1 -> 49 | C50: ='1. Справочник'!C46 -> CM 1606 | D50: ='1. Справочник'!F46 -> Студия | E50: 70/30 | F50: Чек-лист комплектации апартаментов | G50: How to find Marriott 1606 | H50: https://airbnb.com/h/m1606 | J50: https://sutochno.ru/front/searchapp/detail/1761838?guests_adults=1&occupied=2024-06-01;2024-08-31&id=1&term=%D0%A7%D0%B0%D0%BA%D0%B2%D0%B8&SW.lat=41.63776226540329&SW.lng=41.6075522195129&NE.lat=41.645681489519276&NE.lng=41.624503780487025 | L50: - | M50: 6011026871 | N50: 291/5-1606 | O50: 11606 | P50: 10$ | V50: депозит | W50: депозит | X50: депозит | Y50: депозит | Z50: депозит | AA50: депозит
A51: Дина | B51: =B50+1 -> 50 | C51: ='1. Справочник'!C47 -> CM 1931 | D51: ='1. Справочник'!F47 -> Студия | E51: 70/30 | F51: Чек-лист комплектации апартаментов | G51: How to find Marriott 1931 | H51: https://airbnb.ru/h/mar1931 | J51: https://sutochno.ru/front/searchapp/detail/1742348?guests_adults=1&occupied=2024-06-01;2024-08-31&id=1&term=%D0%A7%D0%B0%D0%BA%D0%B2%D0%B8&SW.lat=41.63776226540329&SW.lng=41.6075522195129&NE.lat=41.645681489519276&NE.lng=41.624503780487025 | K51: https://ostrovok.ru/hotel/georgia/batumi/mid13343898/courtyard_by_marriott_1931_apartments/ | L51: - | M51: 6011025671 | N51: 291/5-1931 | O51: 11931 | P51: 10$ | R51: GE28TB7330245064400008 | S51: Aramais ter-astvatsaturian | T51: TBC | Y51: минус | Z51: возмещение | AA51: депозит
A52: Дина | B52: =B51+1 -> 51 | C52: ='1. Справочник'!C48 -> CM 1304 | D52: 1+1 | E52: 70/30 | F52: СМ 1304. Чек-лист комплектации апартаментов | G52: Копия How to find Marriott 1304 | H52: airbnb.ru/h/cm1304 | J52: https://sutochno.ru/front/searchapp/detail/2181060?host_id=11237896&host_device=PC&guest_id= | L52: - | M52: - | N52: - | O52: 11304 | P52: 10$ | R52: GE65CD0360000029637838 | S52: MANOLIS GRIGOREV | T52: Кредо | Y52: минус | AB52: 1084
A53: Дина | B53: =B52+1 -> 52 | C53: ='1. Справочник'!C49 -> CM 1327 | D53: 1+1 | E53: 70/30 | F53: 1327. Чек-лист комплектации апартаментов | G53: How to find Marriott 1327 | H53: airbnb.ru/h/cm1327 | J53: https://sutochno.ru/front/searchapp/detail/2198219?host_id=11237896&host_device=PC&guest_id= | L53: - | M53: 6011018550 | N53: 291-51327 | O53: 11327 | P53: 10$ | R53: GE57BG0000000607381483 | T53: BOG | Z53: минус | AA53: минус
A54: Юлия | B54: =B53+1 -> 53 | C54: ='1. Справочник'!C57 -> PT2604 | D54: ='1. Справочник'!F57 -> Студия | E54: 70/30 | F54: Чек-лист комплектации апартаментов | G54: "How to find Porta Batumi Tower №2604" | H54: https://airbnb.ru/h/porta2604 | J54: https://sutochno.ru/front/searchapp/detail/2015965?price_per=1&guests_adults=2&id=1&SW.lat=41.65053097859726&SW.lng=41.63049469570893&NE.lat=41.65844862164388&NE.lng=41.647446256683066 | L54: - | M54: 6011359631 | N54: 103/4-2604 | O54: 308003451 | R54: GE84CD0360000050936562 | S54: MANN ANDREI | T54: Кредо | X54: кэш
A55: Юлия | B55: =B54+1 -> 54 | C55: ='1. Справочник'!C58 -> PT2704 | D55: ='1. Справочник'!F58 -> Студия | E55: 70/30 | F55: Чек-лист комплектации апартаментов | G55: How to find Porta Batumi Tower №2704t | H55: https://airbnb.ru/h/porta2704 | J55: https://sutochno.ru/front/searchapp/detail/2181784?host_id=11237896&host_device=PC&guest_id= | L55: - | M55: 6011359650 | N55: 103/4-2704 | O55: 308003321 | X55: кэш | AB55: 2980
A56: Юлия | B56: =B55+1 -> 55 | C56: ='1. Справочник'!C59 -> PT3604 | D56: Студия | E56: 70/30 | F56: 3604. Чек-лист комплектации апартаментов | G56: How to find Porta Batumi Tower №3604 | M56: 6011606752 | N56: 103/4-3604а | Z56: нет дохода
A57: Юлия | B57: =B56+1 -> 56 | C57: ='1. Справочник'!C63 -> MZ 718 | D57: ='1. Справочник'!F63 -> Студия | E57: 70/30 | F57: Чек-лист комплектации апартаментов | G57: How to find MZ 718 .docx | H57: https://airbnb.ru/h/mz718 | J57: https://sutochno.ru/front/searchapp/detail/2024275?guests_adults=2 | L57: - | M57: 6011471272 | N57: 454/46g-718 | O57: 306940056 | R57: GE60CD0360000030501713 | S57: DOBRIN ANDREI | T57: Кредо | AA57: депозит
A58: Юлия | B58: =B57+1 -> 57 | C58: ='1. Справочник'!C64 -> MZ 913 | D58: ='1. Справочник'!F64 -> Студия | E58: 70/30 | F58: Чек-лист комплектации апартаментов | G58: How to find MZ 913.docx | H58: https://airbnb.ru/h/mz913 | J58: https://sutochno.ru/front/searchapp/detail/2024275?guests_adults=2 | L58: - | M58: 6011471280 | N58: 454/46g-913 | O58: 306940085 | AA58: депозит
A59: Юлия | B59: =B58+1 -> 58 | C59: ='1. Справочник'!C65 -> MZ 1408 | D59: ='1. Справочник'!F65 -> 1+1 | E59: 70/30 | F59: 1416,1408. Чек-лист комплектации апартаментов | G59: How to find MZ 1408 .docx | H59: https://www.airbnb.ru/rooms/1455831071319616668?guests=1&adults=1&s=67&unique_share_id=fd34a5cf-bc2f-4850-ba6f-7590131ec980 | J59: https://sutochno.ru/front/searchapp/detail/2103186?host_id=11237896&host_device=PC&guest_id= | L59: - | M59: 6011442532 | N59: 454/46g-1408 | O59: 306316828 | R59: GE43CD0360000044512602 | S59: SVIATOSLAV CHERNOV | T59: Кредо | X59: кэш | Z59: нет дохода | AA59: рубли | AB59: рубли
A60: Юлия | B60: =B59+1 -> 59 | C60: ='1. Справочник'!C66 -> MZ А 1113 | D60: ='1. Справочник'!F66 -> 1+1 | E60: 70/30 | F60: MZ 1113. Чек-лист комплектации | G60: How to find MZ А 1113 .docx | H60: airbnb.ru/h/mza1113 | J60: https://sutochno.ru/front/searchapp/detail/2191302?guests_adults=2 | L60: - | M60: 6011463851 | N60: 454/46а-1113 | O60: 306244928 | P60: 45 | R60: GE81LB0711167463952000 | S60: Leonid Leonov | T60: Либерти | Y60: нет дохода | Z60: нет дохода | AB60: 214.37
A61: Юлия | B61: =B60+1 -> 60 | C61: ='1. Справочник'!C67 -> MZ C 511 | D61: Студия | E61: 70/30 | F61: MZ 511. Чек-лист комплектации апартаментов | G61: How to find MZ 511 .docx | H61: airbnb.ru/h/mz511 | J61: https://sutochno.ru/front/searchapp/detail/2219090?host_id=11237896&host_device=PC&guest_id= | M61: 6011588872 | N61: 454/46g-511 | O61: 309007254 | P61: 37 | R61: GE92CD0360000059559524 | S61: PYZHEVICH DMITRII | T61: Кредо | Z61: нет дохода | AA61: нет дохода
A62: Дина | B62: =B61+1 -> 61 | C62: ='1. Справочник'!C60 -> NW 2-5 | D62: ='1. Справочник'!F60 -> 1+1 | E62: 70/30 | F62: Чек-лист комплектации апартаментов | G62: How to find Next White 2-5 and rules.docx | H62: https://www.airbnb.ru/rooms/1473153859281802022?guests=1&adults=1&s=67&unique_share_id=bd6768ef-8aa4-4cd2-a9b5-28d6bc5a57dd | I62: https://admin.booking.com/hotel/hoteladmin/extranet_ng/manage/rooms.html?ses=697fcbf387dcd49c84b3dd16e81cb762&hotel_id=14509270&lang=ru | L62: 2118145426 | M62: 6011592412 | N62: 263/27-206 | O62: 308312967 | P62: 36 | R62: TCQNWrpRsesFEc4LTXmzb22JYGwgpiNBUe | S62: Usdt (trc20) | V62: минус | W62: 2392.7 | Y62: крипта | Z62: крипта | AA62: крипта
A63: Дина | B63: =B62+1 -> 62 | C63: ='1. Справочник'!C136 -> NW 4-9 | D63: ='1. Справочник'!F136 -> Студия | E63: 70/30 | F63: Чек-лист комплектации апартаментов | G63: How to find Next White 4-9 and rules.docx | H63: https://www.airbnb.ru/rooms/1452886356812519040?guests=1&adults=1&s=67&unique_share_id=72bfaaea-a6e3-492f-a08b-b85514fe5f5b | I63: https://admin.booking.com/hotel/hoteladmin/extranet_ng/manage/rooms.html?ses=697fcbf387dcd49c84b3dd16e81cb762&hotel_id=14509270&lang=ru | J63: https://sutochno.ru/front/searchapp/detail/2101833?host_id=11237896&host_device=PC&guest_id= | K63: - | L63: 2118145767 | M63: 6011357970 | N63: 263-27409 | O63: 308310377 | P63: 36 | V63: минус | Y63: крипта | Z63: депозит | AA63: нет дохода
A64: Дина | B64: =B63+1 -> 63 | C64: ='1. Справочник'!C137 -> NW 4-10 | D64: ='1. Справочник'!F137 -> Студия | E64: 70/30 | F64: Чек-лист комплектации апартаментов | G64: How to find Next White 4-10 and rules.docx | H64: airbnb.ru/h/nw4-10 | I64: https://admin.booking.com/hotel/hoteladmin/extranet_ng/manage/rooms.html?ses=697fcbf387dcd49c84b3dd16e81cb762&hotel_id=14509270&lang=ru | J64: https://sutochno.ru/front/searchapp/detail/2101805?host_id=11237896&host_device=PC&guest_id= | K64: - | L64: 2118145778 | M64: 6011358161 | N64: 263-27410 | O64: 308310337 | P64: 36 | V64: минус | Y64: крипта | Z64: депозит | AA64: нет дохода
A65: Дина | B65: =B64+1 -> 64 | C65: ='1. Справочник'!C138 -> NW 10-6 | D65: ='1. Справочник'!F138 -> Студия | E65: 70/30 | F65: Чек-лист комплектации апартаментов | G65: How to find Next White 10-6 and rules.docx | H65: https://www.airbnb.ru/rooms/1454265562224346712?guests=1&adults=1&s=67&unique_share_id=df5b1223-192b-4042-abc9-34d201836f4 | I65: https://admin.booking.com/hotel/hoteladmin/extranet_ng/manage/rooms.html?ses=697fcbf387dcd49c84b3dd16e81cb762&hotel_id=14509270&lang=ru | J65: https://sutochno.ru/front/searchapp/detail/2103035?host_id=11237896&host_device=PC&guest_id= | K65: - | L65: 2118147291 | M65: 6011355892 | N65: 263/27-1006 | O65: 308310244 | P65: 36 | R65: TD5tdeCF4EyoSannpdj98hF4e6DXMdC685 | S65: Usdt (trc20) | Y65: крипта | Z65: депозит | AA65: нет дохода
A66: Дина | B66: =B65+1 -> 65 | C66: ='1. Справочник'!C61 -> NW 3-7 | D66: Студия | E66: 70/30 | F66: Чек-лист комплектации апартаментов NW 3-7 | G66: How to find Next White 3-07 and rules.docx | H66: airbnb.ru/h/nw3-7 | I66: https://admin.booking.com/hotel/hoteladmin/extranet_ng/manage/rooms.html?ses=697fcbf387dcd49c84b3dd16e81cb762&hotel_id=14509270&lang=ru | J66: https://sutochno.ru/front/searchapp/detail/2242475?host_id=11237896&host_device=PC&guest_id= | K66: - | L66: 2118145621 | M66: 6011357782 | N66: 263-27307 | O66: 308444330 | P66: 36 | R66: 371519025 | S66: Usdt (trc20) | T66: UID ByBit | V66: минус | Y66: крипта | Z66: крипта | AA66: крипта
A67: Дина | B67: =B66+1 -> 66 | C67: ='1. Справочник'!C62 -> NA 3-16 | D67: Студия | E67: 90/10 | F67: Чек-лист комплектации апартаментов NА-316 | G67: How to find Next Apart 316 and rules.docx | L67: 2117863311 | M67: 6011303190 | N67: 263-21a3016 | O67: 309152032 | P67: 37 | R67: GE36TB7758045064400008 | S67: Pavel Moiseenko | T67: TBC | Y67: минус | AB67: 837
A68: Дина | B68: =B67+1 -> 67 | C68: ='1. Справочник'!C50 -> Int 2905 | D68: ='1. Справочник'!F50 -> 1+1 | E68: 90/10 | F68: Смета на запуск | G68: How to find Intourist A 2905 and rules.docx | H68: https://airbnb.com/h/inta2905 | J68: https://sutochno.ru/front/searchapp/detail/1695116?guests_adults=1&occupied=2024-06-01;2024-08-31&id=1&term=%D0%A7%D0%B0%D0%BA%D0%B2%D0%B8&SW.lat=41.636307175329&SW.lng=41.60915121951291&NE.lat=41.64422657959494&NE.lng=41.62610278048704 | K68: https://ostrovok.ru/hotel/georgia/batumi/mid13343962/inturist_2905_apartments/ | L68: 1117313438 | M68: 6011209751 | N68: 222-17a2905 | O68: 302824611 | R68: GE83BG0000000539684424 | S68: KAGAN ALEKSANDR | T68: BOG | Y68: депозит | Z68: депозит | AA68: 440.06
A69: Дина | B69: =B68+1 -> 68 | C69: ='1. Справочник'!C51 -> Int 2612 | D69: 1+1 | E69: 70/30 | F69: Инт В 2612. Чек-лист комплектации апартаментов | G69: How to find Intourist В 2612 and rules.docx | H69: https://www.airbnb.ru/rooms/1442041191428358249?guests=1&adults=1&s=67&unique_share_id=024c1e37-efbe-4560-bef1-9f66286378dd | J69: https://sutochno.ru/front/searchapp/detail/2083137?host_id=11237896&host_device=PC&guest_id= | L69: 2116817982 | M69: 6011542702 | N69: 222/17b-2612 | O69: 308217116 | P69: 42 | R69: GE76CD0360000054943679 | S69: Potriasova Marina | T69: Кредо | AB69: 978
A70: Дина | B70: =B69+1 -> 69 | C70: ='1. Справочник'!C52 -> Шар 2505 | D70: ='1. Справочник'!F52 -> Студия | E70: 70/30 | G70: How to find Shartava 8 (apart 2505A) | H70: https://airbnb.com/h/sh8 | J70: https://sutochno.ru/front/searchapp/detail/1820876?price_per=1&guests_adults=2&guests_childrens=7&id=1&SW.lat=41.635323114441185&SW.lng=41.60847721951294&NE.lat=41.64324264053761&NE.lng=41.62542878048707 | K70: https://ostrovok.ru/hotel/georgia/batumi/mid13343969/sh8_2505_a_apartments/ | L70: - | M70: 6011270272 | N70: 624/8-311 | O70: 422560058 | R70: GE72BG0000000570225557 | S70: SHTRASGEIM VLADIMIR | T70: BOG | AA70: 267.96
A71: Дина | B71: =B70+1 -> 70 | C71: ='1. Справочник'!C53 -> Шар 2708 | D71: ='1. Справочник'!F53 -> 1+1 | E71: 70/30 | M71: 6011634281 | N71: 624/8-331а | O71: 422731113
A72: Дина | B72: =B71+1 -> 71 | C72: ='1. Справочник'!C54 -> Багратиони | D72: 1+2 | E72: 80/20 | F72: БР 226. Чек-лист комплектации апартаментов | G72: How to find Bagrationi 227 | H72: https://airbnb.ru/h/bg227 | J72: https://sutochno.ru/front/searchapp/detail/2210028?host_id=11237896&host_device=PC&guest_id= | M72: 6011562030 | N72: 137/131а-227 | O72: 309317791 | P72: 37 | Q72: 75503626 | Z72: нет дохода | AA72: минус
A73: Юлия | B73: =B72+1 -> 72 | C73: ='1. Справочник'!C55 -> Думбадзе | D73: 1+1 | E73: 80/20 | F73: DZ 12 Apartment equipment checklist | G73: "How to find Dumbadze12 | H73: airbnb.ru/h/dz12-17 | I73: https://sutochno.ru/front/searchapp/detail/2210280?host_id=11237896&host_device=PC&guest_id= | O73: 309160851 | P73: 36 | R73: GE49TB7701445164400001 | S73: TOMER GLANTZ | T73: TBC | AB73: 1358.83
A74: Юлия | B74: =B73+1 -> 73 | C74: ='1. Справочник'!C56 -> 26 мая 52 - 813 | D74: 1+1 | F74: 26 мая. Чек-лист комплектации апартаментов | H74: airbnb.com/h/26m813 | O74: 309922369 | P74: 34 | AA74: нет дохода
A75: Дина | B75: =B74+1 -> 74 | C75: ='1. Справочник'!C74 -> шартава 16/18 | D75: ='1. Справочник'!F74 -> Студия | E75: 90/10 | F75: Чек-лист комплектации апартаментов | L75: 2117710931 | M75: 6011407402 | N75: 624/16b-018a | O75: 307943576 | P75: - | R75: GE88BG0000000607321949 | S75: BRAZDEIKE JULIJA | T75: BOG | AB75: 728
A76: ='1. Справочник'!B78 | B76: =B75+1 -> 75 | C76: ='1. Справочник'!C75 -> DL 11-1112 | D76: ='1. Справочник'!F75 -> Студия | E76: 70/30 | F76: Чек-лист комплектации апартаментов | G76: How to find Dreamland block 11 1112.docx | H76: https://airbnb.ru/h/dl-11-1112 | I76: https://www.booking.com/Share-TeyA38 | J76: https://sutochno.ru/front/searchapp/detail/1781305?price_per=1&guests_adults=2&guests_childrens=7&id=1&SW.lat=41.717946232929975&SW.lng=41.718682219512935&NE.lat=41.72585552192161&NE.lng=41.735633780487035 | L76: - | O76: 293602 | P76: 40 | R76: GE34BG0000000549875156 | S76: DANOVSKI LECH | T76: BOG
A77: ='1. Справочник'!B79 | B77: =B76+1 -> 76 | C77: ='1. Справочник'!C76 -> DL 11-1305 | D77: ='1. Справочник'!F76 -> 1+1 | E77: 70/30 | F77: Чек-лист комплектации апартаментов | G77: How to find Dreamland block 11 1305.docx | H77: https://www.airbnb.ru/rooms/1183253783255910298?guests=1&adults=1&s=67&unique_share_id=1a9e7f9e-bfc4-43cc-8f7c-701e38861957 | I77: https://www.booking.com/Share-TeyA38 | J77: https://sutochno.ru/front/searchapp/detail/1780189?guests_adults=2&occupied=2024-06-25;2024-06-26&id=1&term=%D0%A7%D0%B0%D0%BA%D0%B2%D0%B8&SW.lat=41.717946232929975&SW.lng=41.718682219512935&NE.lat=41.72585552192161&NE.lng=41.735633780487035 | L77: - | O77: 293621 | P77: 40 | R77: депозит | U77: депозит | V77: депозит | W77: депозит | X77: депозит | Y77: депозит | Z77: депозит
A78: ='1. Справочник'!B80 | B78: =B77+1 -> 77 | C78: ='1. Справочник'!C77 -> DL 14-516 | D78: ='1. Справочник'!F77 -> 1+1 | E78: 70/30 | F78: Чек-лист комплектации апартаментов | G78: How to find Dreamland block 14 516.docx | H78: https://airbnb.ru/h/dl14-516 | I78: https://www.booking.com/Share-TeyA38 | J78: https://sutochno.ru/front/searchapp/detail/1782185?guests_adults=2&occupied=2024-06-25;2024-06-26&id=1&term=%D0%A7%D0%B0%D0%BA%D0%B2%D0%B8&SW.lat=41.717946232929975&SW.lng=41.718682219512935&NE.lat=41.72585552192161&NE.lng=41.735633780487035 | L78: - | O78: 293934 | P78: 40 | R78: GE98TB7791045163400001 | S78: ALEKSEI NIKIFOROV | V78: далее хочет оплаты в $ через кассу банка | X78: кэш | Y78: кэш
A79: ='1. Справочник'!B81 | B79: =B78+1 -> 78 | C79: ='1. Справочник'!C78 -> DL 14-702 | D79: ='1. Справочник'!F78 -> 1+1 | E79: 70/30 | F79: Чек-лист комплектации апартаментов | G79: How to find Dreamland block 14 702.docx | H79: https://airbnb.ru/h/dl14-702 | I79: https://www.booking.com/Share-TeyA38 | J79: https://sutochno.ru/front/searchapp/detail/1761287?guests_adults=1&occupied=2024-06-01;2024-08-31&id=1&term=%D0%A7%D0%B0%D0%BA%D0%B2%D0%B8&SW.lat=41.717946232929975&SW.lng=41.718682219512935&NE.lat=41.72585552192161&NE.lng=41.735633780487035 | L79: - | O79: 293954 | P79: 40 | R79: GE22CD0360000036840765 | S79: Константин Удодов | T79: Кредо | U79: депозит | X79: минус | Y79: минус | Z79: минус
A80: ='1. Справочник'!B82 | B80: =B79+1 -> 79 | C80: ='1. Справочник'!C79 -> DL 14-1214 | D80: ='1. Справочник'!F79 -> Студия | E80: 70/30 | F80: Чек-лист комплектации апартаментов | G80: How to find Dreamland block 14 1214.docx | H80: https://airbnb.ru/h/dl14-1214 | I80: https://www.booking.com/Share-TeyA38 | L80: - | O80: 293782 | P80: 40 | R80: GE74BG0000000537401982 / znaichenko82@mail.ru | S80: ZNAICHENKO Vadim | T80: BOG / USDT
A81: ='1. Справочник'!B83 | B81: =B80+1 -> 80 | C81: ='1. Справочник'!C80 -> 14-411 | D81: ='1. Справочник'!F80 -> Студия/твин | E81: 70/30 | F81: Чек-лист комплектации апартаментов | G81: How to find Dreamland block 14 411.docx | H81: https://airbnb.ru/h/DL-14-411 | I81: https://www.booking.com/Share-TeyA38 | L81: - | O81: 293910 | P81: 40 | R81: TNndGrfEpUJMJJ9NQkqzV3DkQHeqZ54g9F | S81: 20208925 | T81: UID ByBit
A82: ='1. Справочник'!B85 | B82: =B81+1 -> 81 | C82: ='1. Справочник'!C81 -> DL 4-09 | D82: ='1. Справочник'!F81 -> Студия | E82: 70/30 | F82: Чек-лист комплектации апартаментов | G82: How to find Dreamland block 04 09.docx | H82: https://airbnb.ru/h/dl4-09 | I82: https://www.booking.com/Share-TeyA38 | J82: https://sutochno.ru/front/searchapp/detail/1780129?guests_adults=2&occupied=2024-06-25;2024-06-26&id=1&term=%D0%A7%D0%B0%D0%BA%D0%B2%D0%B8&SW.lat=41.715478079909495&SW.lng=41.71741621951294&NE.lat=41.723387674944185&NE.lng=41.73436778048704 | L82: - | O82: 293403 | P82: 40 | R82: GE17CR0150009490893601 | S82: Elizaveta Pavlik | U82: депозит | X82: депозит | Y82: депозит | Z82: депозит
A83: ='1. Справочник'!B87 | B83: =B82+1 -> 82 | C83: ='1. Справочник'!C82 -> DL14-518 | D83: ='1. Справочник'!F82 -> Студия | E83: 70/30 | F83: Чек-лист комплектации апартаментов | G83: How to find Dreamland block 14 518.docx | H83: https://airbnb.ru/h/dl14-518 | I83: https://www.booking.com/Share-TeyA38 | L83: - | O83: 239937 | P83: 40 | R83: GE05CD0360000039394887 | S83: Lakhtikova Varvara | T83: Кредо
A84: ='1. Справочник'!B84 | B84: =B83+1 -> 83 | C84: ='1. Справочник'!C83 -> DL14-1405 | D84: ='1. Справочник'!F83 -> 1+1 | E84: 70/30 | F84: Чек-лист комплектации апартаментов | G84: How to find Dreamland block 14 1405.docx | H84: https://airbnb.ru/h/dl14-1405 | I84: https://www.booking.com/Share-TeyA38 | L84: - | O84: 293802 | P84: 40 | R84: депозит | W84: депозит | X84: депозит | Z84: депозит | AA84: крипта
A85: ='1. Справочник'!B98 -> Светлана | B85: =B84+1 -> 84 | C85: ='1. Справочник'!C87 -> DL14-305 | D85: ='1. Справочник'!F87 -> Студия | E85: 70/30 | F85: Чек-лист комплектации апартаментов | G85: How to find | H85: https://airbnb.ru/h/dl14-305 | I85: https://www.booking.com/Share-TeyA38 | L85: - | O85: 293888 | P85: 40 | R85: GE69TB7965345064400010 | S85: Iuliia Savchenko | T85: TBC
A86: ='1. Справочник'!B141 | B86: =B85+1 -> 85 | C86: ='1. Справочник'!C84 -> DL 14-505 | D86: ='1. Справочник'!F84 -> Студия/твин | E86: 70/30 | F86: Чек-лист комплектации апартаментов | G86: How to find | H86: https://airbnb.ru/h/dl14-505 | I86: https://www.booking.com/Share-TeyA38 | J86: https://sutochno.ru/front/searchapp/detail/2090023?guests_adults=2 | L86: - | O86: 293922 | P86: 40
A87: ='1. Справочник'!B141 | B87: =B86+1 -> 86 | C87: DL 14-506 | D87: Студия | E87: 70/30 | F87: DL 14-506. Чек-лист комплектации апартаментов | G87: How to find 14-506 | H87: airbnb.com/h/dl14-506 | I87: https://www.booking.com/Share-TeyA37 | O87: 293923 | P87: 40 | R87: GE15CR0150009552043601 | S87: VERONIKA ZHUK | T87: Cartu
A88: ='1. Справочник'!B143 | B88: =B87+1 -> 87 | C88: ='1. Справочник'!C86 -> DL 14-1710 | D88: ='1. Справочник'!F86 -> Студия | E88: 70/30 | G88: How to find DL | H88: https://www.airbnb.ru/rooms/1430277481145870994?guests=1&adults=1&s=67&unique_share_id=76311261-0c43-49b6-879e-026abfc647c6 | I88: https://www.booking.com/Share-TeyA38 | L88: - | O88: 293888 | P88: 40 | R88: GE23BG0000000538696783 | S88: Lina Zilinskiene | T88: BOG
A89: ='1. Справочник'!B145 | B89: =B88+1 -> 88 | C89: ='1. Справочник'!C88 -> DL14-501-502 | D89: ='1. Справочник'!F88 -> 1+1 | E89: 70/30 | G89: How to find | H89: https://www.airbnb.ru/rooms/1439863862616318204?guests=1&adults=1&s=67&unique_share_id=311f5dee-0348-46c3-a31f-a3e4c7a9b293 | I89: https://www.booking.com/Share-TeyA38 | L89: - | O89: 293918 | P89: 40 | R89: GE02TB7950645064400011 | S89: Kitaichik Genadi | T89: TBC | X89: кэш
A90: ='1. Справочник'!B99 -> Светлана | B90: =B89+1 -> 89 | C90: ='1. Справочник'!C89 -> DL7-16 | D90: Студия | E90: 70/30 | F90: 7-16/ Чек-лист комплектации апартаментов | G90: How to find | H90: https://airbnb.ru/h/dl7-16 | I90: https://www.booking.com/Share-TeyA38 | J90: https://sutochno.ru/front/searchapp/detail/2088335?guests_adults=2 | L90: - | O90: 293484 | P90: 40 | R90: TWush6wVZN2S8ck4BVbdPm2S4PEhpqQq6f | S90: Usdt (trc20) | Z90: крипта | AA90: крипта | AC90: крипта
A91: ='1. Справочник'!B147 | B91: =B90+1 -> 90 | C91: DL 13-201 | D91: Студия | E91: 70/30 | F91: DL 13-201. Чек-лист комплектации апартаментов | G91: How to find 13/201 | I91: https://www.booking.com/Share-TeyA39 | W91: 2 706.12 депозит | X91: кэш
A92: ='1. Справочник'!B147 | B92: =B91+1 -> 91 | C92: ='1. Справочник'!C90 -> DL 13-206 | D92: ='1. Справочник'!F90 -> Студия на 4х | E92: 70/30 | G92: How to find 13/206 | H92: https://airbnb.com/h/dl13-206 | I92: https://www.booking.com/Share-TeyA40 | R92: GE57BG0000000499462484 | S92: Alexander Baranov | T92: GEL BOG | X92: кэш
A93: ='1. Справочник'!B148 | B93: =B92+1 -> 92 | C93: ='1. Справочник'!C92 -> DL 13-709 | D93: ='1. Справочник'!F92 -> Студия на 4х | E93: 70/30 | G93: How to find 13/709 | H93: https://airbnb.ru/h/dl13-709 | I93: https://www.booking.com/Share-TeyA41 | T93: наличные | X93: кэш
A94: ='1. Справочник'!B149 | B94: =B93+1 -> 93 | C94: ='1. Справочник'!C93 -> DL 13-703 | D94: ='1. Справочник'!F93 -> 1+1 | E94: 70/30 | F94: DL 13-703. Чек-лист комплектации апартаментов | G94: How to find 13/703 | H94: https://airbnb.ru/h/dl13-703 | I94: https://www.booking.com/Share-TeyA42 | V94: депозит | W94: депозит | X94: кэш
A95: ='1. Справочник'!B150 | B95: =B94+1 -> 94 | C95: ='1. Справочник'!C94 -> DL 13-1006 | D95: ='1. Справочник'!F94 -> 1+1 | E95: 70/30 | F95: Копия DL 13-1006. Чек-лист комплектации апартаментов | G95: How to find 13/1006 | I95: https://www.booking.com/Share-TeyA44 | R95: GE21CD0360000041416467 | S95: ZAKHAROV MIKHAIL | T95: Credo bank
A96: ='1. Справочник'!B100 -> Светлана | B96: =B95+1 -> 95 | C96: ='1. Справочник'!C95 -> DL 13-1106 | D96: ='1. Справочник'!F94 -> 1+1 | E96: 70/30 | F96: DL 13-1106Чек-лист комплектации апартаментов | G96: How to find 13/1106 | I96: https://www.booking.com/Share-TeyA44 | X96: минус | Y96: минус
A97: ='1. Справочник'!B140 | B97: =B96+1 -> 96 | C97: ='1. Справочник'!C140 -> TGA1 | D97: ='1. Справочник'!F140 -> 1+2 | E97: 70/30 | F97: https://docs.google.com/spreadsheets/d/1_zCnzIjXJZLLwRv65RgdFzoNDY9lNL6D/edit | G97: How to find Tropical Garden .docx | H97: https://airbnb.ru/h/tg-1a | I97: https://www.booking.com/Share-8BzKUBw | J97: https://sutochno.ru/front/searchapp/detail/2002928?host_id | L97: 2116441487 | M97: 6110361780 | N97: 532/25a-1 | O97: 422196093 | P97: 42 | R97: наличные | Z97: в сейфе 11 005 лари
A98: ='1. Справочник'!B96 | B98: =B97+1 -> 97 | C98: ='1. Справочник'!C98 -> TGA2 | D98: ='1. Справочник'!F98 -> 1+1 | E98: 70/30 | G98: How to find Tropical Garden .docx | H98: https://airbnb.ru/h/tg-2a | I98: https://www.booking.com/Share-8BzKUBw | J98: https://sutochno.ru/front/searchapp/detail/2003576?host_id | L98: 2116441498 | M98: 6110363032 | N98: 532/25a-2 | O98: 422410189 | P98: 42
A99: ='1. Справочник'!B141 | B99: =B98+1 -> 98 | C99: ='1. Справочник'!C141 -> TGA3 | D99: ='1. Справочник'!F141 -> Студия | E99: 70/30 | G99: How to find Tropical Garden .docx | H99: https://airbnb.ru/h/tg-3a | I99: https://www.booking.com/Share-8BzKUBw | J99: https://sutochno.ru/front/searchapp/detail/2003592?host_id | L99: 2116441502 | M99: 6110363122 | N99: 532/25a-3 | O99: 422881705 | P99: 51
A100: ='1. Справочник'!B142 | B100: =B99+1 -> 99 | C100: ='1. Справочник'!C142 -> TGA4 | D100: ='1. Справочник'!F142 -> 1+1 | E100: 70/30 | G100: How to find Tropical Garden .docx | H100: https://airbnb.ru/h/tg-4a | I100: https://www.booking.com/Share-8BzKUBw | J100: https://sutochno.ru/front/searchapp/detail/2003576?host_id | L100: 2116441513 | M100: 6110363040 | N100: 532/25a-4 | O100: 422740287 | P100: 42
...

Sheet ЗАПУСК
B1: Отв | C1: комплекс | D1: номер | E1: Собственник | F1: тип | G1: Старт запуска | H1: Дата завершения | I1: кол-во дней | J1: Текущая стадия | K1: индекс Соб | L1: Чат с СОБ | M1: Договор | N1: Аудит (ссылка) | O1: затраты на комплектацию | P1: Хоумст | Q1: Ремонт | R1: Хоумст | S1: Закуп | T1: Комлект | U1: Фотосессия | V1: Готовность к запуску | W1: airbnb (ссылка) | X1: Суточно | Y1: Бук | Z1: Островок | AA1: Синхронизация с HF | AB1: Обучение по РК | AC1: ЗАПУСК | AD1: Контр проверка чек-листа | AE1: Списание затрат на запуск | AG1: Шортс | AH1: Откуда
B2: =#REF! -> #REF! | D2: ='1. Справочник'!C13 -> WS A805 | F2: ='1. Справочник'!F87 -> Студия | K2: 7 | L2: TRUE | M2: TRUE | N2: TRUE | O2: FALSE | P2: FALSE | Q2: FALSE | R2: FALSE | S2: TRUE | T2: TRUE | U2: TRUE | V2: FALSE | W2: TRUE | X2: TRUE | Y2: TRUE | Z2: FALSE | AA2: TRUE | AB2: TRUE | AC2: TRUE
B3: ='1. Справочник'!B3 -> Марина | D3: F 1103 | F3: 1+1 | K3: 9 | L3: TRUE | M3: TRUE | N3: TRUE | O3: FALSE | P3: FALSE | Q3: FALSE | R3: FALSE | S3: TRUE | T3: TRUE | U3: TRUE | V3: FALSE | W3: TRUE | X3: TRUE | Y3: TRUE | Z3: FALSE | AA3: TRUE | AB3: TRUE | AC3: TRUE
B4: Светлана | D4: ='1. Справочник'!C88 -> DL14-501-502 | F4: ='1. Справочник'!F88 -> 1+1 | K4: 9 | L4: TRUE | M4: TRUE | N4: TRUE | O4: FALSE | P4: FALSE | Q4: FALSE | R4: FALSE | S4: TRUE | T4: TRUE | U4: TRUE | V4: FALSE | W4: TRUE | X4: FALSE | Y4: TRUE | Z4: FALSE | AA4: TRUE | AB4: TRUE | AC4: TRUE
B5: Светлана | D5: =#REF! -> #REF! | F5: =#REF! -> #REF! | K5: 7 | L5: FALSE | M5: TRUE | N5: TRUE | O5: FALSE | P5: FALSE | Q5: FALSE | R5: FALSE | S5: TRUE | T5: TRUE | U5: TRUE | V5: FALSE | W5: TRUE | X5: FALSE | Y5: TRUE | Z5: FALSE | AA5: TRUE | AB5: TRUE | AC5: TRUE
B6: Светлана | D6: ='1. Справочник'!C87 -> DL14-305 | F6: ='1. Справочник'!F84 -> Студия/твин | K6: 7 | L6: TRUE | M6: TRUE | N6: TRUE | O6: FALSE | P6: FALSE | Q6: FALSE | R6: FALSE | S6: TRUE | T6: TRUE | U6: TRUE | V6: FALSE | W6: TRUE | X6: FALSE | Y6: TRUE | Z6: FALSE | AA6: TRUE | AB6: TRUE | AC6: TRUE
B7: Светлана | D7: ='1. Справочник'!C85 -> DL 14-1614 | F7: Студия | K7: 9 | L7: TRUE | M7: TRUE | N7: TRUE | O7: FALSE | P7: FALSE | Q7: FALSE | R7: FALSE | S7: TRUE | T7: TRUE | U7: TRUE | V7: FALSE | W7: TRUE | X7: FALSE | Y7: TRUE | Z7: FALSE | AA7: TRUE | AB7: TRUE | AC7: TRUE
B8: Светлана | D8: ='1. Справочник'!C86 -> DL 14-1710 | F8: Студия | K8: 9 | L8: TRUE | M8: TRUE | N8: TRUE | O8: FALSE | P8: FALSE | Q8: FALSE | R8: FALSE | S8: TRUE | T8: TRUE | U8: TRUE | V8: FALSE | W8: TRUE | X8: FALSE | Y8: TRUE | Z8: FALSE | AA8: TRUE | AB8: TRUE | AC8: TRUE
B9: Светлана | D9: DL 07-16 | F9: ='1. Справочник'!F89 -> 1+2 с террасой | K9: 5 | L9: TRUE | M9: TRUE | N9: TRUE | O9: FALSE | P9: FALSE | Q9: FALSE | R9: FALSE | S9: TRUE | T9: FALSE | U9: TRUE | V9: FALSE | W9: TRUE | X9: TRUE | Y9: TRUE | Z9: FALSE | AA9: TRUE | AB9: TRUE | AC9: TRUE
B10: Юлия | D10: ='1. Справочник'!C136 -> NW 4-9 | F10: ='1. Справочник'!F136 -> Студия | K10: 7 | L10: TRUE | M10: TRUE | N10: TRUE | O10: FALSE | P10: FALSE | Q10: FALSE | R10: FALSE | S10: TRUE | T10: TRUE | U10: TRUE | V10: FALSE | W10: TRUE | X10: TRUE | Y10: TRUE | Z10: FALSE | AA10: TRUE | AB10: TRUE | AC10: TRUE
B11: Юлия | D11: ='1. Справочник'!C137 -> NW 4-10 | F11: ='1. Справочник'!F137 -> Студия | K11: индекс Собственника | L11: TRUE | M11: TRUE | N11: TRUE | O11: FALSE | P11: FALSE | Q11: FALSE | R11: FALSE | S11: TRUE | T11: TRUE | U11: TRUE | V11: FALSE | W11: TRUE | X11: TRUE | Y11: FALSE | Z11: FALSE | AA11: TRUE | AB11: TRUE | AC11: TRUE
B12: Юлия | D12: ='1. Справочник'!C138 -> NW 10-6 | F12: ='1. Справочник'!F138 -> Студия | K12: 7 | L12: TRUE | M12: TRUE | N12: TRUE | O12: FALSE | P12: FALSE | Q12: FALSE | R12: FALSE | S12: TRUE | T12: TRUE | U12: TRUE | V12: FALSE | W12: TRUE | X12: TRUE | Y12: TRUE | Z12: FALSE | AA12: TRUE | AB12: TRUE | AC12: TRUE
B13: Юлия | D13: Инт В 2612 | F13: 1+1 | K13: 9 | L13: TRUE | M13: TRUE | N13: TRUE | O13: FALSE | P13: FALSE | Q13: FALSE | R13: FALSE | S13: TRUE | T13: TRUE | U13: TRUE | V13: FALSE | W13: TRUE | X13: TRUE | Y13: FALSE | Z13: FALSE | AA13: TRUE | AB13: TRUE | AC13: TRUE
B14: Юлия | D14: MZ C 1416 | F14: Студия | K14: 7 | L14: TRUE | M14: TRUE | N14: TRUE | O14: FALSE | P14: FALSE | Q14: FALSE | R14: FALSE | S14: TRUE | T14: TRUE | U14: TRUE | V14: FALSE | W14: TRUE | X14: TRUE | Y14: FALSE | Z14: FALSE | AA14: TRUE | AB14: TRUE | AC14: TRUE
B15: Юлия | D15: MZ C 1408 | F15: 1+1 | K15: 7 | L15: TRUE | M15: TRUE | N15: TRUE | O15: FALSE | P15: FALSE | Q15: FALSE | R15: FALSE | S15: TRUE | T15: TRUE | U15: TRUE | V15: FALSE | W15: TRUE | X15: TRUE | Y15: FALSE | Z15: FALSE | AA15: TRUE | AB15: TRUE | AC15: TRUE
B16: Светлана | D16: DL 13-709 | F16: Студия | K16: 9 | L16: TRUE | M16: TRUE | N16: TRUE | O16: FALSE | P16: FALSE | Q16: FALSE | R16: FALSE | S16: TRUE | T16: TRUE | U16: TRUE | V16: FALSE | W16: TRUE | X16: FALSE | Y16: TRUE | Z16: FALSE | AA16: TRUE | AB16: TRUE | AC16: TRUE
B17: Светлана | D17: DL 13-206 | F17: 1+1 | K17: 9 | L17: TRUE | M17: TRUE | N17: TRUE | O17: FALSE | P17: FALSE | Q17: FALSE | R17: FALSE | S17: FALSE | T17: FALSE | U17: FALSE | V17: FALSE | W17: FALSE | X17: FALSE | Y17: FALSE | Z17: FALSE | AA17: FALSE | AB17: TRUE | AC17: FALSE
B18: Светлана | D18: DL 13-703 | F18: 1+1 | K18: 5 | L18: TRUE | M18: TRUE | N18: TRUE | O18: FALSE | P18: FALSE | Q18: FALSE | R18: FALSE | S18: FALSE | T18: FALSE | U18: FALSE | V18: FALSE | W18: FALSE | X18: FALSE | Y18: FALSE | Z18: FALSE | AA18: FALSE | AB18: TRUE | AC18: FALSE
B19: Светлана | D19: DL 13-701 | F19: Студия | K19: 7 | L19: TRUE | M19: FALSE | N19: FALSE | O19: FALSE | P19: FALSE | Q19: FALSE | R19: FALSE | S19: FALSE | T19: FALSE | U19: FALSE | V19: FALSE | W19: FALSE | X19: FALSE | Y19: FALSE | Z19: FALSE | AA19: FALSE | AB19: FALSE | AC19: FALSE
B20: Светлана | D20: DL 14-506 | F20: Студия | K20: индекс Собственника | L20: TRUE | M20: TRUE | N20: FALSE | O20: FALSE | P20: FALSE | Q20: FALSE | R20: FALSE | S20: FALSE | T20: FALSE | U20: FALSE | V20: FALSE | W20: FALSE | X20: FALSE | Y20: FALSE | Z20: FALSE | AA20: FALSE | AB20: FALSE | AC20: FALSE
B21: Светлана | D21: TG 195 | F21: 1+1 | K21: 7 | L21: TRUE | M21: TRUE | N21: FALSE | O21: FALSE | P21: FALSE | Q21: FALSE | R21: FALSE | S21: FALSE | T21: FALSE | U21: FALSE | V21: FALSE | W21: FALSE | X21: FALSE | Y21: FALSE | Z21: FALSE | AA21: FALSE | AB21: FALSE | AC21: FALSE
B22: Борис | D22: D1 3902 | F22: 1+1 | K22: 9 | L22: TRUE | M22: TRUE | N22: FALSE | O22: FALSE | P22: FALSE | Q22: FALSE | R22: FALSE | S22: FALSE | T22: FALSE | U22: FALSE | V22: FALSE | W22: FALSE | X22: FALSE | Y22: FALSE | Z22: FALSE | AA22: FALSE | AB22: TRUE | AC22: TRUE
B23: Борис | D23: ='1. Справочник'!C44 -> D2 503 | F23: 1+1 | J23: с 25.06. | K23: 9 | L23: TRUE | M23: TRUE | N23: TRUE | O23: FALSE | P23: FALSE | Q23: FALSE | R23: FALSE | S23: TRUE | T23: TRUE | U23: TRUE | V23: FALSE | W23: TRUE | X23: TRUE | Y23: FALSE | Z23: FALSE | AA23: TRUE | AB23: TRUE | AC23: TRUE
B24: Юлия | D24: ='1. Справочник'!C60 -> NW 2-5 | F24: 1+1 | K24: 7 | L24: TRUE | M24: TRUE | N24: TRUE | O24: FALSE | P24: FALSE | Q24: FALSE | R24: FALSE | S24: TRUE | T24: TRUE | U24: FALSE | V24: FALSE | W24: FALSE | X24: FALSE | Y24: FALSE | Z24: FALSE | AA24: TRUE | AB24: TRUE | AC24: TRUE
B25: Юлия | D25: ='1. Справочник'!C62 -> NA 3-16 | F25: студия | J25: синхронизация с РК | K25: 6 | L25: TRUE | M25: TRUE | N25: Чек-лист комплектации апартаментов NА-316 | P25: нет | S25: TRUE | T25: TRUE | U25: TRUE | V25: TRUE | AA25: FALSE | AB25: FALSE | AC25: TRUE | AG25: да
B26: Юлия | D26: ='1. Справочник'!C48 -> CM 1304 | F26: 1+1 | J26: Выполнено | K26: 7 | L26: TRUE | M26: TRUE | N26: https://docs.google.com/spreadsheets/d/1SU1XnXcn8cX9nJXZAXTvTEukq2Addt7kJMtSa5of7n8/edit?gid=0#gid=0 | P26: Нина | R26: TRUE | S26: TRUE | T26: TRUE | U26: TRUE | V26: TRUE | W26: airbnb.ru/h/cm1304 | X26: https://sutochno.ru/front/searchapp/detail/2181060?host_id=11237896&host_device=PC&guest_id= | AA26: TRUE | AB26: TRUE | AC26: TRUE | AG26: да
B27: Юлия | D27: MZ 1113 | F27: 1+1 | J27: Выполнено | K27: 9 | L27: TRUE | M27: TRUE | N27: MZ 1113. Чек-лист комплектации | P27: Алеся | R27: TRUE | S27: TRUE | T27: TRUE | U27: TRUE | V27: TRUE | W27: airbnb.ru/h/mza1113 | X27: https://sutochno.ru/front/searchapp/detail/2191302?host_id=11237896&host_device=PC&guest_id= | AA27: TRUE | AB27: TRUE | AC27: TRUE | AG27: да
B28: Дарья | D28: ='1. Справочник'!C17 -> BV A 100 | F28: студия | J28: Выполнено | K28: 2 | L28: TRUE | M28: TRUE | N28: Чек-лист комплектации апартаментов BV A 100 | P28: нет | S28: TRUE | T28: TRUE | U28: TRUE | V28: TRUE | AA28: TRUE | AB28: TRUE | AC28: TRUE | AG28: нет | AH28: строители
B29: Дарья | D29: ='1. Справочник'!C6 -> WS В 807 | F29: студия | J29: Выполнено | K29: 7 | L29: TRUE | M29: TRUE | N29: В 807. Чек-лист комплектации апартаментов | P29: Нина | Q29: TRUE | R29: TRUE | S29: TRUE | T29: TRUE | U29: TRUE | V29: TRUE | W29: арб | X29: https://sutochno.ru/front/searchapp/detail/2196284?guests_adults=2 | Y29: https://www.booking.com/Share-YrYvd59 | AA29: TRUE | AB29: TRUE | AC29: TRUE | AG29: нет | AH29: санафан
B30: Светлана | D30: WH 176 | F30: студия | J30: Выполнено | K30: 6 | L30: TRUE | M30: TRUE | N30: WH 176. Чек-лист комплектации апартаментов | P30: Нина | Q30: TRUE | R30: TRUE | S30: TRUE | T30: TRUE | U30: TRUE | V30: FALSE | W30: 176 АРБ | X30: https://sutochno.ru/front/searchapp/detail/2197711?guests_adults=2 | AA30: TRUE | AB30: TRUE | AC30: TRUE | AG30: нет | AH30: санафан
B31: Юлия | D31: СМ 1327 | F31: 1+1 | J31: Выполнено | K31: 8 | L31: TRUE | M31: TRUE | N31: 1327. Чек-лист комплектации апартаментов | P31: нет | Q31: TRUE | R31: TRUE | S31: TRUE | T31: TRUE | U31: TRUE | V31: TRUE | W31: 1327 АРБ | X31: https://sutochno.ru/front/searchapp/detail/2198219?host_id=11237896&host_device=PC&guest_id= | AA31: TRUE | AB31: TRUE | AC31: TRUE | AG31: нет | AH31: риелторы
B32: Дарья | D32: WS F 1008 | F32: студия | J32: Выполнено | K32: 7 | L32: TRUE | M32: TRUE | N32: Смета на запуск | P32: Нина | Q32: TRUE | R32: TRUE | S32: TRUE | T32: TRUE | U32: TRUE | V32: TRUE | W32: https://airbnb.ru/h/wsf1008 | X32: https://sutochno.ru/front/searchapp/detail/2209519?host_id=11237896&host_device=PC&guest_id= | AA32: TRUE | AB32: TRUE | AC32: TRUE | AG32: нет | AH32: санафан
B33: Юлия | D33: Багратиони | F33: 2+1 | J33: Выполнено | K33: 4 | L33: TRUE | M33: TRUE | N33: БР 226. Чек-лист комплектации апартаментов | P33: нет | Q33: TRUE | S33: TRUE | T33: TRUE | U33: TRUE | V33: TRUE | W33: airbnb.ru/h/bg227 | X33: https://sutochno.ru/front/searchapp/detail/2210028?host_id=11237896&host_device=PC&guest_id= | AA33: TRUE | AB33: TRUE | AC33: TRUE | AG33: да
B34: Юлия | D34: Думбадзе | F34: 1+1 | J34: Выполнено | K34: 9 | L34: TRUE | M34: TRUE | N34: DZ. Смета на запуск | P34: Алеся | Q34: TRUE | R34: TRUE | S34: TRUE | T34: TRUE | U34: TRUE | V34: TRUE | W34: airbnb.ru/h/dz12-17 | X34: https://sutochno.ru/front/searchapp/detail/2210280?host_id=11237896&host_device=PC&guest_id= | AA34: TRUE | AB34: TRUE | AC34: TRUE | AG34: нет | AH34: санафан
B35: Светлана | D35: OBT 2906 | F35: студия | J35: Выполнено | K35: 6 | L35: TRUE | M35: TRUE | N35: РЕНОВАЦИЯ СМЕТА | P35: Алеся | Q35: TRUE | R35: TRUE | S35: TRUE | T35: TRUE | U35: TRUE | V35: TRUE | W35: airbnb.ru/h/obt2906 | Y35: https://www.booking.com/hotel/ge/beach-tower-app-montreux.ru.html?label=gen173nr-10CAsoUkIYYmVhY2gtdG93ZXItYXBwLW1vbnRyZXV4SDNYBGhSiAEBmAEzuAEXyAEM2AED6AEB-AEBiAIBqAIBuALnnIDKBsACAdICJDE5ZGY4NDQ5LTgyMDMtNGFhYi1hODYzLTgwYTllZDUyODVlZtgCAeACAQ&sid=a1de48d8e17c657d54e265ede55366e1&dist=0&keep_landing=1&sb_price_type=total&type=total& | AA35: TRUE | AB35: TRUE | AC35: TRUE | AG35: нет | AH35: санафан
B36: Светлана | D36: OBT 2908 | F36: студия | J36: Выполнено | K36: 6 | L36: TRUE | M36: TRUE | P36: Алеся | Q36: TRUE | R36: TRUE | S36: TRUE | T36: TRUE | U36: TRUE | V36: TRUE | W36: http://airbnb.ru/h/obt2908 | AA36: TRUE | AB36: TRUE | AC36: TRUE | AG36: нет | AH36: санафан
B37: Светлана | D37: OBT 2910 | F37: студия | J37: Выполнено | K37: 6 | L37: TRUE | M37: TRUE | P37: Алеся | Q37: TRUE | R37: TRUE | S37: TRUE | T37: TRUE | U37: TRUE | V37: TRUE | W37: http://airbnb.ru/h/obt2910 | AA37: TRUE | AB37: TRUE | AC37: TRUE | AG37: нет | AH37: санафан
B38: Юлия | D38: MZ C 511 | F38: студия | J38: Выполнено | K38: 6 | L38: TRUE | M38: TRUE | N38: MZ 511. Чек-лист комплектации апартаментов | P38: нет | Q38: TRUE | S38: TRUE | T38: TRUE | U38: TRUE | V38: TRUE | W38: airbnb.ru/h/mz511 | X38: https://sutochno.ru/front/searchapp/detail/2219090?host_id=11237896&host_device=PC&guest_id= | AA38: TRUE | AB38: TRUE | AC38: TRUE | AG38: нет | AH38: санафан
B39: Юлия | D39: 26 мая 50 - 813 | F39: 1+1 | J39: Выполнено | K39: 9 | L39: TRUE | M39: TRUE | N39: 26 мая. Чек-лист комплектации апартаментов | P39: нет | Q39: TRUE | S39: TRUE | T39: TRUE | U39: TRUE | V39: TRUE | AA39: FALSE | AB39: FALSE | AC39: FALSE | AG39: да
B40: Светлана | D40: Batumi View 145 | F40: 1+1 | J40: Выполнено | K40: 7 | L40: TRUE | M40: TRUE | N40: ОБЩИЙ. Чек-лист комплектации апартаментов | P40: BV. Смета на запуск. Нина | Q40: TRUE | R40: TRUE | S40: TRUE | T40: TRUE | U40: TRUE | V40: TRUE | W40: airbnb.ru/h/bva145 | X40: https://sutochno.ru/front/searchapp/detail/2226306? | Y40: https://www.booking.com/hotel/ge/batumi-view-first-line.html | AA40: TRUE | AB40: TRUE | AC40: TRUE | AG40: нет | AH40: санафан
B41: Светлана | D41: Batumi View 147 | F41: 1+1 | J41: Выполнено | K41: 7 | L41: TRUE | M41: TRUE | Q41: TRUE | R41: TRUE | S41: TRUE | T41: TRUE | U41: TRUE | V41: TRUE | W41: airbnb.ru/h/bva147 | Y41: https://www.booking.com/hotel/ge/batumi-view-first-line.html | AA41: TRUE | AB41: TRUE | AC41: TRUE | AG41: нет | AH41: санафан
B42: Светлана | D42: Batumi View 144 | F42: 1+1 | J42: Выполнено | K42: 7 | L42: TRUE | M42: TRUE | Q42: TRUE | R42: TRUE | S42: TRUE | T42: TRUE | U42: TRUE | V42: TRUE | W42: airbnb.ru/h/bva144 | X42: https://sutochno.ru/front/searchapp/detail/2226291? | Y42: https://www.booking.com/hotel/ge/batumi-view-first-line.html | AA42: TRUE | AB42: TRUE | AC42: TRUE | AG42: нет | AH42: санафан
B43: Светлана | D43: Batumi View С 137 | F43: студия | J43: Выполнено | K43: 7 | L43: TRUE | M43: TRUE | Q43: TRUE | R43: TRUE | S43: TRUE | T43: TRUE | U43: TRUE | V43: TRUE | W43: airbnb.ru/h/bvc137 | X43: https://sutochno.ru/front/searchapp/detail/2226325? | Y43: https://www.booking.com/hotel/ge/batumi-view-first-line.html | AA43: TRUE | AB43: TRUE | AC43: TRUE | AG43: нет | AH43: санафан
B44: Светлана | D44: Batumi View 133 | F44: 1+1 | J44: Выполнено | K44: 7 | L44: TRUE | M44: TRUE | Q44: TRUE | R44: TRUE | S44: TRUE | T44: TRUE | U44: TRUE | V44: TRUE | W44: airbnb.ru/h/bva133 | Y44: https://www.booking.com/hotel/ge/batumi-view-first-line.html | AA44: TRUE | AB44: FALSE | AC44: TRUE | AG44: нет | AH44: санафан
B45: Светлана | D45: Batumi View 134 | F45: 1+1 | J45: Выполнено | K45: 7 | L45: TRUE | M45: TRUE | Q45: TRUE | R45: TRUE | S45: TRUE | T45: TRUE | U45: TRUE | V45: TRUE | W45: airbnb.ru/h/bva134 | X45: https://sutochno.ru/front/searchapp/detail/2239413? | Y45: https://www.booking.com/hotel/ge/batumi-view-first-line.html | AA45: TRUE | AB45: TRUE | AC45: TRUE | AG45: нет | AH45: санафан
B46: Светлана | C46: Batumi View | D46: 225 | F46: 1+1 | J46: Выполнено | K46: 7 | L46: TRUE | M46: TRUE | P46: нет | Q46: TRUE | R46: FALSE | S46: TRUE | T46: TRUE | U46: TRUE | V46: TRUE | W46: airbnb.ru/h/bva225 | AA46: TRUE | AB46: FALSE | AC46: TRUE | AG46: нет | AH46: санафан
B47: Светлана | C47: Batumi View | D47: 164 | F47: 1+1 | J47: Выполнено | K47: 7 | L47: TRUE | M47: TRUE | Q47: FALSE | R47: TRUE | S47: TRUE | T47: TRUE | U47: TRUE | V47: TRUE | W47: airbnb.ru/h/bva164 | AA47: TRUE | AB47: FALSE | AC47: TRUE | AG47: нет | AH47: санафан
B48: Светлана | C48: Batumi View | D48: 210 | F48: 1+1 | J48: Выполнено | K48: 7 | L48: TRUE | M48: TRUE | Q48: TRUE | R48: TRUE | S48: TRUE | T48: TRUE | U48: TRUE | V48: TRUE | W48: airbnb.ru/h/bva210 | AA48: TRUE | AB48: FALSE | AC48: TRUE | AG48: нет | AH48: санафан
B49: Светлана | C49: Batumi View | D49: с 0505 | F49: студия | J49: Выполнено | K49: 6 | L49: TRUE | M49: TRUE | N49: С 0505. Чек-лист комплектации апартаментов | P49: Нина | Q49: TRUE | R49: TRUE | S49: TRUE | T49: TRUE | U49: TRUE | V49: TRUE | W49: airbnb.com/h/bvc0505 | AA49: FALSE | AB49: FALSE | AC49: FALSE | AG49: нет | AH49: санафан
B50: Светлана | C50: МетроСити | D50: А708 | E50: Владимир | F50: студия | G50: 46062 | H50: 46083 | I50: =H50-G50 -> 21 | J50: объявление | K50: 7 | L50: TRUE | M50: TRUE | N50: A 708 Metro Чек-лист комплектации апартаментов | O50: мави | P50: нет | Q50: TRUE | R50: TRUE | S50: TRUE | T50: TRUE | U50: TRUE | V50: TRUE | W50: airbnb.com/h/mca708 | AA50: FALSE | AB50: FALSE | AC50: TRUE | AD50: FALSE | AE50: не выполнено | AG50: нет | AH50: от Китайчика
B51: Дина | C51: NА | D51: 3-16 | E51: Павел | F51: студия | G51: 12 март | J51: объявление | K51: 9 | L51: TRUE | M51: TRUE | P51: нет | Q51: TRUE | R51: TRUE | S51: TRUE | T51: TRUE | U51: TRUE | V51: FALSE | AA51: FALSE | AB51: FALSE | AC51: FALSE | AD51: FALSE | AE51: выполнено | AG51: да
A52: 109 | B52: Дина | C52: Шар 8 | D52: 2708 | E52: Михаил | F52: 1+1 | G52: 46092 | J52: хоумстейджинг | K52: 9 | L52: TRUE | M52: TRUE | N52: Шартава 8, 331/2708 27 этаж Чек-лист комплектации апартаментов | O52: мави | P52: Алеся | Q52: FALSE | R52: FALSE | S52: FALSE | T52: FALSE | U52: FALSE | V52: FALSE | AA52: FALSE | AB52: FALSE | AC52: FALSE | AD52: FALSE | AE52: не в полном объеме | AG52: да
A53: =A56+1 -> 111 | B53: Юлия | C53: Порто | D53: 3604 | E53: Денис | F53: студия | G53: 46097 | J53: Ремонт | K53: 9 | L53: TRUE | M53: TRUE | N53: 3604. Чек-лист комплектации апартаментов | O53: мави | P53: Дина | Q53: FALSE | R53: FALSE | S53: FALSE | T53: FALSE | U53: FALSE | V53: FALSE | AA53: FALSE | AB53: FALSE | AC53: FALSE | AD53: FALSE | AG53: да
Q54: FALSE | R54: FALSE | S54: FALSE | T54: FALSE | U54: FALSE | V54: FALSE | AA54: FALSE | AB54: FALSE | AC54: FALSE | AD54: FALSE
Q55: FALSE | R55: FALSE | S55: FALSE | T55: FALSE | U55: FALSE | V55: FALSE | AA55: FALSE | AB55: FALSE | AC55: FALSE | AD55: FALSE
A56: =A52+1 -> 110 | B56: Дина | C56: СМ | E56: Наталья | F56: 1+1 | J56: договор | K56: 5 | L56: TRUE | M56: FALSE | P56: нет | Q56: FALSE | R56: FALSE | S56: FALSE | T56: FALSE | U56: FALSE | V56: FALSE | AA56: FALSE | AB56: FALSE | AC56: FALSE | AD56: FALSE
B57: Юлия | C57: MZ | D57: 1105 | E57: Виктор | F57: студия | J57: договор | K57: 7 | L57: TRUE | M57: FALSE | O57: соб | P57: Алеся | Q57: TRUE | R57: FALSE | S57: FALSE | T57: FALSE | U57: FALSE | V57: FALSE | AA57: FALSE | AB57: FALSE | AC57: FALSE | AD57: FALSE | AG57: нет
B58: Юлия | C58: MZ | D58: 910 | E58: Виктор | F58: студия | J58: договор | K58: 7 | L58: TRUE | M58: FALSE | O58: соб | P58: Алеся | Q58: TRUE | R58: FALSE | S58: FALSE | T58: FALSE | U58: FALSE | V58: FALSE | AA58: FALSE | AB58: FALSE | AC58: FALSE | AD58: FALSE | AG58: нет
Q59: FALSE | R59: FALSE | S59: FALSE | T59: FALSE | U59: FALSE | V59: FALSE | AA59: FALSE | AB59: FALSE | AC59: FALSE | AD59: FALSE
B61: Дина | C61: Blue Sky | D61: 1419 | E61: Марина | F61: студия | G61: 46096 | K61: 9 | L61: TRUE | M61: TRUE | O61: соб | P61: Дина | Q61: FALSE | R61: FALSE | S61: FALSE | T61: FALSE | U61: FALSE | V61: FALSE | AA61: FALSE | AB61: FALSE | AC61: FALSE | AG61: да
B62: Дина | C62: Blue Sky | D62: 2314 | E62: Ольга Чайковски | F62: студия | G62: 46096 | K62: 9 | L62: TRUE | M62: TRUE | O62: соб | P62: Дина | Q62: FALSE | R62: FALSE | S62: FALSE | T62: FALSE | U62: FALSE | V62: FALSE | AA62: FALSE | AB62: FALSE | AC62: FALSE | AG62: нет | AH62: Кауфман
B63: Дина | C63: Blue Sky | D63: 1718 | F63: студия | G63: 46096 | K63: 8 | L63: TRUE | M63: TRUE | Q63: FALSE | R63: FALSE | S63: FALSE | T63: FALSE | U63: FALSE | V63: FALSE | AA63: FALSE | AB63: FALSE | AC63: FALSE | AG63: нет | AH63: Кауфман
B64: Дина | C64: Blue Sky | D64: 2838 | F64: студия | G64: 46096 | K64: 8 | L64: TRUE | M64: TRUE | Q64: FALSE | R64: FALSE | S64: FALSE | T64: FALSE | U64: FALSE | V64: FALSE | AA64: FALSE | AB64: FALSE | AC64: FALSE
B65: Дина | C65: Blue Sky | D65: 2840 | F65: студия | G65: 46096 | K65: 8 | L65: TRUE | M65: TRUE | Q65: FALSE | R65: FALSE | S65: FALSE | T65: FALSE | U65: FALSE | V65: FALSE | AA65: FALSE | AB65: FALSE | AC65: FALSE
C67: ELT | E67: Андрей | F67: студия | G67: 46113 | K67: 7 | L67: TRUE | M67: FALSE
C68: ELT marina | E68: Андрей | F68: студия | G68: 46113 | K68: 7 | L68: TRUE | M68: FALSE
C69: ELT marina | F69: студия | G69: 46113
C70: ELT marina | F70: студия | G70: 46113
C71: ELT marina | F71: студия | G71: 46114
B74: Виталий | C74: DL | D74: 14-1614 | F74: студия | G74: 46143 | K74: 6 | L74: TRUE | M74: TRUE | Q74: FALSE | R74: FALSE | S74: FALSE | T74: FALSE | U74: FALSE | V74: FALSE | AA74: FALSE | AB74: FALSE | AC74: FALSE
B75: Виталий | C75: DL | D75: 13-503 | E75: Газгольдер | F75: 1+1 | G75: 46144 | L75: TRUE | M75: FALSE | Q75: FALSE | R75: FALSE | S75: FALSE | T75: FALSE | U75: FALSE | V75: FALSE | AA75: FALSE | AB75: FALSE | AC75: FALSE
B76: Виталий | C76: DL | D76: 13-507 | E76: Газгольдер | F76: 1+1 | G76: 46145 | L76: TRUE | M76: FALSE | Q76: FALSE | R76: FALSE | S76: FALSE | T76: FALSE | U76: FALSE | V76: FALSE | AA76: FALSE | AB76: FALSE | AC76: FALSE
B77: Виталий | C77: DL | D77: 13-310 | E77: Сергей | F77: студия | G77: 46146 | L77: TRUE | M77: FALSE | Q77: FALSE | R77: FALSE | S77: FALSE | T77: FALSE | U77: FALSE | V77: FALSE | AA77: FALSE | AB77: FALSE | AC77: FALSE | AG77: нет

Sheet Отзывы
F1: авто | G1: авто | H1: мбип | I1: мбип | J1: мбип
E2: Отзывы | F2: Отзывы ARB | I2: Отзывы Суточно | K2: Букинг | M2: карты | O2: Кол-во заселений (по неделям) | AE2: Кол-во отзывов (по неделям)
B3: комплекс | C3: номер | D3: дата | E3: ∑ | F3: кол-во | G3: Ср оц | H3: выбор гостей | I3: кол-во | J3: Ср оц | O3: 1 | P3: 2 | Q3: 3 | R3: 4 | S3: 5 | T3: янв | U3: 6 | V3: 7 | W3: 8 | X3: 9 | Y3: фев | Z3: 10 | AA3: 11 | AB3: 12 | AC3: 13 | AD3: март | AE3: 1 | AF3: 2 | AG3: 3 | AH3: 4 | AI3: 5 | AJ3: январь | AK3: 6 | AL3: 7 | AM3: 8 | AN3: 9 | AO3: февраль | AP3: 10 | AQ3: 11 | AR3: 12 | AS3: 13 | AT3: март
B4: Марина | C4: 1 | WS B 503 | White Sails |1+1 | D4: 45129 | E4: =F4+I4+K4+M4 -> 2 | F4: =IFERROR(VLOOKUP(C4,'Лист20'!$A$1:$C1088,2,0),0) -> 0 | G4: =IFERROR(VLOOKUP(C4,'Лист20'!$A$1:$C1088,3,0),0) -> 0 | H4: FALSE | I4: 2 | J4: 9 | T4: =SUM(O4:S4) -> 0 | Y4: =SUM(U4:X4) -> 0 | AE4: =COUNTIF('выгрузка отзывов'!$B$34:$B$39,C4) -> 0 | AF4: =COUNTIF('выгрузка отзывов'!$B$25:$B$33,C4) -> 0 | AG4: =COUNTIF('выгрузка отзывов'!$B$18:$B$24,C4) -> 0 | AH4: =COUNTIF('выгрузка отзывов'!$B$11:$B$17,C4) -> 0 | AI4: =COUNTIF('выгрузка отзывов'!$B$8:$B$10,C4) -> 0 | AJ4: =SUM(AE4:AI4) -> 0 | AK4: =COUNTIF('выгрузка отзывов'!$B$2:$B$7,$C4) -> 0 | AL4: =COUNTIF('выгрузка отзывов'!$B$2:$B$7,$C4) -> 0 | AM4: =COUNTIF('выгрузка отзывов'!$B$2:$B$7,$C4) -> 0 | AO4: =SUM(AK4:AN4) -> 0
B5: Марина | C5: ='1. Справочник'!C3 -> WS F 907 | D5: 45161 | E5: =F5+I5+K5+M5 -> 8 | F5: =IFERROR(VLOOKUP(C5,'Лист20'!$A$1:$C1088,2,0),0) -> 0 | G5: =IFERROR(VLOOKUP(C5,'Лист20'!$A$1:$C1088,3,0),0) -> 0 | H5: TRUE | I5: 8 | J5: 9.2 | T5: =SUM(O5:S5) -> 0 | Y5: =SUM(U5:X5) -> 0 | AE5: =COUNTIF('выгрузка отзывов'!$B$34:$B$39,C5) -> 0 | AF5: =COUNTIF('выгрузка отзывов'!$B$25:$B$33,C5) -> 0 | AG5: =COUNTIF('выгрузка отзывов'!$B$18:$B$24,C5) -> 0 | AH5: =COUNTIF('выгрузка отзывов'!$B$11:$B$17,C5) -> 0 | AI5: =COUNTIF('выгрузка отзывов'!$B$8:$B$10,C5) -> 0 | AJ5: =SUM(AE5:AI5) -> 0 | AK5: =COUNTIF('выгрузка отзывов'!$B$2:$B$7,$C5) -> 0 | AL5: =COUNTIF('выгрузка отзывов'!$B$2:$B$7,$C5) -> 0 | AM5: =COUNTIF('выгрузка отзывов'!$B$2:$B$7,$C5) -> 0 | AO5: =SUM(AK5:AN5) -> 0
B6: Марина | C6: ='1. Справочник'!C4 -> WS В 212 | D6: 45129 | E6: =F6+I6+K6+M6 -> 14 | F6: =IFERROR(VLOOKUP(C6,'Лист20'!$A$1:$C1088,2,0),0) -> 0 | G6: =IFERROR(VLOOKUP(C6,'Лист20'!$A$1:$C1088,3,0),0) -> 0 | H6: FALSE | I6: 14 | J6: 9.8 | T6: =SUM(O6:S6) -> 0 | Y6: =SUM(U6:X6) -> 0 | AE6: =COUNTIF('выгрузка отзывов'!$B$34:$B$39,C6) -> 0 | AF6: =COUNTIF('выгрузка отзывов'!$B$25:$B$33,C6) -> 0 | AG6: =COUNTIF('выгрузка отзывов'!$B$18:$B$24,C6) -> 0 | AH6: =COUNTIF('выгрузка отзывов'!$B$11:$B$17,C6) -> 0 | AI6: =COUNTIF('выгрузка отзывов'!$B$8:$B$10,C6) -> 0 | AJ6: =SUM(AE6:AI6) -> 0 | AK6: =COUNTIF('выгрузка отзывов'!$B$2:$B$7,$C6) -> 0 | AL6: =COUNTIF('выгрузка отзывов'!$B$2:$B$7,$C6) -> 0 | AM6: =COUNTIF('выгрузка отзывов'!$B$2:$B$7,$C6) -> 0 | AO6: =SUM(AK6:AN6) -> 0
B7: Марина | C7: ='1. Справочник'!C5 -> WS В 1510 | D7: 45283 | E7: =F7+I7+K7+M7 -> 4 | F7: =IFERROR(VLOOKUP(C7,'Лист20'!$A$1:$C1088,2,0),0) -> 0 | G7: =IFERROR(VLOOKUP(C7,'Лист20'!$A$1:$C1088,3,0),0) -> 0 | H7: TRUE | I7: 4 | J7: 9.5 | T7: =SUM(O7:S7) -> 0 | Y7: =SUM(U7:X7) -> 0 | AE7: =COUNTIF('выгрузка отзывов'!$B$34:$B$39,C7) -> 0 | AF7: =COUNTIF('выгрузка отзывов'!$B$25:$B$33,C7) -> 0 | AG7: =COUNTIF('выгрузка отзывов'!$B$18:$B$24,C7) -> 0 | AH7: =COUNTIF('выгрузка отзывов'!$B$11:$B$17,C7) -> 0 | AI7: =COUNTIF('выгрузка отзывов'!$B$8:$B$10,C7) -> 0 | AJ7: =SUM(AE7:AI7) -> 0 | AK7: =COUNTIF('выгрузка отзывов'!$B$2:$B$7,$C7) -> 0 | AL7: =COUNTIF('выгрузка отзывов'!$B$2:$B$7,$C7) -> 0 | AM7: =COUNTIF('выгрузка отзывов'!$B$2:$B$7,$C7) -> 0 | AO7: =SUM(AK7:AN7) -> 0
B8: Марина | C8: ='1. Справочник'!C6 -> WS В 807 | D8: дке 2025 | E8: =F8+I8+K8+M8 -> 0 | F8: =IFERROR(VLOOKUP(C8,'Лист20'!$A$1:$C1088,2,0),0) -> 0 | G8: =IFERROR(VLOOKUP(C8,'Лист20'!$A$1:$C1088,3,0),0) -> 0 | H8: FALSE | T8: =SUM(O8:S8) -> 0 | Y8: =SUM(U8:X8) -> 0 | AE8: =COUNTIF('выгрузка отзывов'!$B$34:$B$39,C8) -> 0 | AF8: =COUNTIF('выгрузка отзывов'!$B$25:$B$33,C8) -> 0 | AG8: =COUNTIF('выгрузка отзывов'!$B$18:$B$24,C8) -> 0 | AH8: =COUNTIF('выгрузка отзывов'!$B$11:$B$17,C8) -> 0 | AI8: =COUNTIF('выгрузка отзывов'!$B$8:$B$10,C8) -> 0 | AJ8: =SUM(AE8:AI8) -> 0 | AK8: =COUNTIF('выгрузка отзывов'!$B$2:$B$7,$C8) -> 0 | AL8: =COUNTIF('выгрузка отзывов'!$B$2:$B$7,$C8) -> 0 | AM8: =COUNTIF('выгрузка отзывов'!$B$2:$B$7,$C8) -> 0 | AO8: =SUM(AK8:AN8) -> 0
B9: Марина | C9: 1 | WS E 1202 | White Sails |1+1 | D9: 45374 | E9: =F9+I9+K9+M9 -> 1 | F9: =IFERROR(VLOOKUP(C9,'Лист20'!$A$1:$C1088,2,0),0) -> 0 | G9: =IFERROR(VLOOKUP(C9,'Лист20'!$A$1:$C1088,3,0),0) -> 0 | H9: TRUE | I9: 1 | J9: 10 | T9: =SUM(O9:S9) -> 0 | Y9: =SUM(U9:X9) -> 0 | AE9: =COUNTIF('выгрузка отзывов'!$B$34:$B$39,C9) -> 0 | AF9: =COUNTIF('выгрузка отзывов'!$B$25:$B$33,C9) -> 1 | AG9: =COUNTIF('выгрузка отзывов'!$B$18:$B$24,C9) -> 0 | AH9: =COUNTIF('выгрузка отзывов'!$B$11:$B$17,C9) -> 0 | AI9: =COUNTIF('выгрузка отзывов'!$B$8:$B$10,C9) -> 0 | AJ9: =SUM(AE9:AI9) -> 1 | AK9: =COUNTIF('выгрузка отзывов'!$B$2:$B$7,$C9) -> 0 | AL9: =COUNTIF('выгрузка отзывов'!$B$2:$B$7,$C9) -> 0 | AM9: =COUNTIF('выгрузка отзывов'!$B$2:$B$7,$C9) -> 0 | AO9: =SUM(AK9:AN9) -> 0
B10: Марина | C10: ='1. Справочник'!C8 -> WS A 409 | D10: 45448 | E10: =F10+I10+K10+M10 -> 0 | F10: =IFERROR(VLOOKUP(C10,'Лист20'!$A$1:$C1088,2,0),0) -> 0 | G10: =IFERROR(VLOOKUP(C10,'Лист20'!$A$1:$C1088,3,0),0) -> 0 | H10: TRUE | I10: 0 | T10: =SUM(O10:S10) -> 0 | Y10: =SUM(U10:X10) -> 0 | AE10: =COUNTIF('выгрузка отзывов'!$B$34:$B$39,C10) -> 0 | AF10: =COUNTIF('выгрузка отзывов'!$B$25:$B$33,C10) -> 0 | AG10: =COUNTIF('выгрузка отзывов'!$B$18:$B$24,C10) -> 0 | AH10: =COUNTIF('выгрузка отзывов'!$B$11:$B$17,C10) -> 0 | AI10: =COUNTIF('выгрузка отзывов'!$B$8:$B$10,C10) -> 0 | AJ10: =SUM(AE10:AI10) -> 0 | AK10: =COUNTIF('выгрузка отзывов'!$B$2:$B$7,$C10) -> 0 | AL10: =COUNTIF('выгрузка отзывов'!$B$2:$B$7,$C10) -> 0 | AM10: =COUNTIF('выгрузка отзывов'!$B$2:$B$7,$C10) -> 0 | AO10: =SUM(AK10:AN10) -> 0
B11: Марина | C11: ='1. Справочник'!C9 -> WS A 608 | D11: 45448 | E11: =F11+I11+K11+M11 -> 0 | F11: =IFERROR(VLOOKUP(C11,'Лист20'!$A$1:$C1088,2,0),0) -> 0 | G11: =IFERROR(VLOOKUP(C11,'Лист20'!$A$1:$C1088,3,0),0) -> 0 | H11: TRUE | I11: 0 | T11: =SUM(O11:S11) -> 0 | Y11: =SUM(U11:X11) -> 0 | AE11: =COUNTIF('выгрузка отзывов'!$B$34:$B$39,C11) -> 0 | AF11: =COUNTIF('выгрузка отзывов'!$B$25:$B$33,C11) -> 0 | AG11: =COUNTIF('выгрузка отзывов'!$B$18:$B$24,C11) -> 0 | AH11: =COUNTIF('выгрузка отзывов'!$B$11:$B$17,C11) -> 0 | AI11: =COUNTIF('выгрузка отзывов'!$B$8:$B$10,C11) -> 0 | AJ11: =SUM(AE11:AI11) -> 0 | AK11: =COUNTIF('выгрузка отзывов'!$B$2:$B$7,$C11) -> 0 | AL11: =COUNTIF('выгрузка отзывов'!$B$2:$B$7,$C11) -> 0 | AM11: =COUNTIF('выгрузка отзывов'!$B$2:$B$7,$C11) -> 0 | AO11: =SUM(AK11:AN11) -> 0
B12: Марина | C12: ='1. Справочник'!C10 -> WS A907 | D12: 45448 | E12: =F12+I12+K12+M12 -> 4 | F12: =IFERROR(VLOOKUP(C12,'Лист20'!$A$1:$C1088,2,0),0) -> 0 | G12: =IFERROR(VLOOKUP(C12,'Лист20'!$A$1:$C1088,3,0),0) -> 0 | H12: FALSE | I12: 4 | J12: 9.8 | T12: =SUM(O12:S12) -> 0 | Y12: =SUM(U12:X12) -> 0 | AE12: =COUNTIF('выгрузка отзывов'!$B$34:$B$39,C12) -> 0 | AF12: =COUNTIF('выгрузка отзывов'!$B$25:$B$33,C12) -> 0 | AG12: =COUNTIF('выгрузка отзывов'!$B$18:$B$24,C12) -> 0 | AH12: =COUNTIF('выгрузка отзывов'!$B$11:$B$17,C12) -> 0 | AI12: =COUNTIF('выгрузка отзывов'!$B$8:$B$10,C12) -> 0 | AJ12: =SUM(AE12:AI12) -> 0 | AK12: =COUNTIF('выгрузка отзывов'!$B$2:$B$7,$C12) -> 0 | AL12: =COUNTIF('выгрузка отзывов'!$B$2:$B$7,$C12) -> 0 | AM12: =COUNTIF('выгрузка отзывов'!$B$2:$B$7,$C12) -> 0 | AO12: =SUM(AK12:AN12) -> 0
B13: Марина | C13: ='1. Справочник'!C11 -> WS Е804 | D13: 45449 | E13: =F13+I13+K13+M13 -> 4 | F13: =IFERROR(VLOOKUP(C13,'Лист20'!$A$1:$C1088,2,0),0) -> 0 | G13: =IFERROR(VLOOKUP(C13,'Лист20'!$A$1:$C1088,3,0),0) -> 0 | H13: TRUE | I13: 4 | J13: 9.7 | T13: =SUM(O13:S13) -> 0 | Y13: =SUM(U13:X13) -> 0 | AE13: =COUNTIF('выгрузка отзывов'!$B$34:$B$39,C13) -> 0 | AF13: =COUNTIF('выгрузка отзывов'!$B$25:$B$33,C13) -> 0 | AG13: =COUNTIF('выгрузка отзывов'!$B$18:$B$24,C13) -> 0 | AH13: =COUNTIF('выгрузка отзывов'!$B$11:$B$17,C13) -> 0 | AI13: =COUNTIF('выгрузка отзывов'!$B$8:$B$10,C13) -> 0 | AJ13: =SUM(AE13:AI13) -> 0 | AK13: =COUNTIF('выгрузка отзывов'!$B$2:$B$7,$C13) -> 0 | AL13: =COUNTIF('выгрузка отзывов'!$B$2:$B$7,$C13) -> 0 | AM13: =COUNTIF('выгрузка отзывов'!$B$2:$B$7,$C13) -> 0 | AO13: =SUM(AK13:AN13) -> 0
B14: Марина | C14: ='1. Справочник'!C12 -> WS E704 | D14: 45448 | E14: =F14+I14+K14+M14 -> 11 | F14: =IFERROR(VLOOKUP(C14,'Лист20'!$A$1:$C1088,2,0),0) -> 0 | G14: =IFERROR(VLOOKUP(C14,'Лист20'!$A$1:$C1088,3,0),0) -> 0 | H14: TRUE | I14: 11 | J14: 9.9 | T14: =SUM(O14:S14) -> 0 | Y14: =SUM(U14:X14) -> 0 | AE14: =COUNTIF('выгрузка отзывов'!$B$34:$B$39,C14) -> 0 | AF14: =COUNTIF('выгрузка отзывов'!$B$25:$B$33,C14) -> 0 | AG14: =COUNTIF('выгрузка отзывов'!$B$18:$B$24,C14) -> 0 | AH14: =COUNTIF('выгрузка отзывов'!$B$11:$B$17,C14) -> 0 | AI14: =COUNTIF('выгрузка отзывов'!$B$8:$B$10,C14) -> 0 | AJ14: =SUM(AE14:AI14) -> 0 | AK14: =COUNTIF('выгрузка отзывов'!$B$2:$B$7,$C14) -> 0 | AL14: =COUNTIF('выгрузка отзывов'!$B$2:$B$7,$C14) -> 0 | AM14: =COUNTIF('выгрузка отзывов'!$B$2:$B$7,$C14) -> 0 | AO14: =SUM(AK14:AN14) -> 0
B15: Марина | C15: ='1. Справочник'!C13 -> WS A805 | D15: июнь 25 | E15: =F15+I15+K15+M15 -> 0 | F15: =IFERROR(VLOOKUP(C15,'Лист20'!$A$1:$C1088,2,0),0) -> 0 | G15: =IFERROR(VLOOKUP(C15,'Лист20'!$A$1:$C1088,3,0),0) -> 0 | H15: FALSE | I15: 0 | T15: =SUM(O15:S15) -> 0 | Y15: =SUM(U15:X15) -> 0 | AE15: =COUNTIF('выгрузка отзывов'!$B$34:$B$39,C15) -> 0 | AF15: =COUNTIF('выгрузка отзывов'!$B$25:$B$33,C15) -> 0 | AG15: =COUNTIF('выгрузка отзывов'!$B$18:$B$24,C15) -> 0 | AH15: =COUNTIF('выгрузка отзывов'!$B$11:$B$17,C15) -> 0 | AI15: =COUNTIF('выгрузка отзывов'!$B$8:$B$10,C15) -> 0 | AJ15: =SUM(AE15:AI15) -> 0 | AK15: =COUNTIF('выгрузка отзывов'!$B$2:$B$7,$C15) -> 0 | AL15: =COUNTIF('выгрузка отзывов'!$B$2:$B$7,$C15) -> 0 | AM15: =COUNTIF('выгрузка отзывов'!$B$2:$B$7,$C15) -> 0 | AO15: =SUM(AK15:AN15) -> 0
B16: Марина | C16: ='1. Справочник'!C14 -> WS F1103 | D16: июнь 25 | E16: =F16+I16+K16+M16 -> 0 | F16: =IFERROR(VLOOKUP(C16,'Лист20'!$A$1:$C1088,2,0),0) -> 0 | G16: =IFERROR(VLOOKUP(C16,'Лист20'!$A$1:$C1088,3,0),0) -> 0 | H16: FALSE | I16: 0 | T16: =SUM(O16:S16) -> 0 | Y16: =SUM(U16:X16) -> 0 | AE16: =COUNTIF('выгрузка отзывов'!$B$34:$B$39,C16) -> 0 | AF16: =COUNTIF('выгрузка отзывов'!$B$25:$B$33,C16) -> 0 | AG16: =COUNTIF('выгрузка отзывов'!$B$18:$B$24,C16) -> 0 | AH16: =COUNTIF('выгрузка отзывов'!$B$11:$B$17,C16) -> 0 | AI16: =COUNTIF('выгрузка отзывов'!$B$8:$B$10,C16) -> 0 | AJ16: =SUM(AE16:AI16) -> 0 | AK16: =COUNTIF('выгрузка отзывов'!$B$2:$B$7,$C16) -> 0 | AO16: =SUM(AK16:AN16) -> 0
B17: Марина | C17: ='1. Справочник'!C15 -> WS F1008 | D17: 45992 | E17: =F17+I17+K17+M17 -> 0 | F17: =IFERROR(VLOOKUP(C17,'Лист20'!$A$1:$C1088,2,0),0) -> 0 | G17: =IFERROR(VLOOKUP(C17,'Лист20'!$A$1:$C1088,3,0),0) -> 0 | H17: FALSE | T17: =SUM(O17:S17) -> 0 | Y17: =SUM(U17:X17) -> 0 | AE17: =COUNTIF('выгрузка отзывов'!$B$34:$B$39,C17) -> 0 | AF17: =COUNTIF('выгрузка отзывов'!$B$25:$B$33,C17) -> 0 | AG17: =COUNTIF('выгрузка отзывов'!$B$18:$B$24,C17) -> 0 | AH17: =COUNTIF('выгрузка отзывов'!$B$11:$B$17,C17) -> 0 | AI17: =COUNTIF('выгрузка отзывов'!$B$8:$B$10,C17) -> 0 | AJ17: =SUM(AE17:AI17) -> 0 | AK17: =COUNTIF('выгрузка отзывов'!$B$2:$B$7,$C17) -> 0 | AO17: =SUM(AK17:AN17) -> 0
B18: Светлана | C18: 1 | BV B 1318 | Batumi View | Studio | D18: 45611 | E18: =F18+I18+K18+M18 -> 1 | F18: =IFERROR(VLOOKUP(C18,'Лист20'!$A$1:$C1088,2,0),0) -> 0 | G18: =IFERROR(VLOOKUP(C18,'Лист20'!$A$1:$C1088,3,0),0) -> 0 | H18: TRUE | I18: 1 | J18: 10 | T18: =SUM(O18:S18) -> 0 | Y18: =SUM(U18:X18) -> 0 | AE18: =COUNTIF('выгрузка отзывов'!$B$34:$B$39,C18) -> 0 | AF18: =COUNTIF('выгрузка отзывов'!$B$25:$B$33,C18) -> 1 | AG18: =COUNTIF('выгрузка отзывов'!$B$18:$B$24,C18) -> 0 | AH18: =COUNTIF('выгрузка отзывов'!$B$11:$B$17,C18) -> 0 | AI18: =COUNTIF('выгрузка отзывов'!$B$8:$B$10,C18) -> 0 | AJ18: =SUM(AE18:AI18) -> 1 | AK18: =COUNTIF('выгрузка отзывов'!$B$2:$B$7,$C18) -> 0 | AO18: =SUM(AK18:AN18) -> 0
B19: Светлана | C19: 1 | BV C 137 | Batumi View | Studio | H19: FALSE | AE19: =COUNTIF('выгрузка отзывов'!$B$34:$B$39,C19) -> 0 | AF19: =COUNTIF('выгрузка отзывов'!$B$25:$B$33,C19) -> 0 | AG19: =COUNTIF('выгрузка отзывов'!$B$18:$B$24,C19) -> 1 | AH19: =COUNTIF('выгрузка отзывов'!$B$11:$B$17,C19) -> 0 | AI19: =COUNTIF('выгрузка отзывов'!$B$8:$B$10,C19) -> 0 | AJ19: =SUM(AE19:AI19) -> 1 | AK19: =COUNTIF('выгрузка отзывов'!$B$2:$B$7,$C19) -> 0
B20: Светлана | C20: 1 | BV A 144 | Batumi View | 1+1 | H20: FALSE | AE20: =COUNTIF('выгрузка отзывов'!$B$34:$B$39,C20) -> 0 | AF20: =COUNTIF('выгрузка отзывов'!$B$25:$B$33,C20) -> 0 | AG20: =COUNTIF('выгрузка отзывов'!$B$18:$B$24,C20) -> 0 | AH20: =COUNTIF('выгрузка отзывов'!$B$11:$B$17,C20) -> 0 | AI20: =COUNTIF('выгрузка отзывов'!$B$8:$B$10,C20) -> 0 | AJ20: =SUM(AE20:AI20) -> 0 | AK20: =COUNTIF('выгрузка отзывов'!$B$2:$B$7,$C20) -> 1
B21: Светлана | C21: 1 | BV A 0514 | Batumi View | Studio | D21: 45566 | E21: =F21+I21+K21+M21 -> 0 | F21: =IFERROR(VLOOKUP(C21,'Лист20'!$A$1:$C1088,2,0),0) -> 0 | G21: =IFERROR(VLOOKUP(C21,'Лист20'!$A$1:$C1088,3,0),0) -> 0 | H21: FALSE | I21: 0 | T21: =SUM(O21:S21) -> 0 | Y21: =SUM(U21:X21) -> 0 | AE21: =COUNTIF('выгрузка отзывов'!$B$34:$B$39,C21) -> 1 | AF21: =COUNTIF('выгрузка отзывов'!$B$25:$B$33,C21) -> 0 | AG21: =COUNTIF('выгрузка отзывов'!$B$18:$B$24,C21) -> 0 | AH21: =COUNTIF('выгрузка отзывов'!$B$11:$B$17,C21) -> 0 | AI21: =COUNTIF('выгрузка отзывов'!$B$8:$B$10,C21) -> 0 | AJ21: =SUM(AE21:AI21) -> 1 | AK21: =COUNTIF('выгрузка отзывов'!$B$2:$B$7,$C21) -> 0 | AO21: =SUM(AK21:AN21) -> 0
B22: Светлана | C22: ='1. Справочник'!C18 -> Steps1123 | D22: 45748 | E22: =F22+I22+K22+M22 -> 0 | F22: =IFERROR(VLOOKUP(C22,'Лист20'!$A$1:$C1088,2,0),0) -> 0 | G22: =IFERROR(VLOOKUP(C22,'Лист20'!$A$1:$C1088,3,0),0) -> 0 | H22: FALSE | I22: 0 | T22: =SUM(O22:S22) -> 0 | Y22: =SUM(U22:X22) -> 0 | AE22: =COUNTIF('выгрузка отзывов'!$B$34:$B$39,C22) -> 0 | AF22: =COUNTIF('выгрузка отзывов'!$B$25:$B$33,C22) -> 0 | AG22: =COUNTIF('выгрузка отзывов'!$B$18:$B$24,C22) -> 0 | AH22: =COUNTIF('выгрузка отзывов'!$B$11:$B$17,C22) -> 0 | AI22: =COUNTIF('выгрузка отзывов'!$B$8:$B$10,C22) -> 0 | AJ22: =SUM(AE22:AI22) -> 0 | AK22: =COUNTIF('выгрузка отзывов'!$B$2:$B$7,$C22) -> 0 | AO22: =SUM(AK22:AN22) -> 0
B23: Светлана | C23: 1 | WH 176 | White House |Studio | D23: 45992 | E23: =F23+I23+K23+M23 -> 0 | F23: =IFERROR(VLOOKUP(C23,'Лист20'!$A$1:$C1088,2,0),0) -> 0 | G23: =IFERROR(VLOOKUP(C23,'Лист20'!$A$1:$C1088,3,0),0) -> 0 | H23: FALSE | T23: =SUM(O23:S23) -> 0 | Y23: =SUM(U23:X23) -> 0 | AE23: =COUNTIF('выгрузка отзывов'!$B$34:$B$39,C23) -> 0 | AF23: =COUNTIF('выгрузка отзывов'!$B$25:$B$33,C23) -> 0 | AG23: =COUNTIF('выгрузка отзывов'!$B$18:$B$24,C23) -> 0 | AH23: =COUNTIF('выгрузка отзывов'!$B$11:$B$17,C23) -> 0 | AI23: =COUNTIF('выгрузка отзывов'!$B$8:$B$10,C23) -> 1 | AJ23: =SUM(AE23:AI23) -> 1 | AK23: =COUNTIF('выгрузка отзывов'!$B$2:$B$7,$C23) -> 0 | AO23: =SUM(AK23:AN23) -> 0
B24: Светлана | C24: ='1. Справочник'!C20 -> OBT 2906 | D24: 45993 | E24: =F24+I24+K24+M24 -> 0 | F24: =IFERROR(VLOOKUP(C24,'Лист20'!$A$1:$C1088,2,0),0) -> 0 | G24: =IFERROR(VLOOKUP(C24,'Лист20'!$A$1:$C1088,3,0),0) -> 0 | T24: =SUM(O24:S24) -> 0 | Y24: =SUM(U24:X24) -> 0 | AE24: =COUNTIF('выгрузка отзывов'!$B$34:$B$39,C24) -> 0 | AF24: =COUNTIF('выгрузка отзывов'!$B$25:$B$33,C24) -> 0 | AG24: =COUNTIF('выгрузка отзывов'!$B$18:$B$24,C24) -> 0 | AH24: =COUNTIF('выгрузка отзывов'!$B$11:$B$17,C24) -> 0 | AI24: =COUNTIF('выгрузка отзывов'!$B$8:$B$10,C24) -> 0 | AJ24: =SUM(AE24:AI24) -> 0 | AK24: =COUNTIF('выгрузка отзывов'!$B$2:$B$7,$C24) -> 0 | AO24: =SUM(AK24:AN24) -> 0
B25: Светлана | C25: 1 | OBT 2908 | Orbi Beach Tower | Studio | D25: 45994 | E25: =F25+I25+K25+M25 -> 0 | F25: =IFERROR(VLOOKUP(C25,'Лист20'!$A$1:$C1088,2,0),0) -> 0 | G25: =IFERROR(VLOOKUP(C25,'Лист20'!$A$1:$C1088,3,0),0) -> 0 | T25: =SUM(O25:S25) -> 0 | Y25: =SUM(U25:X25) -> 0 | AE25: =COUNTIF('выгрузка отзывов'!$B$34:$B$39,C25) -> 0 | AF25: =COUNTIF('выгрузка отзывов'!$B$25:$B$33,C25) -> 1 | AG25: =COUNTIF('выгрузка отзывов'!$B$18:$B$24,C25) -> 0 | AH25: =COUNTIF('выгрузка отзывов'!$B$11:$B$17,C25) -> 0 | AI25: =COUNTIF('выгрузка отзывов'!$B$8:$B$10,C25) -> 0 | AJ25: =SUM(AE25:AI25) -> 1 | AK25: =COUNTIF('выгрузка отзывов'!$B$2:$B$7,$C25) -> 0 | AO25: =SUM(AK25:AN25) -> 0
B26: Светлана | C26: ='1. Справочник'!C22 -> OBT 2910 | D26: 45995 | E26: =F26+I26+K26+M26 -> 0 | F26: =IFERROR(VLOOKUP(C26,'Лист20'!$A$1:$C1088,2,0),0) -> 0 | G26: =IFERROR(VLOOKUP(C26,'Лист20'!$A$1:$C1088,3,0),0) -> 0 | T26: =SUM(O26:S26) -> 0 | Y26: =SUM(U26:X26) -> 0 | AE26: =COUNTIF('выгрузка отзывов'!$B$34:$B$39,C26) -> 0 | AF26: =COUNTIF('выгрузка отзывов'!$B$25:$B$33,C26) -> 0 | AG26: =COUNTIF('выгрузка отзывов'!$B$18:$B$24,C26) -> 0 | AH26: =COUNTIF('выгрузка отзывов'!$B$11:$B$17,C26) -> 0 | AI26: =COUNTIF('выгрузка отзывов'!$B$8:$B$10,C26) -> 0 | AJ26: =SUM(AE26:AI26) -> 0 | AK26: =COUNTIF('выгрузка отзывов'!$B$2:$B$7,$C26) -> 0 | AO26: =SUM(AK26:AN26) -> 0
B27: Дарья | C27: ='1. Справочник'!C68 -> Пиросмани 162 | E27: =F27+I27+K27+M27 -> 0 | T27: =SUM(O27:S27) -> 0 | X27: =SUMIF('Заполняемость'!$C$8:$C1088,$C27,'Заполняемость'!$T$8:$T1088) -> 0 | Y27: =SUM(U27:X27) -> 0 | Z27: =SUMIF('Заполняемость'!$C$8:$C1088,$C27,'Заполняемость'!$T$8:$T1088) -> 0 | AA27: =SUMIF('Заполняемость'!$C$8:$C1088,$C27,'Заполняемость'!$Z$8:$Z1088) -> 0 | AE27: =COUNTIF('выгрузка отзывов'!$B$34:$B$39,C27) -> 0 | AF27: =COUNTIF('выгрузка отзывов'!$B$34:$B$39,C27) -> 0 | AG27: =COUNTIF('выгрузка отзывов'!$B$18:$B$24,C27) -> 0 | AH27: =COUNTIF('выгрузка отзывов'!$B$11:$B$17,C27) -> 0 | AI27: =COUNTIF('выгрузка отзывов'!$B$8:$B$10,C27) -> 0 | AJ27: =SUM(AE27:AI27) -> 0 | AK27: =COUNTIF('выгрузка отзывов'!$B$2:$B$7,$C27) -> 0 | AN27: =SUMIF('Заполняемость'!$C$8:$C1088,$C27,'Заполняемость'!$T$8:$T1088) -> 0 | AO27: =SUM(AK27:AN27) -> 0 | AP27: =SUMIF('Заполняемость'!$C$8:$C1088,$C27,'Заполняемость'!$T$8:$T1088) -> 0 | AQ27: =SUMIF('Заполняемость'!$C$8:$C1088,$C27,'Заполняемость'!$Z$8:$Z1088) -> 0
B28: Дарья | C28: ='1. Справочник'!C69 -> Пиросмани 181 | E28: =F28+I28+K28+M28 -> 0 | F28: 0 | T28: =SUM(O28:S28) -> 0 | X28: =SUMIF('Заполняемость'!$C$8:$C1088,$C28,'Заполняемость'!$T$8:$T1088) -> 0 | Y28: =SUM(U28:X28) -> 0 | Z28: =SUMIF('Заполняемость'!$C$8:$C1088,$C28,'Заполняемость'!$T$8:$T1088) -> 0 | AA28: =SUMIF('Заполняемость'!$C$8:$C1088,$C28,'Заполняемость'!$Z$8:$Z1088) -> 0 | AE28: =COUNTIF('выгрузка отзывов'!$B$34:$B$39,C28) -> 0 | AF28: =COUNTIF('выгрузка отзывов'!$B$34:$B$39,C28) -> 0 | AG28: =COUNTIF('выгрузка отзывов'!$B$18:$B$24,C28) -> 0 | AH28: =COUNTIF('выгрузка отзывов'!$B$11:$B$17,C28) -> 0 | AI28: =COUNTIF('выгрузка отзывов'!$B$8:$B$10,C28) -> 0 | AJ28: =SUM(AE28:AI28) -> 0 | AK28: =COUNTIF('выгрузка отзывов'!$B$2:$B$7,$C28) -> 0 | AN28: =SUMIF('Заполняемость'!$C$8:$C1088,$C28,'Заполняемость'!$T$8:$T1088) -> 0 | AO28: =SUM(AK28:AN28) -> 0 | AP28: =SUMIF('Заполняемость'!$C$8:$C1088,$C28,'Заполняемость'!$T$8:$T1088) -> 0 | AQ28: =SUMIF('Заполняемость'!$C$8:$C1088,$C28,'Заполняемость'!$Z$8:$Z1088) -> 0
B29: Дарья | C29: ='1. Справочник'!C70 -> Pollo 2-2 | E29: =F29+I29+K29+M29 -> 0 | F29: 0 | T29: =SUM(O29:S29) -> 0 | X29: =SUMIF('Заполняемость'!$C$8:$C1088,$C29,'Заполняемость'!$T$8:$T1088) -> 0 | Y29: =SUM(U29:X29) -> 0 | Z29: =SUMIF('Заполняемость'!$C$8:$C1088,$C29,'Заполняемость'!$T$8:$T1088) -> 0 | AA29: =SUMIF('Заполняемость'!$C$8:$C1088,$C29,'Заполняемость'!$Z$8:$Z1088) -> 0 | AE29: =COUNTIF('выгрузка отзывов'!$B$34:$B$39,C29) -> 0 | AF29: =COUNTIF('выгрузка отзывов'!$B$34:$B$39,C29) -> 0 | AG29: =COUNTIF('выгрузка отзывов'!$B$18:$B$24,C29) -> 0 | AH29: =COUNTIF('выгрузка отзывов'!$B$11:$B$17,C29) -> 0 | AI29: =COUNTIF('выгрузка отзывов'!$B$8:$B$10,C29) -> 0 | AJ29: =SUM(AE29:AI29) -> 0 | AK29: =COUNTIF('выгрузка отзывов'!$B$2:$B$7,$C29) -> 0 | AN29: =SUMIF('Заполняемость'!$C$8:$C1088,$C29,'Заполняемость'!$T$8:$T1088) -> 0 | AO29: =SUM(AK29:AN29) -> 0 | AP29: =SUMIF('Заполняемость'!$C$8:$C1088,$C29,'Заполняемость'!$T$8:$T1088) -> 0 | AQ29: =SUMIF('Заполняемость'!$C$8:$C1088,$C29,'Заполняемость'!$Z$8:$Z1088) -> 0
B30: Дарья | C30: ='1. Справочник'!C71 -> Pollo 3-5 | E30: =F30+I30+K30+M30 -> 0 | F30: 0 | G30: =VLOOKUP(C30,'Лист20'!$A$1:$C1088,3,0) -> #NAME? | R30: =SUMIF('Заполняемость'!$C$8:$C1088,C30,'Заполняемость'!$E$8:$E1088) -> 1 | S30: =SUMIF('Заполняемость'!$C$8:$C1088,$C30,'Заполняемость'!$H$8:$H1088) -> 0 | T30: =SUM(O30:S30) -> 1 | U30: =SUMIF('Заполняемость'!$C$8:$C1088,$C30,'Заполняемость'!$K$8:$K1088) -> 0 | V30: =SUMIF('Заполняемость'!$C$8:$C1088,$C30,'Заполняемость'!$N$8:$N1088) -> 0 | W30: =SUMIF('Заполняемость'!$C$8:$C1088,$C30,'Заполняемость'!$Q$8:$Q1088) -> 0 | X30: =SUMIF('Заполняемость'!$C$8:$C1088,$C30,'Заполняемость'!$T$8:$T1088) -> 0 | Y30: =SUM(U30:X30) -> 0 | Z30: =SUMIF('Заполняемость'!$C$8:$C1088,$C30,'Заполняемость'!$T$8:$T1088) -> 0 | AA30: =SUMIF('Заполняемость'!$C$8:$C1088,$C30,'Заполняемость'!$Z$8:$Z1088) -> 0 | AE30: =COUNTIF('выгрузка отзывов'!$B$34:$B$39,C30) -> 0 | AF30: =COUNTIF('выгрузка отзывов'!$B$34:$B$39,C30) -> 0 | AG30: =COUNTIF('выгрузка отзывов'!$B$18:$B$24,C30) -> 0 | AH30: =COUNTIF('выгрузка отзывов'!$B$11:$B$17,C30) -> 0 | AI30: =COUNTIF('выгрузка отзывов'!$B$8:$B$10,C30) -> 0 | AJ30: =SUM(AE30:AI30) -> 0 | AK30: =COUNTIF('выгрузка отзывов'!$B$2:$B$7,$C30) -> 0 | AL30: =SUMIF('Заполняемость'!$C$8:$C1088,$C30,'Заполняемость'!$N$8:$N1088) -> 0 | AM30: =SUMIF('Заполняемость'!$C$8:$C1088,$C30,'Заполняемость'!$Q$8:$Q1088) -> 0 | AN30: =SUMIF('Заполняемость'!$C$8:$C1088,$C30,'Заполняемость'!$T$8:$T1088) -> 0 | AO30: =SUM(AK30:AN30) -> 0 | AP30: =SUMIF('Заполняемость'!$C$8:$C1088,$C30,'Заполняемость'!$T$8:$T1088) -> 0 | AQ30: =SUMIF('Заполняемость'!$C$8:$C1088,$C30,'Заполняемость'!$Z$8:$Z1088) -> 0
B31: Дарья | C31: ='1. Справочник'!C72 -> Polo 4-12 | E31: =F31+I31+K31+M31 -> 0 | F31: 0 | G31: =VLOOKUP(C31,'Лист20'!$A$1:$C1088,3,0) -> #NAME? | R31: =SUMIF('Заполняемость'!$C$8:$C1088,C31,'Заполняемость'!$E$8:$E1088) -> 0 | S31: =SUMIF('Заполняемость'!$C$8:$C1088,$C31,'Заполняемость'!$H$8:$H1088) -> 0 | T31: =SUM(O31:S31) -> 0 | U31: =SUMIF('Заполняемость'!$C$8:$C1088,$C31,'Заполняемость'!$K$8:$K1088) -> 0 | V31: =SUMIF('Заполняемость'!$C$8:$C1088,$C31,'Заполняемость'!$N$8:$N1088) -> 0 | W31: =SUMIF('Заполняемость'!$C$8:$C1088,$C31,'Заполняемость'!$Q$8:$Q1088) -> 0 | X31: =SUMIF('Заполняемость'!$C$8:$C1088,$C31,'Заполняемость'!$T$8:$T1088) -> 0 | Y31: =SUM(U31:X31) -> 0 | Z31: =SUMIF('Заполняемость'!$C$8:$C1088,$C31,'Заполняемость'!$T$8:$T1088) -> 0 | AA31: =SUMIF('Заполняемость'!$C$8:$C1088,$C31,'Заполняемость'!$Z$8:$Z1088) -> 0 | AE31: =COUNTIF('выгрузка отзывов'!$B$34:$B$39,C31) -> 0 | AF31: =COUNTIF('выгрузка отзывов'!$B$34:$B$39,C31) -> 0 | AG31: =COUNTIF('выгрузка отзывов'!$B$18:$B$24,C31) -> 0 | AH31: =COUNTIF('выгрузка отзывов'!$B$11:$B$17,C31) -> 0 | AI31: =COUNTIF('выгрузка отзывов'!$B$8:$B$10,C31) -> 0 | AJ31: =SUM(AE31:AI31) -> 0 | AK31: =COUNTIF('выгрузка отзывов'!$B$2:$B$7,$C31) -> 0 | AL31: =SUMIF('Заполняемость'!$C$8:$C1088,$C31,'Заполняемость'!$N$8:$N1088) -> 0 | AM31: =SUMIF('Заполняемость'!$C$8:$C1088,$C31,'Заполняемость'!$Q$8:$Q1088) -> 0 | AN31: =SUMIF('Заполняемость'!$C$8:$C1088,$C31,'Заполняемость'!$T$8:$T1088) -> 0 | AO31: =SUM(AK31:AN31) -> 0 | AP31: =SUMIF('Заполняемость'!$C$8:$C1088,$C31,'Заполняемость'!$T$8:$T1088) -> 0 | AQ31: =SUMIF('Заполняемость'!$C$8:$C1088,$C31,'Заполняемость'!$Z$8:$Z1088) -> 0
C32: 20 | E32: =F32+I32+K32+M32 -> 49 | F32: =SUM(F4:F22) -> 0 | I32: =SUM(I4:I22) -> 49 | O32: =SUM(O4:O21) -> 0 | P32: =SUM(P4:P21) -> 0 | Q32: =SUM(Q4:Q21) -> 0 | R32: =SUM(R4:R21) -> 0 | S32: =SUM(S4:S21) -> 0 | T32: =SUM(T4:T21) -> 0 | U32: =SUM(U4:U21) -> 0 | V32: =SUM(V4:V21) -> 0 | ... AD32: =SUM(AD4:AD21) -> 0 | AE32: =SUM(AE4:AE26) -> 1 | AF32: =SUM(AF4:AF26) -> 3 | AG32: =SUM(AG4:AG26) -> 1 | AH32: =SUM(AH4:AH26) -> 0 | AI32: =SUM(AI4:AI26) -> 1 | AJ32: =SUM(AJ4:AJ26) -> 6 | AK32: =SUM(AK4:AK26) -> 1 | AL32: =SUM(AL4:AL26) -> 0 | ... AT32: =SUM(AT4:AT26) -> 0
B33: Борис | C33: 2 | Orbi C 1125 | Orbi Sity | Studio | D33: 2024 | E33: =F33+I33+K33+M33 -> 4 | F33: =IFERROR(VLOOKUP(C33,'Лист20'!$A$1:$C1088,2,0),0) -> 0 | G33: =IFERROR(VLOOKUP(C33,'Лист20'!$A$1:$C1088,3,0),0) -> 0 | H33: TRUE | I33: 4 | J33: 10 | T33: =SUM(O33:S33) -> 0 | Y33: =SUM(U33:X33) -> 0 | AE33: =COUNTIF('выгрузка отзывов'!$B$34:$B$39,C33) -> 0 | AF33: =COUNTIF('выгрузка отзывов'!$B$25:$B$33,C33) -> 0 | AG33: =COUNTIF('выгрузка отзывов'!$B$18:$B$24,C33) -> 0 | AH33: =COUNTIF('выгрузка отзывов'!$B$11:$B$17,C33) -> 1 | AI33: =COUNTIF('выгрузка отзывов'!$B$8:$B$10,C33) -> 0 | AJ33: =SUM(AE33:AI33) -> 1 | AK33: =COUNTIF('выгрузка отзывов'!$B$2:$B$7,$C33) -> 0 | AO33: =SUM(AK33:AN33) -> 0
B34: Борис | C34: ='1. Справочник'!C35 -> С 1443 | D34: 2024 | E34: =F34+I34+K34+M34 -> 6 | F34: =IFERROR(VLOOKUP(C34,'Лист20'!$A$1:$C1088,2,0),0) -> 0 | G34: =IFERROR(VLOOKUP(C34,'Лист20'!$A$1:$C1088,3,0),0) -> 0 | H34: TRUE | I34: 6 | J34: 9.8 | T34: =SUM(O34:S34) -> 0 | Y34: =SUM(U34:X34) -> 0 | AE34: =COUNTIF('выгрузка отзывов'!$B$34:$B$39,C34) -> 0 | AF34: =COUNTIF('выгрузка отзывов'!$B$25:$B$33,C34) -> 0 | AG34: =COUNTIF('выгрузка отзывов'!$B$18:$B$24,C34) -> 0 | AH34: =COUNTIF('выгрузка отзывов'!$B$11:$B$17,C34) -> 0 | AI34: =COUNTIF('выгрузка отзывов'!$B$8:$B$10,C34) -> 0 | AJ34: =SUM(AE34:AI34) -> 0 | AK34: =COUNTIF('выгрузка отзывов'!$B$2:$B$7,$C34) -> 0 | AO34: =SUM(AK34:AN34) -> 0
B35: Борис | C35: ='1. Справочник'!C36 -> C 4245 | D35: 2024 | E35: =F35+I35+K35+M35 -> 12 | F35: =IFERROR(VLOOKUP(C35,'Лист20'!$A$1:$C1088,2,0),0) -> 0 | G35: =IFERROR(VLOOKUP(C35,'Лист20'!$A$1:$C1088,3,0),0) -> 0 | H35: TRUE | I35: 12 | J35: 9.6 | T35: =SUM(O35:S35) -> 0 | Y35: =SUM(U35:X35) -> 0 | AE35: =COUNTIF('выгрузка отзывов'!$B$34:$B$39,C35) -> 0 | AF35: =COUNTIF('выгрузка отзывов'!$B$25:$B$33,C35) -> 0 | AG35: =COUNTIF('выгрузка отзывов'!$B$18:$B$24,C35) -> 0 | AH35: =COUNTIF('выгрузка отзывов'!$B$11:$B$17,C35) -> 0 | AI35: =COUNTIF('выгрузка отзывов'!$B$8:$B$10,C35) -> 0 | AJ35: =SUM(AE35:AI35) -> 0 | AK35: =COUNTIF('выгрузка отзывов'!$B$2:$B$7,$C35) -> 0 | AO35: =SUM(AK35:AN35) -> 0
B36: Борис | C36: ='1. Справочник'!C37 -> А 4049 | D36: 2024 | E36: =F36+I36+K36+M36 -> 4 | F36: =IFERROR(VLOOKUP(C36,'Лист20'!$A$1:$C1088,2,0),0) -> 0 | G36: =IFERROR(VLOOKUP(C36,'Лист20'!$A$1:$C1088,3,0),0) -> 0 | H36: TRUE | I36: 4 | J36: 10 | T36: =SUM(O36:S36) -> 0 | Y36: =SUM(U36:X36) -> 0 | AE36: =COUNTIF('выгрузка отзывов'!$B$34:$B$39,C36) -> 0 | AF36: =COUNTIF('выгрузка отзывов'!$B$25:$B$33,C36) -> 0 | AG36: =COUNTIF('выгрузка отзывов'!$B$18:$B$24,C36) -> 0 | AH36: =COUNTIF('выгрузка отзывов'!$B$11:$B$17,C36) -> 0 | AI36: =COUNTIF('выгрузка отзывов'!$B$8:$B$10,C36) -> 0 | AJ36: =SUM(AE36:AI36) -> 0 | AK36: =COUNTIF('выгрузка отзывов'!$B$2:$B$7,$C36) -> 0 | AO36: =SUM(AK36:AN36) -> 0
B37: Борис | C37: ='1. Справочник'!C39 -> С 2756 | D37: 2024 | E37: =F37+I37+K37+M37 -> 0 | F37: =IFERROR(VLOOKUP(C37,'Лист20'!$A$1:$C1088,2,0),0) -> 0 | G37: =IFERROR(VLOOKUP(C37,'Лист20'!$A$1:$C1088,3,0),0) -> 0 | H37: TRUE | I37: 0 | T37: =SUM(O37:S37) -> 0 | Y37: =SUM(U37:X37) -> 0 | AE37: =COUNTIF('выгрузка отзывов'!$B$34:$B$39,C37) -> 0 | AF37: =COUNTIF('выгрузка отзывов'!$B$25:$B$33,C37) -> 0 | AG37: =COUNTIF('выгрузка отзывов'!$B$18:$B$24,C37) -> 0 | AH37: =COUNTIF('выгрузка отзывов'!$B$11:$B$17,C37) -> 0 | AI37: =COUNTIF('выгрузка отзывов'!$B$8:$B$10,C37) -> 0 | AJ37: =SUM(AE37:AI37) -> 0 | AK37: =COUNTIF('выгрузка отзывов'!$B$2:$B$7,$C37) -> 0 | AO37: =SUM(AK37:AN37) -> 0
B38: Борис | C38: 2 | Orbi D1 1321 | Orbi Sity | Studio | D38: 2024 | E38: =F38+I38+K38+M38 -> 10 | F38: =IFERROR(VLOOKUP(C38,'Лист20'!$A$1:$C1088,2,0),0) -> 0 | G38: =IFERROR(VLOOKUP(C38,'Лист20'!$A$1:$C1088,3,0),0) -> 0 | H38: TRUE | I38: 10 | J38: 9.6 | T38: =SUM(O38:S38) -> 0 | Y38: =SUM(U38:X38) -> 0 | AE38: =COUNTIF('выгрузка отзывов'!$B$34:$B$39,C38) -> 0 | AF38: =COUNTIF('выгрузка отзывов'!$B$25:$B$33,C38) -> 0 | AG38: =COUNTIF('выгрузка отзывов'!$B$18:$B$24,C38) -> 0 | AH38: =COUNTIF('выгрузка отзывов'!$B$11:$B$17,C38) -> 0 | AI38: =COUNTIF('выгрузка отзывов'!$B$8:$B$10,C38) -> 0 | AJ38: =SUM(AE38:AI38) -> 0 | AK38: =COUNTIF('выгрузка отзывов'!$B$2:$B$7,$C38) -> 1 | AO38: =SUM(AK38:AN38) -> 1
B39: Борис | C39: 2 | Orbi D2 1625 | Orbi Sity | 1+1 | E39: =F39+I39+K39+M39 -> 4 | F39: =IFERROR(VLOOKUP(C39,'Лист20'!$A$1:$C1088,2,0),0) -> 0 | G39: =IFERROR(VLOOKUP(C39,'Лист20'!$A$1:$C1088,3,0),0) -> 0 | H39: TRUE | I39: 4 | J39: 9.9 | T39: =SUM(O39:S39) -> 0 | Y39: =SUM(U39:X39) -> 0 | AE39: =COUNTIF('выгрузка отзывов'!$B$34:$B$39,C39) -> 0 | AF39: =COUNTIF('выгрузка отзывов'!$B$25:$B$33,C39) -> 0 | AG39: =COUNTIF('выгрузка отзывов'!$B$18:$B$24,C39) -> 0 | AH39: =COUNTIF('выгрузка отзывов'!$B$11:$B$17,C39) -> 0 | AI39: =COUNTIF('выгрузка отзывов'!$B$8:$B$10,C39) -> 0 | AJ39: =SUM(AE39:AI39) -> 0 | AK39: =COUNTIF('выгрузка отзывов'!$B$2:$B$7,$C39) -> 0 | AO39: =SUM(AK39:AN39) -> 0
B40: Борис | C40: 2 | Orbi D2 3216 | Orbi Sity | 1+1 | E40: =F40+I40+K40+M40 -> 3 | F40: =IFERROR(VLOOKUP(C40,'Лист20'!$A$1:$C1088,2,0),0) -> 0 | G40: =IFERROR(VLOOKUP(C40,'Лист20'!$A$1:$C1088,3,0),0) -> 0 | H40: TRUE | I40: 3 | J40: 9.9 | T40: =SUM(O40:S40) -> 0 | Y40: =SUM(U40:X40) -> 0 | AE40: =COUNTIF('выгрузка отзывов'!$B$34:$B$39,C40) -> 1 | AF40: =COUNTIF('выгрузка отзывов'!$B$25:$B$33,C40) -> 0 | AG40: =COUNTIF('выгрузка отзывов'!$B$18:$B$24,C40) -> 0 | AH40: =COUNTIF('выгрузка отзывов'!$B$11:$B$17,C40) -> 0 | AI40: =COUNTIF('выгрузка отзывов'!$B$8:$B$10,C40) -> 0 | AJ40: =SUM(AE40:AI40) -> 1 | AK40: =COUNTIF('выгрузка отзывов'!$B$2:$B$7,$C40) -> 0 | AO40: =SUM(AK40:AN40) -> 0
B41: Борис | C41: 2 | Orbi D1 3902 | Orbi Sity | 1+1 | E41: =F41+I41+K41+M41 -> 3 | F41: =IFERROR(VLOOKUP(C41,'Лист20'!$A$1:$C1088,2,0),0) -> 0 | G41: =IFERROR(VLOOKUP(C41,'Лист20'!$A$1:$C1088,3,0),0) -> 0 | H41: TRUE | I41: 3 | J41: 9.1 | T41: =SUM(O41:S41) -> 0 | Y41: =SUM(U41:X41) -> 0 | AE41: =COUNTIF('выгрузка отзывов'!$B$34:$B$39,C41) -> 2 | AF41: =COUNTIF('выгрузка отзывов'!$B$25:$B$33,C41) -> 1 | AG41: =COUNTIF('выгрузка отзывов'!$B$18:$B$24,C41) -> 0 | AH41: =COUNTIF('выгрузка отзывов'!$B$11:$B$17,C41) -> 0 | AI41: =COUNTIF('выгрузка отзывов'!$B$8:$B$10,C41) -> 0 | AJ41: =SUM(AE41:AI41) -> 3 | AK41: =COUNTIF('выгрузка отзывов'!$B$2:$B$7,$C41) -> 1 | AO41: =SUM(AK41:AN41) -> 1
B42: Борис | C42: ='1. Справочник'!C44 -> D2 503 | D42: июль 25 | E42: =F42+I42+K42+M42 -> 1 | F42: =IFERROR(VLOOKUP(C42,'Лист20'!$A$1:$C1088,2,0),0) -> 0 | G42: =IFERROR(VLOOKUP(C42,'Лист20'!$A$1:$C1088,3,0),0) -> 0 | H42: FALSE | I42: 1 | J42: 10 | T42: =SUM(O42:S42) -> 0 | Y42: =SUM(U42:X42) -> 0 | AE42: =COUNTIF('выгрузка отзывов'!$B$34:$B$39,C42) -> 0 | AF42: =COUNTIF('выгрузка отзывов'!$B$25:$B$33,C42) -> 0 | AG42: =COUNTIF('выгрузка отзывов'!$B$18:$B$24,C42) -> 0 | AH42: =COUNTIF('выгрузка отзывов'!$B$11:$B$17,C42) -> 0 | AI42: =COUNTIF('выгрузка отзывов'!$B$8:$B$10,C42) -> 0 | AJ42: =SUM(AE42:AI42) -> 0 | AK42: =COUNTIF('выгрузка отзывов'!$B$2:$B$7,$C42) -> 0 | AO42: =SUM(AK42:AN42) -> 0
C43: 12 | E43: =F43+I43+K43+M43 -> 47 | F43: =F37+F41+F40+F39+F38+F36+F35+F34+F33+F42 -> 0 | I43: =SUM(I33:I42) -> 47 | O43: =SUM(O33:O42) -> 0 | P43: =SUM(P33:P42) -> 0 | Q43: =SUM(Q33:Q42) -> 0 | R43: =SUM(R33:R42) -> 0 | S43: =SUM(S33:S42) -> 0 | T43: =SUM(T33:T42) -> 0 | U43: =SUM(U33:U42) -> 0 | V43: =SUM(V33:V42) -> 0 | ... AT43: =SUM(AT33:AT42) -> 0
B44: Юлия | C44: 2 | Mar 1604 | Courtyard by Marriott | 1+1 | D44: 2024 | E44: =F44+I44+K44+M44 -> 0 | F44: =IFERROR(VLOOKUP(C44,'Лист20'!$A$1:$C1088,2,0),0) -> 0 | G44: =IFERROR(VLOOKUP(C44,'Лист20'!$A$1:$C1088,3,0),0) -> 0 | H44: TRUE | I44: 0 | T44: 1 | Y44: 0 | AE44: =COUNTIF('выгрузка отзывов'!$B$34:$B$39,C44) -> 0 | AF44: =COUNTIF('выгрузка отзывов'!$B$25:$B$33,C44) -> 0 | AG44: =COUNTIF('выгрузка отзывов'!$B$18:$B$24,C44) -> 0 | AH44: =COUNTIF('выгрузка отзывов'!$B$11:$B$17,C44) -> 1 | AI44: =COUNTIF('выгрузка отзывов'!$B$8:$B$10,C44) -> 0 | AJ44: =SUM(AE44:AI44) -> 1 | AK44: =COUNTIF('выгрузка отзывов'!$B$2:$B$7,$C44) -> 0 | AO44: =SUM(AK44:AN44) -> 0
B45: Юлия | C45: 2 | Mar 1606 | Courtyard by Marriott | Studio | D45: 2024 | E45: =F45+I45+K45+M45 -> 0 | F45: =IFERROR(VLOOKUP(C45,'Лист20'!$A$1:$C1088,2,0),0) -> 0 | G45: =IFERROR(VLOOKUP(C45,'Лист20'!$A$1:$C1088,3,0),0) -> 0 | H45: TRUE | I45: 0 | T45: 2 | Y45: 1 | AE45: =COUNTIF('выгрузка отзывов'!$B$34:$B$39,C45) -> 0 | AF45: =COUNTIF('выгрузка отзывов'!$B$25:$B$33,C45) -> 2 | AG45: =COUNTIF('выгрузка отзывов'!$B$18:$B$24,C45) -> 1 | AH45: =COUNTIF('выгрузка отзывов'!$B$11:$B$17,C45) -> 0 | AI45: =COUNTIF('выгрузка отзывов'!$B$8:$B$10,C45) -> 1 | AJ45: =SUM(AE45:AI45) -> 4 | AK45: =COUNTIF('выгрузка отзывов'!$B$2:$B$7,$C45) -> 0 | AO45: =SUM(AK45:AN45) -> 0
B46: Юлия | C46: ='1. Справочник'!C47 -> CM 1931 | D46: 2024 | E46: =F46+I46+K46+M46 -> 7 | F46: =IFERROR(VLOOKUP(C46,'Лист20'!$A$1:$C1088,2,0),0) -> 0 | G46: =IFERROR(VLOOKUP(C46,'Лист20'!$A$1:$C1088,3,0),0) -> 0 | H46: TRUE | I46: 7 | J46: 9.9 | T46: 1 | Y46: =SUM(U46:X46) -> 0 | AE46: =COUNTIF('выгрузка отзывов'!$B$34:$B$39,C46) -> 0 | AF46: =COUNTIF('выгрузка отзывов'!$B$25:$B$33,C46) -> 0 | AG46: =COUNTIF('выгрузка отзывов'!$B$18:$B$24,C46) -> 0 | AH46: =COUNTIF('выгрузка отзывов'!$B$11:$B$17,C46) -> 0 | AI46: =COUNTIF('выгрузка отзывов'!$B$8:$B$10,C46) -> 0 | AJ46: =SUM(AE46:AI46) -> 0 | AK46: =COUNTIF('выгрузка отзывов'!$B$2:$B$7,$C46) -> 0 | AO46: =SUM(AK46:AN46) -> 0
B47: Юлия | C47: 2 | Mar 1304 | Courtyard by Marriott | 1+1 | D47: 45931 | E47: =F47+I47+K47+M47 -> 0 | F47: =IFERROR(VLOOKUP(C47,'Лист20'!$A$1:$C1088,2,0),0) -> 0 | G47: =IFERROR(VLOOKUP(C47,'Лист20'!$A$1:$C1088,3,0),0) -> 0 | H47: TRUE | T47: 2 | Y47: 1 | AE47: =COUNTIF('выгрузка отзывов'!$B$34:$B$39,C47) -> 0 | AF47: =COUNTIF('выгрузка отзывов'!$B$25:$B$33,C47) -> 0 | AG47: =COUNTIF('выгрузка отзывов'!$B$18:$B$24,C47) -> 1 | AH47: =COUNTIF('выгрузка отзывов'!$B$11:$B$17,C47) -> 0 | AI47: =COUNTIF('выгрузка отзывов'!$B$8:$B$10,C47) -> 0 | AJ47: =SUM(AE47:AI47) -> 1 | AK47: =COUNTIF('выгрузка отзывов'!$B$2:$B$7,$C47) -> 0 | AO47: =SUM(AK47:AN47) -> 0
B48: Юлия | C48: 2 | Mar 1327 | Courtyard by Marriott | 1+1 | H48: FALSE | T48: 4 | Y48: 3 | AE48: =COUNTIF('выгрузка отзывов'!$B$34:$B$39,C48) -> 0 | AF48: =COUNTIF('выгрузка отзывов'!$B$25:$B$33,C48) -> 1 | AG48: =COUNTIF('выгрузка отзывов'!$B$18:$B$24,C48) -> 1 | AH48: =COUNTIF('выгрузка отзывов'!$B$11:$B$17,C48) -> 0 | AI48: =COUNTIF('выгрузка отзывов'!$B$8:$B$10,C48) -> 0 | AJ48: =SUM(AE48:AI48) -> 2 | AK48: =COUNTIF('выгрузка отзывов'!$B$2:$B$7,$C48) -> 1
B49: Юлия | C49: 3 | PT 2604 | Old town | Studio | D49: 45772 | E49: =F49+I49+K49+M49 -> 2 | F49: =IFERROR(VLOOKUP(C49,'Лист20'!$A$1:$C1088,2,0),0) -> 0 | G49: =IFERROR(VLOOKUP(C49,'Лист20'!$A$1:$C1088,3,0),0) -> 0 | H49: TRUE | I49: 2 | J49: 10 | T49: =SUM(O49:S49) -> 0 | Y49: =SUM(U49:X49) -> 0 | AE49: =COUNTIF('выгрузка отзывов'!$B$34:$B$39,C49) -> 0 | AF49: =COUNTIF('выгрузка отзывов'!$B$25:$B$33,C49) -> 0 | AG49: =COUNTIF('выгрузка отзывов'!$B$18:$B$24,C49) -> 0 | AH49: =COUNTIF('выгрузка отзывов'!$B$11:$B$17,C49) -> 0 | AI49: =COUNTIF('выгрузка отзывов'!$B$8:$B$10,C49) -> 0 | AJ49: =SUM(AE49:AI49) -> 0 | AK49: =COUNTIF('выгрузка отзывов'!$B$2:$B$7,$C49) -> 0 | AO49: =SUM(AK49:AN49) -> 0
B50: Юлия | C50: 3 | PT 2704 | Old town | Studio | D50: 45772 | E50: =F50+I50+K50+M50 -> 0 | F50: =IFERROR(VLOOKUP(C50,'Лист20'!$A$1:$C1088,2,0),0) -> 0 | G50: =IFERROR(VLOOKUP(C50,'Лист20'!$A$1:$C1088,3,0),0) -> 0 | H50: TRUE | I50: 0 | T50: 5 | Y50: 1 | AE50: =COUNTIF('выгрузка отзывов'!$B$34:$B$39,C50) -> 0 | AF50: =COUNTIF('выгрузка отзывов'!$B$25:$B$33,C50) -> 1 | AG50: =COUNTIF('выгрузка отзывов'!$B$18:$B$24,C50) -> 2 | AH50: =COUNTIF('выгрузка отзывов'!$B$11:$B$17,C50) -> 0 | AI50: =COUNTIF('выгрузка отзывов'!$B$8:$B$10,C50) -> 1 | AJ50: =SUM(AE50:AI50) -> 4 | AK50: =COUNTIF('выгрузка отзывов'!$B$2:$B$7,$C50) -> 1 | AO50: 2
B51: Юлия | C51: 4 | MZ 718 | Mziuri Gardens | Studio | D51: 45773 | E51: =F51+I51+K51+M51 -> 3 | F51: =IFERROR(VLOOKUP(C51,'Лист20'!$A$1:$C1088,2,0),0) -> 0 | G51: =IFERROR(VLOOKUP(C51,'Лист20'!$A$1:$C1088,3,0),0) -> 0 | H51: TRUE | I51: 3 | J51: 10 | T51: 1 | Y51: =SUM(U51:X51) -> 0 | AE51: =COUNTIF('выгрузка отзывов'!$B$34:$B$39,C51) -> 0 | AF51: =COUNTIF('выгрузка отзывов'!$B$25:$B$33,C51) -> 0 | AG51: =COUNTIF('выгрузка отзывов'!$B$18:$B$24,C51) -> 0 | AH51: =COUNTIF('выгрузка отзывов'!$B$11:$B$17,C51) -> 1 | AI51: =COUNTIF('выгрузка отзывов'!$B$8:$B$10,C51) -> 0 | AJ51: =SUM(AE51:AI51) -> 1 | AK51: =COUNTIF('выгрузка отзывов'!$B$2:$B$7,$C51) -> 0 | AO51: =SUM(AK51:AN51) -> 0
B52: Юлия | C52: 4 | MZ 913 | Mziuri Gardens | Studio | D52: 45774 | E52: =F52+I52+K52+M52 -> 0 | F52: =IFERROR(VLOOKUP(C52,'Лист20'!$A$1:$C1088,2,0),0) -> 0 | G52: =IFERROR(VLOOKUP(C52,'Лист20'!$A$1:$C1088,3,0),0) -> 0 | H52: TRUE | T52: 1 | Y52: 3 | AE52: =COUNTIF('выгрузка отзывов'!$B$34:$B$39,C52) -> 0 | AF52: =COUNTIF('выгрузка отзывов'!$B$25:$B$33,C52) -> 0 | AG52: =COUNTIF('выгрузка отзывов'!$B$18:$B$24,C52) -> 0 | AH52: =COUNTIF('выгрузка отзывов'!$B$11:$B$17,C52) -> 0 | AI52: =COUNTIF('выгрузка отзывов'!$B$8:$B$10,C52) -> 0 | AJ52: =SUM(AE52:AI52) -> 0 | AK52: =COUNTIF('выгрузка отзывов'!$B$2:$B$7,$C52) -> 1 | AO52: 3
B53: Юлия | C53: ='1. Справочник'!C65 -> MZ 1408 | D53: июль 25 | E53: =F53+I53+K53+M53 -> 2 | F53: =IFERROR(VLOOKUP(C53,'Лист20'!$A$1:$C1088,2,0),0) -> 0 | G53: =IFERROR(VLOOKUP(C53,'Лист20'!$A$1:$C1088,3,0),0) -> 0 | H53: TRUE | I53: 2 | J53: 9.8 | T53: 1 | Y53: 1 | AE53: =COUNTIF('выгрузка отзывов'!$B$34:$B$39,C53) -> 0 | AF53: =COUNTIF('выгрузка отзывов'!$B$25:$B$33,C53) -> 0 | AG53: =COUNTIF('выгрузка отзывов'!$B$18:$B$24,C53) -> 0 | AH53: =COUNTIF('выгрузка отзывов'!$B$11:$B$17,C53) -> 0 | AI53: =COUNTIF('выгрузка отзывов'!$B$8:$B$10,C53) -> 0 | AJ53: =SUM(AE53:AI53) -> 0 | AK53: =COUNTIF('выгрузка отзывов'!$B$2:$B$7,$C53) -> 0 | AO53: 1
B54: Юлия | C54: ='1. Справочник'!C66 -> MZ А 1113 | D54: 45931 | E54: =F54+I54+K54+M54 -> 0 | F54: =IFERROR(VLOOKUP(C54,'Лист20'!$A$1:$C1088,2,0),0) -> 0 | G54: =IFERROR(VLOOKUP(C54,'Лист20'!$A$1:$C1088,3,0),0) -> 0 | H54: FALSE | T54: =SUM(O54:S54) -> 0 | Y54: =SUM(U54:X54) -> 0 | AE54: =COUNTIF('выгрузка отзывов'!$B$34:$B$39,C54) -> 0 | AF54: =COUNTIF('выгрузка отзывов'!$B$25:$B$33,C54) -> 0 | AG54: =COUNTIF('выгрузка отзывов'!$B$18:$B$24,C54) -> 0 | AH54: =COUNTIF('выгрузка отзывов'!$B$11:$B$17,C54) -> 0 | AI54: =COUNTIF('выгрузка отзывов'!$B$8:$B$10,C54) -> 0 | AJ54: =SUM(AE54:AI54) -> 0 | AK54: =COUNTIF('выгрузка отзывов'!$B$2:$B$7,$C54) -> 0 | AO54: =SUM(AK54:AN54) -> 0
B55: Юлия | C55: 2 | BG 227 | Bagrationi Residence | 2+1 | H55: FALSE | AE55: =COUNTIF('выгрузка отзывов'!$B$34:$B$39,C55) -> 0 | AF55: =COUNTIF('выгрузка отзывов'!$B$25:$B$33,C55) -> 0 | AG55: =COUNTIF('выгрузка отзывов'!$B$18:$B$24,C55) -> 0 | AH55: =COUNTIF('выгрузка отзывов'!$B$11:$B$17,C55) -> 1 | AI55: =COUNTIF('выгрузка отзывов'!$B$8:$B$10,C55) -> 0 | AJ55: =SUM(AE55:AI55) -> 1 | AK55: =COUNTIF('выгрузка отзывов'!$B$2:$B$7,$C55) -> 0
B56: Юлия | C56: 3 | DZ 12 | Old town | 1+1 | H56: TRUE | T56: 3 | Y56: 1 | AE56: =COUNTIF('выгрузка отзывов'!$B$34:$B$39,C56) -> 1 | AF56: =COUNTIF('выгрузка отзывов'!$B$25:$B$33,C56) -> 0 | AG56: =COUNTIF('выгрузка отзывов'!$B$18:$B$24,C56) -> 1 | AH56: =COUNTIF('выгрузка отзывов'!$B$11:$B$17,C56) -> 1 | AI56: =COUNTIF('выгрузка отзывов'!$B$8:$B$10,C56) -> 0 | AJ56: =SUM(AE56:AI56) -> 3 | AK56: =COUNTIF('выгрузка отзывов'!$B$2:$B$7,$C56) -> 0
B57: Юлия | C57: ='1. Справочник'!C60 -> NW 2-5 | D57: июль 25 | E57: =F57+I57+K57+M57 -> 0 | F57: =IFERROR(VLOOKUP(C57,'Лист20'!$A$1:$C1088,2,0),0) -> 0 | G57: =IFERROR(VLOOKUP(C57,'Лист20'!$A$1:$C1088,3,0),0) -> 0 | H57: FALSE | T57: =SUM(O57:S57) -> 0 | Y57: =SUM(U57:X57) -> 0 | AE57: =COUNTIF('выгрузка отзывов'!$B$34:$B$39,C57) -> 0 | AF57: =COUNTIF('выгрузка отзывов'!$B$25:$B$33,C57) -> 0 | AG57: =COUNTIF('выгрузка отзывов'!$B$18:$B$24,C57) -> 0 | AH57: =COUNTIF('выгрузка отзывов'!$B$11:$B$17,C57) -> 0 | AI57: =COUNTIF('выгрузка отзывов'!$B$8:$B$10,C57) -> 0 | AJ57: =SUM(AE57:AI57) -> 0 | AK57: =COUNTIF('выгрузка отзывов'!$B$2:$B$7,$C57) -> 0 | AO57: =SUM(AK57:AN57) -> 0
B58: Юлия | C58: ='1. Справочник'!C136 -> NW 4-9 | D58: июль 25 | E58: =F58+I58+K58+M58 -> 1 | F58: =IFERROR(VLOOKUP(C58,'Лист20'!$A$1:$C1088,2,0),0) -> 0 | G58: =IFERROR(VLOOKUP(C58,'Лист20'!$A$1:$C1088,3,0),0) -> 0 | H58: TRUE | I58: 1 | J58: 10 | T58: =SUM(O58:S58) -> 0 | Y58: =SUM(U58:X58) -> 0 | AE58: =COUNTIF('выгрузка отзывов'!$B$34:$B$39,C58) -> 0 | AF58: =COUNTIF('выгрузка отзывов'!$B$25:$B$33,C58) -> 0 | AG58: =COUNTIF('выгрузка отзывов'!$B$18:$B$24,C58) -> 0 | AH58: =COUNTIF('выгрузка отзывов'!$B$11:$B$17,C58) -> 0 | AI58: =COUNTIF('выгрузка отзывов'!$B$8:$B$10,C58) -> 0 | AJ58: =SUM(AE58:AI58) -> 0 | AK58: =COUNTIF('выгрузка отзывов'!$B$2:$B$7,$C58) -> 0 | AO58: =SUM(AK58:AN58) -> 0
B59: Юлия | C59: ='1. Справочник'!C137 -> NW 4-10 | D59: июль 25 | E59: =F59+I59+K59+M59 -> 3 | F59: =IFERROR(VLOOKUP(C59,'Лист20'!$A$1:$C1088,2,0),0) -> 0 | G59: =IFERROR(VLOOKUP(C59,'Лист20'!$A$1:$C1088,3,0),0) -> 0 | H59: FALSE | I59: 3 | J59: 10 | T59: =SUM(O59:S59) -> 0 | Y59: =SUM(U59:X59) -> 0 | AE59: =COUNTIF('выгрузка отзывов'!$B$34:$B$39,C59) -> 0 | AF59: =COUNTIF('выгрузка отзывов'!$B$25:$B$33,C59) -> 0 | AG59: =COUNTIF('выгрузка отзывов'!$B$18:$B$24,C59) -> 0 | AH59: =COUNTIF('выгрузка отзывов'!$B$11:$B$17,C59) -> 0 | AI59: =COUNTIF('выгрузка отзывов'!$B$8:$B$10,C59) -> 0 | AJ59: =SUM(AE59:AI59) -> 0 | AK59: =COUNTIF('выгрузка отзывов'!$B$2:$B$7,$C59) -> 0 | AO59: =SUM(AK59:AN59) -> 0
B60: Юлия | C60: ='1. Справочник'!C138 -> NW 10-6 | D60: июль 25 | E60: =F60+I60+K60+M60 -> 1 | F60: =IFERROR(VLOOKUP(C60,'Лист20'!$A$1:$C1088,2,0),0) -> 0 | G60: =IFERROR(VLOOKUP(C60,'Лист20'!$A$1:$C1088,3,0),0) -> 0 | H60: TRUE | I60: 1 | J60: 10 | T60: =SUM(O60:S60) -> 0 | Y60: =SUM(U60:X60) -> 0 | AE60: =COUNTIF('выгрузка отзывов'!$B$34:$B$39,C60) -> 0 | AF60: =COUNTIF('выгрузка отзывов'!$B$25:$B$33,C60) -> 0 | AG60: =COUNTIF('выгрузка отзывов'!$B$18:$B$24,C60) -> 0 | AH60: =COUNTIF('выгрузка отзывов'!$B$11:$B$17,C60) -> 0 | AI60: =COUNTIF('выгрузка отзывов'!$B$8:$B$10,C60) -> 0 | AJ60: =SUM(AE60:AI60) -> 0 | AK60: =COUNTIF('выгрузка отзывов'!$B$2:$B$7,$C60) -> 0 | AO60: =SUM(AK60:AN60) -> 0
B61: Юлия | C61: ='1. Справочник'!C61 -> NW 3-7 | D61: июль 25 | E61: =F61+I61+K61+M61 -> 0 | F61: =IFERROR(VLOOKUP(C61,'Лист20'!$A$1:$C1088,2,0),0) -> 0 | G61: =IFERROR(VLOOKUP(C61,'Лист20'!$A$1:$C1088,3,0),0) -> 0 | H61: TRUE | T61: =SUM(O61:S61) -> 0 | Y61: =SUM(U61:X61) -> 0 | AE61: =COUNTIF('выгрузка отзывов'!$B$34:$B$39,C61) -> 0 | AF61: =COUNTIF('выгрузка отзывов'!$B$25:$B$33,C61) -> 0 | AG61: =COUNTIF('выгрузка отзывов'!$B$18:$B$24,C61) -> 0 | AH61: =COUNTIF('выгрузка отзывов'!$B$11:$B$17,C61) -> 0 | AI61: =COUNTIF('выгрузка отзывов'!$B$8:$B$10,C61) -> 0 | AJ61: =SUM(AE61:AI61) -> 0 | AK61: =COUNTIF('выгрузка отзывов'!$B$2:$B$7,$C61) -> 0 | AO61: =SUM(AK61:AN61) -> 0
B62: Юлия | C62: 7 | PR 18 D 181 | Pirosmani | 2+1 | H62: FALSE | AE62: =COUNTIF('выгрузка отзывов'!$B$34:$B$39,C62) -> 0 | AF62: =COUNTIF('выгрузка отзывов'!$B$25:$B$33,C62) -> 1 | AG62: =COUNTIF('выгрузка отзывов'!$B$18:$B$24,C62) -> 0 | AH62: =COUNTIF('выгрузка отзывов'!$B$11:$B$17,C62) -> 0 | AI62: =COUNTIF('выгрузка отзывов'!$B$8:$B$10,C62) -> 0 | AJ62: =SUM(AE62:AI62) -> 1 | AK62: =COUNTIF('выгрузка отзывов'!$B$2:$B$7,$C62) -> 0
B63: Юлия | C63: 2 | Int A 2905 | Intourist | 1+1 | D63: 2024 | E63: =F63+I63+K63+M63 -> 2 | F63: =IFERROR(VLOOKUP(C63,'Лист20'!$A$1:$C1088,2,0),0) -> 0 | G63: =IFERROR(VLOOKUP(C63,'Лист20'!$A$1:$C1088,3,0),0) -> 0 | H63: TRUE | I63: 2 | J63: 9.7 | T63: =SUM(O63:S63) -> 0 | Y63: =SUM(U63:X63) -> 0 | AE63: =COUNTIF('выгрузка отзывов'!$B$34:$B$39,C63) -> 0 | AF63: =COUNTIF('выгрузка отзывов'!$B$25:$B$33,C63) -> 0 | AG63: =COUNTIF('выгрузка отзывов'!$B$18:$B$24,C63) -> 0 | AH63: =COUNTIF('выгрузка отзывов'!$B$11:$B$17,C63) -> 1 | AI63: =COUNTIF('выгрузка отзывов'!$B$8:$B$10,C63) -> 0 | AJ63: =SUM(AE63:AI63) -> 1 | AK63: =COUNTIF('выгрузка отзывов'!$B$2:$B$7,$C63) -> 0 | AO63: =SUM(AK63:AN63) -> 0
B64: Юлия | C64: 2 | Int B 2612 | Intourist | 1+1 | D64: июнь 25 | E64: =F64+I64+K64+M64 -> 2 | F64: =IFERROR(VLOOKUP(C64,'Лист20'!$A$1:$C1088,2,0),0) -> 0 | G64: =IFERROR(VLOOKUP(C64,'Лист20'!$A$1:$C1088,3,0),0) -> 0 | H64: TRUE | I64: 2 | J64: 10 | T64: 1 | Y64: 1 | AE64: =COUNTIF('выгрузка отзывов'!$B$34:$B$39,C64) -> 1 | AF64: =COUNTIF('выгрузка отзывов'!$B$25:$B$33,C64) -> 0 | AG64: =COUNTIF('выгрузка отзывов'!$B$18:$B$24,C64) -> 0 | AH64: =COUNTIF('выгрузка отзывов'!$B$11:$B$17,C64) -> 0 | AI64: =COUNTIF('выгрузка отзывов'!$B$8:$B$10,C64) -> 0 | AJ64: =SUM(AE64:AI64) -> 1 | AK64: =COUNTIF('выгрузка отзывов'!$B$2:$B$7,$C64) -> 0 | AO64: =SUM(AK64:AN64) -> 0
B65: Юлия | C65: 2 | Sh8 2505 | Shartava | 1+1 | D65: 2024 | E65: =F65+I65+K65+M65 -> 0 | F65: =IFERROR(VLOOKUP(C65,'Лист20'!$A$1:$C1088,2,0),0) -> 0 | G65: =IFERROR(VLOOKUP(C65,'Лист20'!$A$1:$C1088,3,0),0) -> 0 | H65: TRUE | T65: =SUM(O65:S65) -> 0 | Y65: =SUM(U65:X65) -> 0 | AE65: =COUNTIF('выгрузка отзывов'!$B$34:$B$39,C65) -> 0 | AF65: =COUNTIF('выгрузка отзывов'!$B$25:$B$33,C65) -> 0 | AG65: =COUNTIF('выгрузка отзывов'!$B$18:$B$24,C65) -> 0 | AH65: =COUNTIF('выгрузка отзывов'!$B$11:$B$17,C65) -> 1 | AI65: =COUNTIF('выгрузка отзывов'!$B$8:$B$10,C65) -> 0 | AJ65: =SUM(AE65:AI65) -> 1 | AK65: =COUNTIF('выгрузка отзывов'!$B$2:$B$7,$C65) -> 0 | AO65: =SUM(AK65:AN65) -> 0
C66: 12 | E66: =F66+I66+K66+M66 -> 23 | I66: =SUM(I44:I65) -> 23 | O66: =SUM(O44:O65) -> 0 | P66: =SUM(P44:P65) -> 0 | Q66: =SUM(Q44:Q65) -> 0 | R66: =SUM(R44:R65) -> 0 | S66: =SUM(S44:S65) -> 0 | T66: =SUM(O66:S66) -> 0 | U66: =SUM(U44:U65) -> 0 | V66: =SUM(V44:V65) -> 0 | W66: =SUM(W44:W65) -> 0 | X66: =SUM(X44:X65) -> 0 | Y66: =SUM(U66:X66) -> 0 | Z66: =SUM(Z44:Z65) -> 0 | AA66: =SUM(AA44:AA65) -> 0 | AD66: =SUM(AD44:AD65) -> 0 | AE66: =SUM(AE44:AE65) -> 2 | AF66: =SUM(AF44:AF65) -> 5 | AG66: =SUM(AG44:AG65) -> 6 | AH66: =SUM(AH44:AH65) -> 6 | AI66: =SUM(AI44:AI65) -> 2 | AJ66: =SUM(AJ44:AJ65) -> 21 | AK66: =SUM(AK44:AK65) -> 3 | ... AN66: =SUM(AN44:AN65) -> 0 | AO66: =SUM(AK66:AN66) -> 3 | AP66: =SUM(AP44:AP65) -> 0 | AQ66: =SUM(AQ44:AQ65) -> 0 | AT66: =SUM(AT44:AT65) -> 0
C67: ='1. Справочник'!C75 -> DL 11-1112 | E67: =F67+I67+K67+M67 -> #NAME? | F67: =VLOOKUP(C67,'Лист20'!$A$1:$C1088,2,0) -> #NAME? | G67: =VLOOKUP(C67,'Лист20'!$A$1:$C1088,3,0) -> #NAME? | H67: FALSE | R67: =SUMIF('Заполняемость'!$C$8:$C1088,C67,'Заполняемость'!$E$8:$E1088) -> 0 | S67: =SUMIF('Заполняемость'!$C$8:$C1088,$C67,'Заполняемость'!$H$8:$H1088) -> 0 | U67: =SUMIF('Заполняемость'!$C$8:$C1088,$C67,'Заполняемость'!$K$8:$K1088) -> 2 | V67: =SUMIF('Заполняемость'!$C$8:$C1088,$C67,'Заполняемость'!$N$8:$N1088) -> 3 | W67: =SUMIF('Заполняемость'!$C$8:$C1088,$C67,'Заполняемость'!$Q$8:$Q1088) -> 1 | X67: =SUMIF('Заполняемость'!$C$8:$C1088,$C67,'Заполняемость'!$T$8:$T1088) -> 0 | Z67: =SUMIF('Заполняемость'!$C$8:$C1088,$C67,'Заполняемость'!$T$8:$T1088) -> 0 | AA67: =SUMIF('Заполняемость'!$C$8:$C1088,$C67,'Заполняемость'!$Z$8:$Z1088) -> 0 | AH67: =SUMIF('Заполняемость'!$C$8:$C1088,S67,'Заполняемость'!$E$8:$E1088) -> 0 | AI67: =SUMIF('Заполняемость'!$C$8:$C1088,$C67,'Заполняемость'!$H$8:$H1088) -> 0 | AK67: =SUMIF('Заполняемость'!$C$8:$C1088,$C67,'Заполняемость'!$K$8:$K1088) -> 2 | AL67: =SUMIF('Заполняемость'!$C$8:$C1088,$C67,'Заполняемость'!$N$8:$N1088) -> 3 | AM67: =SUMIF('Заполняемость'!$C$8:$C1088,$C67,'Заполняемость'!$Q$8:$Q1088) -> 1 | AN67: =SUMIF('Заполняемость'!$C$8:$C1088,$C67,'Заполняемость'!$T$8:$T1088) -> 0 | AP67: =SUMIF('Заполняемость'!$C$8:$C1088,$C67,'Заполняемость'!$T$8:$T1088) -> 0 | AQ67: =SUMIF('Заполняемость'!$C$8:$C1088,$C67,'Заполняемость'!$Z$8:$Z1088) -> 0
C68: ='1. Справочник'!C76 -> DL 11-1305 | E68: =F68+I68+K68+M68 -> #NAME? | F68: =VLOOKUP(C68,'Лист20'!$A$1:$C1088,2,0) -> #NAME? | G68: =VLOOKUP(C68,'Лист20'!$A$1:$C1088,3,0) -> #NAME? | H68: FALSE | I68: 1 | J68: 10 | R68: =SUMIF('Заполняемость'!$C$8:$C1088,C68,'Заполняемость'!$E$8:$E1088) -> 0 | S68: =SUMIF('Заполняемость'!$C$8:$C1088,$C68,'Заполняемость'!$H$8:$H1088) -> 0 | U68: =SUMIF('Заполняемость'!$C$8:$C1088,$C68,'Заполняемость'!$K$8:$K1088) -> 4 | V68: =SUMIF('Заполняемость'!$C$8:$C1088,$C68,'Заполняемость'!$N$8:$N1088) -> 4 | W68: =SUMIF('Заполняемость'!$C$8:$C1088,$C68,'Заполняемость'!$Q$8:$Q1088) -> 1 | X68: =SUMIF('Заполняемость'!$C$8:$C1088,$C68,'Заполняемость'!$T$8:$T1088) -> 0 | Z68: =SUMIF('Заполняемость'!$C$8:$C1088,$C68,'Заполняемость'!$T$8:$T1088) -> 0 | AA68: =SUMIF('Заполняемость'!$C$8:$C1088,$C68,'Заполняемость'!$Z$8:$Z1088) -> 0 | AH68: =SUMIF('Заполняемость'!$C$8:$C1088,S68,'Заполняемость'!$E$8:$E1088) -> 0 | AI68: =SUMIF('Заполняемость'!$C$8:$C1088,$C68,'Заполняемость'!$H$8:$H1088) -> 0 | AK68: =SUMIF('Заполняемость'!$C$8:$C1088,$C68,'Заполняемость'!$K$8:$K1088) -> 4 | AL68: =SUMIF('Заполняемость'!$C$8:$C1088,$C68,'Заполняемость'!$N$8:$N1088) -> 4 | AM68: =SUMIF('Заполняемость'!$C$8:$C1088,$C68,'Заполняемость'!$Q$8:$Q1088) -> 1 | AN68: =SUMIF('Заполняемость'!$C$8:$C1088,$C68,'Заполняемость'!$T$8:$T1088) -> 0 | AP68: =SUMIF('Заполняемость'!$C$8:$C1088,$C68,'Заполняемость'!$T$8:$T1088) -> 0 | AQ68: =SUMIF('Заполняемость'!$C$8:$C1088,$C68,'Заполняемость'!$Z$8:$Z1088) -> 0
C69: ='1. Справочник'!C77 -> DL 14-516 | E69: =F69+I69+K69+M69 -> #NAME? | F69: =VLOOKUP(C69,'Лист20'!$A$1:$C1088,2,0) -> #NAME? | G69: =VLOOKUP(C69,'Лист20'!$A$1:$C1088,3,0) -> #NAME? | H69: TRUE | I69: 2 | J69: 10 | R69: =SUMIF('Заполняемость'!$C$8:$C1088,C69,'Заполняемость'!$E$8:$E1088) -> 0 | S69: =SUMIF('Заполняемость'!$C$8:$C1088,$C69,'Заполняемость'!$H$8:$H1088) -> 1 | U69: =SUMIF('Заполняемость'!$C$8:$C1088,$C69,'Заполняемость'!$K$8:$K1088) -> 2 | V69: =SUMIF('Заполняемость'!$C$8:$C1088,$C69,'Заполняемость'!$N$8:$N1088) -> 3 | W69: =SUMIF('Заполняемость'!$C$8:$C1088,$C69,'Заполняемость'!$Q$8:$Q1088) -> 2 | X69: =SUMIF('Заполняемость'!$C$8:$C1088,$C69,'Заполняемость'!$T$8:$T1088) -> 0 | Z69: =SUMIF('Заполняемость'!$C$8:$C1088,$C69,'Заполняемость'!$T$8:$T1088) -> 0 | AA69: =SUMIF('Заполняемость'!$C$8:$C1088,$C69,'Заполняемость'!$Z$8:$Z1088) -> 0 | AH69: =SUMIF('Заполняемость'!$C$8:$C1088,S69,'Заполняемость'!$E$8:$E1088) -> 0 | AI69: =SUMIF('Заполняемость'!$C$8:$C1088,$C69,'Заполняемость'!$H$8:$H1088) -> 1 | AK69: =SUMIF('Заполняемость'!$C$8:$C1088,$C69,'Заполняемость'!$K$8:$K1088) -> 2 | AL69: =SUMIF('Заполняемость'!$C$8:$C1088,$C69,'Заполняемость'!$N$8:$N1088) -> 3 | AM69: =SUMIF('Заполняемость'!$C$8:$C1088,$C69,'Заполняемость'!$Q$8:$Q1088) -> 2 | AN69: =SUMIF('Заполняемость'!$C$8:$C1088,$C69,'Заполняемость'!$T$8:$T1088) -> 0 | AP69: =SUMIF('Заполняемость'!$C$8:$C1088,$C69,'Заполняемость'!$T$8:$T1088) -> 0 | AQ69: =SUMIF('Заполняемость'!$C$8:$C1088,$C69,'Заполняемость'!$Z$8:$Z1088) -> 0
C70: ='1. Справочник'!C78 -> DL 14-702 | E70: =F70+I70+K70+M70 -> #NAME? | F70: =VLOOKUP(C70,'Лист20'!$A$1:$C1088,2,0) -> #NAME? | G70: =VLOOKUP(C70,'Лист20'!$A$1:$C1088,3,0) -> #NAME? | H70: FALSE | R70: =SUMIF('Заполняемость'!$C$8:$C1088,C70,'Заполняемость'!$E$8:$E1088) -> 0 | S70: =SUMIF('Заполняемость'!$C$8:$C1088,$C70,'Заполняемость'!$H$8:$H1088) -> 1 | U70: =SUMIF('Заполняемость'!$C$8:$C1088,$C70,'Заполняемость'!$K$8:$K1088) -> 3 | V70: =SUMIF('Заполняемость'!$C$8:$C1088,$C70,'Заполняемость'!$N$8:$N1088) -> 6 | W70: =SUMIF('Заполняемость'!$C$8:$C1088,$C70,'Заполняемость'!$Q$8:$Q1088) -> 0 | X70: =SUMIF('Заполняемость'!$C$8:$C1088,$C70,'Заполняемость'!$T$8:$T1088) -> 0 | Z70: =SUMIF('Заполняемость'!$C$8:$C1088,$C70,'Заполняемость'!$T$8:$T1088) -> 0 | AA70: =SUMIF('Заполняемость'!$C$8:$C1088,$C70,'Заполняемость'!$Z$8:$Z1088) -> 0 | AH70: =SUMIF('Заполняемость'!$C$8:$C1088,S70,'Заполняемость'!$E$8:$E1088) -> 0 | AI70: =SUMIF('Заполняемость'!$C$8:$C1088,$C70,'Заполняемость'!$H$8:$H1088) -> 1 | AK70: =SUMIF('Заполняемость'!$C$8:$C1088,$C70,'Заполняемость'!$K$8:$K1088) -> 3 | AL70: =SUMIF('Заполняемость'!$C$8:$C1088,$C70,'Заполняемость'!$N$8:$N1088) -> 6 | AM70: =SUMIF('Заполняемость'!$C$8:$C1088,$C70,'Заполняемость'!$Q$8:$Q1088) -> 0 | AN70: =SUMIF('Заполняемость'!$C$8:$C1088,$C70,'Заполняемость'!$T$8:$T1088) -> 0 | AP70: =SUMIF('Заполняемость'!$C$8:$C1088,$C70,'Заполняемость'!$T$8:$T1088) -> 0 | AQ70: =SUMIF('Заполняемость'!$C$8:$C1088,$C70,'Заполняемость'!$Z$8:$Z1088) -> 0
C71: ='1. Справочник'!C79 -> DL 14-1214 | E71: =F71+I71+K71+M71 -> #NAME? | F71: =VLOOKUP(C71,'Лист20'!$A$1:$C1088,2,0) -> #NAME? | G71: =VLOOKUP(C71,'Лист20'!$A$1:$C1088,3,0) -> #NAME? | H71: FALSE | R71: =SUMIF('Заполняемость'!$C$8:$C1088,C71,'Заполняемость'!$E$8:$E1088) -> 0 | S71: =SUMIF('Заполняемость'!$C$8:$C1088,$C71,'Заполняемость'!$H$8:$H1088) -> 0 | U71: =SUMIF('Заполняемость'!$C$8:$C1088,$C71,'Заполняемость'!$K$8:$K1088) -> 1 | V71: =SUMIF('Заполняемость'!$C$8:$C1088,$C71,'Заполняемость'!$N$8:$N1088) -> 3 | W71: =SUMIF('Заполняемость'!$C$8:$C1088,$C71,'Заполняемость'!$Q$8:$Q1088) -> 2 | X71: =SUMIF('Заполняемость'!$C$8:$C1088,$C71,'Заполняемость'!$T$8:$T1088) -> 0 | Z71: =SUMIF('Заполняемость'!$C$8:$C1088,$C71,'Заполняемость'!$T$8:$T1088) -> 0 | AA71: =SUMIF('Заполняемость'!$C$8:$C1088,$C71,'Заполняемость'!$Z$8:$Z1088) -> 0 | AH71: =SUMIF('Заполняемость'!$C$8:$C1088,S71,'Заполняемость'!$E$8:$E1088) -> 0 | AI71: =SUMIF('Заполняемость'!$C$8:$C1088,$C71,'Заполняемость'!$H$8:$H1088) -> 0 | AK71: =SUMIF('Заполняемость'!$C$8:$C1088,$C71,'Заполняемость'!$K$8:$K1088) -> 1 | AL71: =SUMIF('Заполняемость'!$C$8:$C1088,$C71,'Заполняемость'!$N$8:$N1088) -> 3 | AM71: =SUMIF('Заполняемость'!$C$8:$C1088,$C71,'Заполняемость'!$Q$8:$Q1088) -> 2 | AN71: =SUMIF('Заполняемость'!$C$8:$C1088,$C71,'Заполняемость'!$T$8:$T1088) -> 0 | AP71: =SUMIF('Заполняемость'!$C$8:$C1088,$C71,'Заполняемость'!$T$8:$T1088) -> 0 | AQ71: =SUMIF('Заполняемость'!$C$8:$C1088,$C71,'Заполняемость'!$Z$8:$Z1088) -> 0
C72: 14-411 | E72: =F72+I72+K72+M72 -> #NAME? | F72: =VLOOKUP(C72,'Лист20'!$A$1:$C1088,2,0) -> #NAME? | G72: =VLOOKUP(C72,'Лист20'!$A$1:$C1088,3,0) -> #NAME? | H72: TRUE | R72: =SUMIF('Заполняемость'!$C$8:$C1088,C72,'Заполняемость'!$E$8:$E1088) -> 0 | S72: =SUMIF('Заполняемость'!$C$8:$C1088,$C72,'Заполняемость'!$H$8:$H1088) -> 1 | U72: =SUMIF('Заполняемость'!$C$8:$C1088,$C72,'Заполняемость'!$K$8:$K1088) -> 5 | V72: =SUMIF('Заполняемость'!$C$8:$C1088,$C72,'Заполняемость'!$N$8:$N1088) -> 5 | W72: =SUMIF('Заполняемость'!$C$8:$C1088,$C72,'Заполняемость'!$Q$8:$Q1088) -> 0 | X72: =SUMIF('Заполняемость'!$C$8:$C1088,$C72,'Заполняемость'!$T$8:$T1088) -> 0 | Z72: =SUMIF('Заполняемость'!$C$8:$C1088,$C72,'Заполняемость'!$T$8:$T1088) -> 0 | AA72: =SUMIF('Заполняемость'!$C$8:$C1088,$C72,'Заполняемость'!$Z$8:$Z1088) -> 0 | AH72: =SUMIF('Заполняемость'!$C$8:$C1088,S72,'Заполняемость'!$E$8:$E1088) -> 0 | AI72: =SUMIF('Заполняемость'!$C$8:$C1088,$C72,'Заполняемость'!$H$8:$H1088) -> 1 | AK72: =SUMIF('Заполняемость'!$C$8:$C1088,$C72,'Заполняемость'!$K$8:$K1088) -> 5 | AL72: =SUMIF('Заполняемость'!$C$8:$C1088,$C72,'Заполняемость'!$N$8:$N1088) -> 5 | AM72: =SUMIF('Заполняемость'!$C$8:$C1088,$C72,'Заполняемость'!$Q$8:$Q1088) -> 0 | AN72: =SUMIF('Заполняемость'!$C$8:$C1088,$C72,'Заполняемость'!$T$8:$T1088) -> 0 | AP72: =SUMIF('Заполняемость'!$C$8:$C1088,$C72,'Заполняемость'!$T$8:$T1088) -> 0 | AQ72: =SUMIF('Заполняемость'!$C$8:$C1088,$C72,'Заполняемость'!$Z$8:$Z1088) -> 0
C73: ='1. Справочник'!C81 -> DL 4-09 | E73: =F73+I73+K73+M73 -> #NAME? | F73: =VLOOKUP(C73,'Лист20'!$A$1:$C1088,2,0) -> #NAME? | G73: =VLOOKUP(C73,'Лист20'!$A$1:$C1088,3,0) -> #NAME? | H73: FALSE | R73: =SUMIF('Заполняемость'!$C$8:$C1088,C73,'Заполняемость'!$E$8:$E1088) -> 0 | S73: =SUMIF('Заполняемость'!$C$8:$C1088,$C73,'Заполняемость'!$H$8:$H1088) -> 0 | U73: =SUMIF('Заполняемость'!$C$8:$C1088,$C73,'Заполняемость'!$K$8:$K1088) -> 2 | V73: =SUMIF('Заполняемость'!$C$8:$C1088,$C73,'Заполняемость'!$N$8:$N1088) -> 5 | W73: =SUMIF('Заполняемость'!$C$8:$C1088,$C73,'Заполняемость'!$Q$8:$Q1088) -> 0 | X73: =SUMIF('Заполняемость'!$C$8:$C1088,$C73,'Заполняемость'!$T$8:$T1088) -> 0 | Z73: =SUMIF('Заполняемость'!$C$8:$C1088,$C73,'Заполняемость'!$T$8:$T1088) -> 0 | AA73: =SUMIF('Заполняемость'!$C$8:$C1088,$C73,'Заполняемость'!$Z$8:$Z1088) -> 0 | AH73: =SUMIF('Заполняемость'!$C$8:$C1088,S73,'Заполняемость'!$E$8:$E1088) -> 0 | AI73: =SUMIF('Заполняемость'!$C$8:$C1088,$C73,'Заполняемость'!$H$8:$H1088) -> 0 | AK73: =SUMIF('Заполняемость'!$C$8:$C1088,$C73,'Заполняемость'!$K$8:$K1088) -> 2 | AL73: =SUMIF('Заполняемость'!$C$8:$C1088,$C73,'Заполняемость'!$N$8:$N1088) -> 5 | AM73: =SUMIF('Заполняемость'!$C$8:$C1088,$C73,'Заполняемость'!$Q$8:$Q1088) -> 0 | AN73: =SUMIF('Заполняемость'!$C$8:$C1088,$C73,'Заполняемость'!$T$8:$T1088) -> 0 | AP73: =SUMIF('Заполняемость'!$C$8:$C1088,$C73,'Заполняемость'!$T$8:$T1088) -> 0 | AQ73: =SUMIF('Заполняемость'!$C$8:$C1088,$C73,'Заполняемость'!$Z$8:$Z1088) -> 0
C74: ='1. Справочник'!C82 -> DL14-518 | E74: =F74+I74+K74+M74 -> #NAME? | F74: =VLOOKUP(C74,'Лист20'!$A$1:$C1088,2,0) -> #NAME? | G74: =VLOOKUP(C74,'Лист20'!$A$1:$C1088,3,0) -> #NAME? | H74: TRUE | R74: =SUMIF('Заполняемость'!$C$8:$C1088,C74,'Заполняемость'!$E$8:$E1088) -> 0 | S74: =SUMIF('Заполняемость'!$C$8:$C1088,$C74,'Заполняемость'!$H$8:$H1088) -> 1 | U74: =SUMIF('Заполняемость'!$C$8:$C1088,$C74,'Заполняемость'!$K$8:$K1088) -> 4 | V74: =SUMIF('Заполняемость'!$C$8:$C1088,$C74,'Заполняемость'!$N$8:$N1088) -> 5 | W74: =SUMIF('Заполняемость'!$C$8:$C1088,$C74,'Заполняемость'!$Q$8:$Q1088) -> 2 | X74: =SUMIF('Заполняемость'!$C$8:$C1088,$C74,'Заполняемость'!$T$8:$T1088) -> 0 | Z74: =SUMIF('Заполняемость'!$C$8:$C1088,$C74,'Заполняемость'!$T$8:$T1088) -> 0 | AA74: =SUMIF('Заполняемость'!$C$8:$C1088,$C74,'Заполняемость'!$Z$8:$Z1088) -> 0 | AH74: =SUMIF('Заполняемость'!$C$8:$C1088,S74,'Заполняемость'!$E$8:$E1088) -> 0 | AI74: =SUMIF('Заполняемость'!$C$8:$C1088,$C74,'Заполняемость'!$H$8:$H1088) -> 1 | AK74: =SUMIF('Заполняемость'!$C$8:$C1088,$C74,'Заполняемость'!$K$8:$K1088) -> 4 | AL74: =SUMIF('Заполняемость'!$C$8:$C1088,$C74,'Заполняемость'!$N$8:$N1088) -> 5 | AM74: =SUMIF('Заполняемость'!$C$8:$C1088,$C74,'Заполняемость'!$Q$8:$Q1088) -> 2 | AN74: =SUMIF('Заполняемость'!$C$8:$C1088,$C74,'Заполняемость'!$T$8:$T1088) -> 0 | AP74: =SUMIF('Заполняемость'!$C$8:$C1088,$C74,'Заполняемость'!$T$8:$T1088) -> 0 | AQ74: =SUMIF('Заполняемость'!$C$8:$C1088,$C74,'Заполняемость'!$Z$8:$Z1088) -> 0
C75: ='1. Справочник'!C83 -> DL14-1405 | E75: =F75+I75+K75+M75 -> #NAME? | F75: =VLOOKUP(C75,'Лист20'!$A$1:$C1088,2,0) -> #NAME? | G75: =VLOOKUP(C75,'Лист20'!$A$1:$C1088,3,0) -> #NAME? | H75: FALSE | R75: =SUMIF('Заполняемость'!$C$8:$C1088,C75,'Заполняемость'!$E$8:$E1088) -> 0 | S75: =SUMIF('Заполняемость'!$C$8:$C1088,$C75,'Заполняемость'!$H$8:$H1088) -> 1 | U75: =SUMIF('Заполняемость'!$C$8:$C1088,$C75,'Заполняемость'!$K$8:$K1088) -> 4 | V75: =SUMIF('Заполняемость'!$C$8:$C1088,$C75,'Заполняемость'!$N$8:$N1088) -> 6 | W75: =SUMIF('Заполняемость'!$C$8:$C1088,$C75,'Заполняемость'!$Q$8:$Q1088) -> 0 | X75: =SUMIF('Заполняемость'!$C$8:$C1088,$C75,'Заполняемость'!$T$8:$T1088) -> 0 | Z75: =SUMIF('Заполняемость'!$C$8:$C1088,$C75,'Заполняемость'!$T$8:$T1088) -> 0 | AA75: =SUMIF('Заполняемость'!$C$8:$C1088,$C75,'Заполняемость'!$Z$8:$Z1088) -> 0 | AH75: =SUMIF('Заполняемость'!$C$8:$C1088,S75,'Заполняемость'!$E$8:$E1088) -> 0 | AI75: =SUMIF('Заполняемость'!$C$8:$C1088,$C75,'Заполняемость'!$H$8:$H1088) -> 1 | AK75: =SUMIF('Заполняемость'!$C$8:$C1088,$C75,'Заполняемость'!$K$8:$K1088) -> 4 | AL75: =SUMIF('Заполняемость'!$C$8:$C1088,$C75,'Заполняемость'!$N$8:$N1088) -> 6 | AM75: =SUMIF('Заполняемость'!$C$8:$C1088,$C75,'Заполняемость'!$Q$8:$Q1088) -> 0 | AN75: =SUMIF('Заполняемость'!$C$8:$C1088,$C75,'Заполняемость'!$T$8:$T1088) -> 0 | AP75: =SUMIF('Заполняемость'!$C$8:$C1088,$C75,'Заполняемость'!$T$8:$T1088) -> 0 | AQ75: =SUMIF('Заполняемость'!$C$8:$C1088,$C75,'Заполняемость'!$Z$8:$Z1088) -> 0
C76: ='1. Справочник'!C84 -> DL 14-505 | E76: =F76+I76+K76+M76 -> #NAME? | F76: =VLOOKUP(C76,'Лист20'!$A$1:$C1088,2,0) -> #NAME? | G76: =VLOOKUP(C76,'Лист20'!$A$1:$C1088,3,0) -> #NAME? | H76: TRUE | R76: =SUMIF('Заполняемость'!$C$8:$C1088,C76,'Заполняемость'!$E$8:$E1088) -> 0 | S76: =SUMIF('Заполняемость'!$C$8:$C1088,$C76,'Заполняемость'!$H$8:$H1088) -> 2 | U76: =SUMIF('Заполняемость'!$C$8:$C1088,$C76,'Заполняемость'!$K$8:$K1088) -> 3 | V76: =SUMIF('Заполняемость'!$C$8:$C1088,$C76,'Заполняемость'!$N$8:$N1088) -> 3 | W76: =SUMIF('Заполняемость'!$C$8:$C1088,$C76,'Заполняемость'!$Q$8:$Q1088) -> 2 | X76: =SUMIF('Заполняемость'!$C$8:$C1088,$C76,'Заполняемость'!$T$8:$T1088) -> 0 | Z76: =SUMIF('Заполняемость'!$C$8:$C1088,$C76,'Заполняемость'!$T$8:$T1088) -> 0 | AA76: =SUMIF('Заполняемость'!$C$8:$C1088,$C76,'Заполняемость'!$Z$8:$Z1088) -> 0 | AH76: =SUMIF('Заполняемость'!$C$8:$C1088,S76,'Заполняемость'!$E$8:$E1088) -> 0 | AI76: =SUMIF('Заполняемость'!$C$8:$C1088,$C76,'Заполняемость'!$H$8:$H1088) -> 2 | AK76: =SUMIF('Заполняемость'!$C$8:$C1088,$C76,'Заполняемость'!$K$8:$K1088) -> 3 | AL76: =SUMIF('Заполняемость'!$C$8:$C1088,$C76,'Заполняемость'!$N$8:$N1088) -> 3 | AM76: =SUMIF('Заполняемость'!$C$8:$C1088,$C76,'Заполняемость'!$Q$8:$Q1088) -> 2 | AN76: =SUMIF('Заполняемость'!$C$8:$C1088,$C76,'Заполняемость'!$T$8:$T1088) -> 0 | AP76: =SUMIF('Заполняемость'!$C$8:$C1088,$C76,'Заполняемость'!$T$8:$T1088) -> 0 | AQ76: =SUMIF('Заполняемость'!$C$8:$C1088,$C76,'Заполняемость'!$Z$8:$Z1088) -> 0
C77: ='1. Справочник'!C85 -> DL 14-1614 | E77: =F77+I77+K77+M77 -> #NAME? | F77: =VLOOKUP(C77,'Лист20'!$A$1:$C1088,2,0) -> #NAME? | G77: =VLOOKUP(C77,'Лист20'!$A$1:$C1088,3,0) -> #NAME? | H77: FALSE | R77: =SUMIF('Заполняемость'!$C$8:$C1088,C77,'Заполняемость'!$E$8:$E1088) -> 0 | S77: =SUMIF('Заполняемость'!$C$8:$C1088,$C77,'Заполняемость'!$H$8:$H1088) -> 0 | U77: =SUMIF('Заполняемость'!$C$8:$C1088,$C77,'Заполняемость'!$K$8:$K1088) -> 0 | V77: =SUMIF('Заполняемость'!$C$8:$C1088,$C77,'Заполняемость'!$N$8:$N1088) -> 0 | W77: =SUMIF('Заполняемость'!$C$8:$C1088,$C77,'Заполняемость'!$Q$8:$Q1088) -> 0 | X77: =SUMIF('Заполняемость'!$C$8:$C1088,$C77,'Заполняемость'!$T$8:$T1088) -> 0 | Z77: =SUMIF('Заполняемость'!$C$8:$C1088,$C77,'Заполняемость'!$T$8:$T1088) -> 0 | AA77: =SUMIF('Заполняемость'!$C$8:$C1088,$C77,'Заполняемость'!$Z$8:$Z1088) -> 0 | AH77: =SUMIF('Заполняемость'!$C$8:$C1088,S77,'Заполняемость'!$E$8:$E1088) -> 0 | AI77: =SUMIF('Заполняемость'!$C$8:$C1088,$C77,'Заполняемость'!$H$8:$H1088) -> 0 | AK77: =SUMIF('Заполняемость'!$C$8:$C1088,$C77,'Заполняемость'!$K$8:$K1088) -> 0 | AL77: =SUMIF('Заполняемость'!$C$8:$C1088,$C77,'Заполняемость'!$N$8:$N1088) -> 0 | AM77: =SUMIF('Заполняемость'!$C$8:$C1088,$C77,'Заполняемость'!$Q$8:$Q1088) -> 0 | AN77: =SUMIF('Заполняемость'!$C$8:$C1088,$C77,'Заполняемость'!$T$8:$T1088) -> 0 | AP77: =SUMIF('Заполняемость'!$C$8:$C1088,$C77,'Заполняемость'!$T$8:$T1088) -> 0 | AQ77: =SUMIF('Заполняемость'!$C$8:$C1088,$C77,'Заполняемость'!$Z$8:$Z1088) -> 0
C78: ='1. Справочник'!C86 -> DL 14-1710 | D78: 45776 | E78: =F78+I78+K78+M78 -> #NAME? | F78: =VLOOKUP(C78,'Лист20'!$A$1:$C1088,2,0) -> #NAME? | G78: =VLOOKUP(C78,'Лист20'!$A$1:$C1088,3,0) -> #NAME? | H78: FALSE | R78: =SUMIF('Заполняемость'!$C$8:$C1088,C78,'Заполняемость'!$E$8:$E1088) -> 0 | S78: =SUMIF('Заполняемость'!$C$8:$C1088,$C78,'Заполняемость'!$H$8:$H1088) -> 0 | U78: =SUMIF('Заполняемость'!$C$8:$C1088,$C78,'Заполняемость'!$K$8:$K1088) -> 4 | V78: =SUMIF('Заполняемость'!$C$8:$C1088,$C78,'Заполняемость'!$N$8:$N1088) -> 4 | W78: =SUMIF('Заполняемость'!$C$8:$C1088,$C78,'Заполняемость'!$Q$8:$Q1088) -> 1 | X78: =SUMIF('Заполняемость'!$C$8:$C1088,$C78,'Заполняемость'!$T$8:$T1088) -> 0 | Z78: =SUMIF('Заполняемость'!$C$8:$C1088,$C78,'Заполняемость'!$T$8:$T1088) -> 0 | AA78: =SUMIF('Заполняемость'!$C$8:$C1088,$C78,'Заполняемость'!$Z$8:$Z1088) -> 0 | AH78: =SUMIF('Заполняемость'!$C$8:$C1088,S78,'Заполняемость'!$E$8:$E1088) -> 0 | AI78: =SUMIF('Заполняемость'!$C$8:$C1088,$C78,'Заполняемость'!$H$8:$H1088) -> 0 | AK78: =SUMIF('Заполняемость'!$C$8:$C1088,$C78,'Заполняемость'!$K$8:$K1088) -> 4 | AL78: =SUMIF('Заполняемость'!$C$8:$C1088,$C78,'Заполняемость'!$N$8:$N1088) -> 4 | AM78: =SUMIF('Заполняемость'!$C$8:$C1088,$C78,'Заполняемость'!$Q$8:$Q1088) -> 1 | AN78: =SUMIF('Заполняемость'!$C$8:$C1088,$C78,'Заполняемость'!$T$8:$T1088) -> 0 | AP78: =SUMIF('Заполняемость'!$C$8:$C1088,$C78,'Заполняемость'!$T$8:$T1088) -> 0 | AQ78: =SUMIF('Заполняемость'!$C$8:$C1088,$C78,'Заполняемость'!$Z$8:$Z1088) -> 0
C79: ='1. Справочник'!C87 -> DL14-305 | D79: 45776 | E79: =F79+I79+K79+M79 -> #NAME? | F79: =VLOOKUP(C79,'Лист20'!$A$1:$C1088,2,0) -> #NAME? | G79: =VLOOKUP(C79,'Лист20'!$A$1:$C1088,3,0) -> #NAME? | H79: FALSE | S79: =SUMIF('Заполняемость'!$C$8:$C1088,$C79,'Заполняемость'!$H$8:$H1088) -> 0 | U79: =SUMIF('Заполняемость'!$C$8:$C1088,$C79,'Заполняемость'!$K$8:$K1088) -> 4 | V79: =SUMIF('Заполняемость'!$C$8:$C1088,$C79,'Заполняемость'!$N$8:$N1088) -> 4 | X79: =SUMIF('Заполняемость'!$C$8:$C1088,$C79,'Заполняемость'!$T$8:$T1088) -> 0 | Z79: =SUMIF('Заполняемость'!$C$8:$C1088,$C79,'Заполняемость'!$T$8:$T1088) -> 0 | AA79: =SUMIF('Заполняемость'!$C$8:$C1088,$C79,'Заполняемость'!$Z$8:$Z1088) -> 0 | AI79: =SUMIF('Заполняемость'!$C$8:$C1088,$C79,'Заполняемость'!$H$8:$H1088) -> 0 | AK79: =SUMIF('Заполняемость'!$C$8:$C1088,$C79,'Заполняемость'!$K$8:$K1088) -> 4 | AL79: =SUMIF('Заполняемость'!$C$8:$C1088,$C79,'Заполняемость'!$N$8:$N1088) -> 4 | AN79: =SUMIF('Заполняемость'!$C$8:$C1088,$C79,'Заполняемость'!$T$8:$T1088) -> 0 | AP79: =SUMIF('Заполняемость'!$C$8:$C1088,$C79,'Заполняемость'!$T$8:$T1088) -> 0 | AQ79: =SUMIF('Заполняемость'!$C$8:$C1088,$C79,'Заполняемость'!$Z$8:$Z1088) -> 0
C80: ='1. Справочник'!C88 -> DL14-501-502 | D80: 45776 | E80: =F80+I80+K80+M80 -> #NAME? | F80: =VLOOKUP(C80,'Лист20'!$A$1:$C1088,2,0) -> #NAME? | G80: =VLOOKUP(C80,'Лист20'!$A$1:$C1088,3,0) -> #NAME? | H80: FALSE | S80: =SUMIF('Заполняемость'!$C$8:$C1088,$C80,'Заполняемость'!$H$8:$H1088) -> 0 | U80: =SUMIF('Заполняемость'!$C$8:$C1088,$C80,'Заполняемость'!$K$8:$K1088) -> 2 | V80: =SUMIF('Заполняемость'!$C$8:$C1088,$C80,'Заполняемость'!$N$8:$N1088) -> 4 | X80: =SUMIF('Заполняемость'!$C$8:$C1088,$C80,'Заполняемость'!$T$8:$T1088) -> 0 | Z80: =SUMIF('Заполняемость'!$C$8:$C1088,$C80,'Заполняемость'!$T$8:$T1088) -> 0 | AA80: =SUMIF('Заполняемость'!$C$8:$C1088,$C80,'Заполняемость'!$Z$8:$Z1088) -> 0 | AI80: =SUMIF('Заполняемость'!$C$8:$C1088,$C80,'Заполняемость'!$H$8:$H1088) -> 0 | AK80: =SUMIF('Заполняемость'!$C$8:$C1088,$C80,'Заполняемость'!$K$8:$K1088) -> 2 | AL80: =SUMIF('Заполняемость'!$C$8:$C1088,$C80,'Заполняемость'!$N$8:$N1088) -> 4 | AN80: =SUMIF('Заполняемость'!$C$8:$C1088,$C80,'Заполняемость'!$T$8:$T1088) -> 0 | AP80: =SUMIF('Заполняемость'!$C$8:$C1088,$C80,'Заполняемость'!$T$8:$T1088) -> 0 | AQ80: =SUMIF('Заполняемость'!$C$8:$C1088,$C80,'Заполняемость'!$Z$8:$Z1088) -> 0
D81: 45776 | E81: =F81+I81+K81+M81 -> 0 | H81: FALSE | S81: =SUMIF('Заполняемость'!$C$8:$C1088,$C81,'Заполняемость'!$H$8:$H1088) -> 0 | U81: =SUMIF('Заполняемость'!$C$8:$C1088,$C81,'Заполняемость'!$K$8:$K1088) -> 0 | V81: =SUMIF('Заполняемость'!$C$8:$C1088,$C81,'Заполняемость'!$N$8:$N1088) -> 0 | X81: =SUMIF('Заполняемость'!$C$8:$C1088,$C81,'Заполняемость'!$T$8:$T1088) -> 0 | Z81: =SUMIF('Заполняемость'!$C$8:$C1088,$C81,'Заполняемость'!$T$8:$T1088) -> 0 | AA81: =SUMIF('Заполняемость'!$C$8:$C1088,$C81,'Заполняемость'!$Z$8:$Z1088) -> 0 | AI81: =SUMIF('Заполняемость'!$C$8:$C1088,$C81,'Заполняемость'!$H$8:$H1088) -> 0 | AK81: =SUMIF('Заполняемость'!$C$8:$C1088,$C81,'Заполняемость'!$K$8:$K1088) -> 0 | AL81: =SUMIF('Заполняемость'!$C$8:$C1088,$C81,'Заполняемость'!$N$8:$N1088) -> 0 | AN81: =SUMIF('Заполняемость'!$C$8:$C1088,$C81,'Заполняемость'!$T$8:$T1088) -> 0 | AP81: =SUMIF('Заполняемость'!$C$8:$C1088,$C81,'Заполняемость'!$T$8:$T1088) -> 0 | AQ81: =SUMIF('Заполняемость'!$C$8:$C1088,$C81,'Заполняемость'!$Z$8:$Z1088) -> 0
C82: ='1. Справочник'!C89 -> DL7-16 | D82: 45776 | E82: =F82+I82+K82+M82 -> #NAME? | F82: =VLOOKUP(C82,'Лист20'!$A$1:$C1088,2,0) -> #NAME? | G82: =VLOOKUP(C82,'Лист20'!$A$1:$C1088,3,0) -> #NAME? | H82: FALSE | S82: =SUMIF('Заполняемость'!$C$8:$C1088,$C82,'Заполняемость'!$H$8:$H1088) -> 0 | U82: =SUMIF('Заполняемость'!$C$8:$C1088,$C82,'Заполняемость'!$K$8:$K1088) -> 1 | V82: =SUMIF('Заполняемость'!$C$8:$C1088,$C82,'Заполняемость'!$N$8:$N1088) -> 4 | X82: =SUMIF('Заполняемость'!$C$8:$C1088,$C82,'Заполняемость'!$T$8:$T1088) -> 0 | Z82: =SUMIF('Заполняемость'!$C$8:$C1088,$C82,'Заполняемость'!$T$8:$T1088) -> 0 | AA82: =SUMIF('Заполняемость'!$C$8:$C1088,$C82,'Заполняемость'!$Z$8:$Z1088) -> 0 | AI82: =SUMIF('Заполняемость'!$C$8:$C1088,$C82,'Заполняемость'!$H$8:$H1088) -> 0 | AK82: =SUMIF('Заполняемость'!$C$8:$C1088,$C82,'Заполняемость'!$K$8:$K1088) -> 1 | AL82: =SUMIF('Заполняемость'!$C$8:$C1088,$C82,'Заполняемость'!$N$8:$N1088) -> 4 | AN82: =SUMIF('Заполняемость'!$C$8:$C1088,$C82,'Заполняемость'!$T$8:$T1088) -> 0 | AP82: =SUMIF('Заполняемость'!$C$8:$C1088,$C82,'Заполняемость'!$T$8:$T1088) -> 0 | AQ82: =SUMIF('Заполняемость'!$C$8:$C1088,$C82,'Заполняемость'!$Z$8:$Z1088) -> 0
B83: Светлана | C83: TGA1 | D83: 45775 | E83: =F83+I83+K83+M83 -> 30 | F83: =IFERROR(VLOOKUP(C83,'Лист20'!$A$1:$C1088,2,0),0) -> 0 | G83: =IFERROR(VLOOKUP(C83,'Лист20'!$A$1:$C1088,3,0),0) -> 0 | H83: TRUE | I83: 30 | J83: 9.8
B84: Светлана | C84: TGA2 | D84: 45776 | E84: =F84+I84+K84+M84 -> 0 | F84: =IFERROR(VLOOKUP(C84,'Лист20'!$A$1:$C1088,2,0),0) -> 0 | G84: =IFERROR(VLOOKUP(C84,'Лист20'!$A$1:$C1088,3,0),0) -> 0 | H84: FALSE
B85: Светлана | C85: TGA3 | D85: 45776 | E85: =F85+I85+K85+M85 -> 0 | F85: =IFERROR(VLOOKUP(C85,'Лист20'!$A$1:$C1088,2,0),0) -> 0 | G85: =IFERROR(VLOOKUP(C85,'Лист20'!$A$1:$C1088,3,0),0) -> 0 | H85: TRUE
B86: Светлана | C86: TGA4 | D86: 45776 | E86: =F86+I86+K86+M86 -> 0 | F86: =IFERROR(VLOOKUP(C86,'Лист20'!$A$1:$C1088,2,0),0) -> 0 | G86: =IFERROR(VLOOKUP(C86,'Лист20'!$A$1:$C1088,3,0),0) -> 0 | H86: TRUE
B87: Светлана | C87: TGA5 | D87: 45776 | E87: =F87+I87+K87+M87 -> 0 | F87: =IFERROR(VLOOKUP(C87,'Лист20'!$A$1:$C1088,2,0),0) -> 0 | G87: =IFERROR(VLOOKUP(C87,'Лист20'!$A$1:$C1088,3,0),0) -> 0 | H87: FALSE
B88: Светлана | C88: TGA6 | D88: 45776 | E88: =F88+I88+K88+M88 -> 0 | F88: =IFERROR(VLOOKUP(C88,'Лист20'!$A$1:$C1088,2,0),0) -> 0 | G88: =IFERROR(VLOOKUP(C88,'Лист20'!$A$1:$C1088,3,0),0) -> 0 | H88: TRUE
B89: Светлана | C89: TGA7 | D89: 45776 | E89: =F89+I89+K89+M89 -> 0 | F89: =IFERROR(VLOOKUP(C89,'Лист20'!$A$1:$C1088,2,0),0) -> 0 | G89: =IFERROR(VLOOKUP(C89,'Лист20'!$A$1:$C1088,3,0),0) -> 0 | H89: FALSE
B90: Светлана | C90: TGA8 | D90: 45776 | E90: =F90+I90+K90+M90 -> 0 | F90: =IFERROR(VLOOKUP(C90,'Лист20'!$A$1:$C1088,2,0),0) -> 0 | G90: =IFERROR(VLOOKUP(C90,'Лист20'!$A$1:$C1088,3,0),0) -> 0 | H90: FALSE
B91: Светлана | C91: TGA9 | D91: 45776 | E91: =F91+I91+K91+M91 -> 0 | F91: =IFERROR(VLOOKUP(C91,'Лист20'!$A$1:$C1088,2,0),0) -> 0 | G91: =IFERROR(VLOOKUP(C91,'Лист20'!$A$1:$C1088,3,0),0) -> 0 | H91: FALSE
B92: Светлана | C92: TGA10 | D92: 45776 | E92: =F92+I92+K92+M92 -> 0 | F92: =IFERROR(VLOOKUP(C92,'Лист20'!$A$1:$C1088,2,0),0) -> 0 | G92: =IFERROR(VLOOKUP(C92,'Лист20'!$A$1:$C1088,3,0),0) -> 0 | H92: FALSE
B93: Светлана | C93: TGB1 | D93: 45776 | E93: =F93+I93+K93+M93 -> 0 | F93: =IFERROR(VLOOKUP(C93,'Лист20'!$A$1:$C1088,2,0),0) -> 0 | G93: =IFERROR(VLOOKUP(C93,'Лист20'!$A$1:$C1088,3,0),0) -> 0 | H93: FALSE
B94: Светлана | C94: TGB2 | D94: 45776 | E94: =F94+I94+K94+M94 -> 0 | F94: =IFERROR(VLOOKUP(C94,'Лист20'!$A$1:$C1088,2,0),0) -> 0 | G94: =IFERROR(VLOOKUP(C94,'Лист20'!$A$1:$C1088,3,0),0) -> 0 | H94: FALSE
B95: Светлана | C95: TGB3 | D95: 45776 | E95: =F95+I95+K95+M95 -> 0 | F95: =IFERROR(VLOOKUP(C95,'Лист20'!$A$1:$C1088,2,0),0) -> 0 | G95: =IFERROR(VLOOKUP(C95,'Лист20'!$A$1:$C1088,3,0),0) -> 0 | H95: FALSE
B96: Светлана | C96: TGB4 | D96: 45776 | E96: =F96+I96+K96+M96 -> 0 | F96: =IFERROR(VLOOKUP(C96,'Лист20'!$A$1:$C1088,2,0),0) -> 0 | G96: =IFERROR(VLOOKUP(C96,'Лист20'!$A$1:$C1088,3,0),0) -> 0 | H96: FALSE
B97: Светлана | C97: TGB5 | D97: 45776 | E97: =F97+I97+K97+M97 -> 0 | F97: =IFERROR(VLOOKUP(C97,'Лист20'!$A$1:$C1088,2,0),0) -> 0 | G97: =IFERROR(VLOOKUP(C97,'Лист20'!$A$1:$C1088,3,0),0) -> 0 | H97: FALSE
B98: Светлана | C98: TGB6 | D98: 45776 | E98: =F98+I98+K98+M98 -> 0 | F98: =IFERROR(VLOOKUP(C98,'Лист20'!$A$1:$C1088,2,0),0) -> 0 | G98: =IFERROR(VLOOKUP(C98,'Лист20'!$A$1:$C1088,3,0),0) -> 0 | H98: TRUE
B99: Светлана | C99: TGB7 | D99: 45776 | E99: =F99+I99+K99+M99 -> 0 | F99: =IFERROR(VLOOKUP(C99,'Лист20'!$A$1:$C1088,2,0),0) -> 0 | G99: =IFERROR(VLOOKUP(C99,'Лист20'!$A$1:$C1088,3,0),0) -> 0 | H99: FALSE
B100: Светлана | C100: TGB8 | D100: 45776 | E100: =F100+I100+K100+M100 -> 0 | F100: =IFERROR(VLOOKUP(C100,'Лист20'!$A$1:$C1088,2,0),0) -> 0 | G100: =IFERROR(VLOOKUP(C100,'Лист20'!$A$1:$C1088,3,0),0) -> 0 | H100: FALSE
...

Sheet выгрузка отзывов
A1: Created | B1: Listing | C1: Reservation | D1: Overall | E1: Accuracy | F1: Check In | G1: Cleanliness | H1: Communication | I1: Location | J1: Value | K1: Public Review | L1: Private Review | M1: Tags
A2: 07.02.2026 | B2: 2 | Orbi D1 1321 | Orbi Sity | Studio | C2: HM4C5CQ58S | D2: 5 | E2: 5 | F2: 5 | G2: 5 | H2: 5 | I2: 5 | J2: 5 | K2: Its a wonderful place | M2: Looked like the photos;Matched the description;Responsive host;Clear instructions;Easy to find;Easy to get inside;Flexible check-in;Always responsive;Local recommendations;Proactive;Helpful instructions;Considerate;Peaceful;Beautiful surroundings;Great restaurants;Walkable | N2: Beautiful surroundings | O2: Great restaurants | P2: Walkable
A3: 07.02.2026 | B3: 1 | BV A 144 | Batumi View | 1+1 | C3: HMPA349EQF | D3: 5 | E3: 5 | F3: 5 | G3: 5 | H3: 5 | I3: 5 | J3: 5 | K3: Great location with everything you need nearby. There are nice cafés right in the building, which is very convenient. Comfortable stay and easy access to the city. Would recommend. | M3: Looked like the photos;Matched the description;Always responsive;Helpful instructions;Considerate;Beautiful surroundings;Great restaurants;Walkable;Had listed amenities & services
A4: 03.02.2026 | B4: 2 | Mar 1327 | Courtyard by Marriott | 1+1 | C4: HMMWJ3ZXEE | D4: 5 | E4: 5 | F4: 5 | G4: 5 | H4: 5 | I4: 5 | J4: 5 | K4: Everything excellent!! | M4: Responsive host;Clear instructions
A5: 03.02.2026 | B5: 3 | PT 2704 | Old town | Studio | C5: HMZBKSEHDW | D5: 5 | E5: 5 | F5: 5 | G5: 5 | H5: 5 | I5: 5 | J5: 4 | K5: We had a good time there🤟
A6: 01.02.2026 | B6: 4 | MZ 913 | Mziuri Gardens | Studio | C6: HMNZTMQE54 | D6: 5 | E6: 5 | F6: 5 | G6: 5 | H6: 5 | I6: 5 | J6: 5 | K6: אירוח מצויין!!דירה יפה מרווחת ונקיה מאוד!! המארחים היו אדיבים וזמינים בכל שעה! ונתנו לנו מה שהיינו צריכים! שירות מעולה!הכל היה נפלא!נשמח לבוא שוב🫶🫶🫶Excellent hospitality!!Beautiful, spacious and very clean apartment!! The hosts were kind and available at all hours! And gave us what we needed! Excellent service!Everything was wonderful!We would love to come again🫶🫶🫶 | L6: We thank you very much!🫶
A7: 01.02.2026 | B7: 2 | Orbi D1 3902 | Orbi Sity | 1+1 | C7: HMZZTN985X | D7: 5 | E7: 5 | F7: 5 | G7: 5 | H7: 5 | I7: 5 | J7: 5 | K7: great appartment with à nice view
A8: 31.01.2026 | B8: 2 | Mar 1606 | Courtyard by Marriott | Studio | C8: HMH2CCCRKD | D8: 5 | E8: 5 | F8: 5 | G8: 5 | H8: 5 | I8: 5 | J8: 5 | K8: The perfect place in terms of everything. Gladly spent 8 days there. Highly recommend. | M8: Squeaky-clean bathroom;Pristine kitchen;Looked like the photos;Matched the description;Clear instructions;Easy to find;Easy to get inside;Always responsive;Proactive;Considerate;Beautiful surroundings;Great restaurants;Lots to do;Walkable;Spotless furniture & linens;Had listed amenities & services | N8: Walkable | O8: Spotless furniture & linens | P8: Had listed amenities & services
A9: 29.01.2026 | B9: 3 | PT 2704 | Old town | Studio | C9: HMDHAKQ5A5 | D9: 5 | E9: 5 | F9: 5 | G9: 5 | H9: 5 | I9: 5 | J9: 5 | K9: Красивая и чистая квартира. | M9: Responsive host;Clear instructions;Easy to find;Easy to get inside
A10: 27.01.2026 | B10: 1 | WH 176 | White House |Studio | C10: HMNAHA8R9B | D10: 5 | E10: 5 | F10: 5 | G10: 5 | H10: 5 | I10: 5 | J10: 5 | K10: We like very much and they answered instant for the messages. We can recommend | M10: Looked like the photos;Matched the description;Clear instructions;Easy to find;Always responsive;Helpful instructions;Considerate
A11: 23.01.2026 | B11: 2 | Mar 1604 | Courtyard by Marriott | 1+1 | C11: HMM4RFEQKP | D11: 5 | E11: 5 | F11: 5 | G11: 5 | H11: 5 | I11: 5 | J11: 5 | K11: İnanılmaz memnun ayrıldık. Herşey çok güzeldi. | M11: Free of clutter;Squeaky-clean bathroom;Pristine kitchen;Looked like the photos;Matched the description;Responsive host;Clear instructions;Easy to get inside;Felt right at home;Always responsive;Proactive;Helpful instructions;Considerate;Peaceful;Beautiful surroundings;Private;Walkable;Spotless furniture & linens;Had listed amenities & services | N11: Peaceful | O11: Beautiful surroundings | P11: Private | Q11: Walkable | R11: Spotless furniture & linens | S11: Had listed amenities & services
A12: 22.01.2026 | B12: 3 | DZ 12 | Old town | 1+1 | C12: HMSP8DYRPD | D12: 5 | E12: 5 | F12: 5 | G12: 5 | H12: 5 | I12: 5 | J12: 5 | K12: Kaldığımız en iyi airbnb dairelerinden biri🍀 ikinci kez konakladık, hatta tatilimizi bu dairenin uygun takvimine göre ayarladık😅 daire inanılmaz temiz ve kullanışlı✨ bu tatilimizde hava çok soğuk ve yoğun yağmur olmasına rağmen hiç sıkıntı yaşamadık, daire sıcaktı ve merkezde olmasından dolayı restaurant, cafe ve butiklere arabasız ulaşım gerçek bir rahatlıktı😊 kışın bile keyifliydi, çok teşekkürler | M12: Free of clutter;Squeaky-clean bathroom;Pristine kitchen;Looked like the photos;Matched the description;Responsive host;Clear instructions;Easy to find;Easy to get inside;Flexible check-in;Felt right at home;Always responsive;Local recommendations;Proactive;Helpful instructions;Considerate;Peaceful;Beautiful surroundings;Private;Great restaurants;Lots to do;Walkable;Spotless furniture & linens;Had listed amenities & services | N12: Proactive | O12: Helpful instructions | P12: Considerate | Q12: Peaceful | R12: Beautiful surroundings | S12: Private | T12: Great restaurants
A13: 21.01.2026 | B13: 2 | BG 227 | Bagrationi Residence | 2+1 | C13: HMS94SBQN9 | D13: 5 | E13: 5 | F13: 5 | G13: 5 | H13: 5 | I13: 5 | J13: 5 | K13: Все было замечательно. Особенное спасибо Юлии, которая помогала со всеми вопросами. В квартире были короткие шторы и проблема с работой посудомоечной машиной, но на следующий же день к нам приехали и починили машинку и повесили другие шторы. Большое спасибо за скорость и внимание к деталям | M13: Looked like the photos;Matched the description;Responsive host;Easy to find;Always responsive;Considerate;Spotless furniture & linens;Had listed amenities & services
A14: 21.01.2026 | B14: 2 | Sh8 2505 | Shartava | 1+1 | C14: HMS83HZMYR | D14: 5 | E14: 5 | F14: 5 | G14: 5 | H14: 5 | I14: 5 | J14: 5 | K14: Отличная квартира, в которой комфортно находиться. Очень чисто, в квартире все хорошо продумано, отличная кухня, ванная комната, предусмотрено множество мелочей. Хозяева быстро реагируют на возникающие вопросы. Удобное расположение - рядом магазины, море, набережная, до центра можно прогуляться пешком. Нам все очень понравилось. | L14: Большое спасибо за отличную квартиру! | M14: Squeaky-clean bathroom;Pristine kitchen;Looked like the photos;Matched the description;Easy to find;Easy to get inside;Had listed amenities & services
A15: 20.01.2026 | B15: 4 | MZ 718 | Mziuri Gardens | Studio | C15: HM9CS9QFC9 | D15: 5 | E15: 5 | F15: 5 | G15: 5 | H15: 5 | I15: 5 | J15: 5 | K15: The apartment was very clean and well organized, and everything was exactly where it should be. The place was comfortable and matched the description. Considering the price, it was absolutely worth every penny. I would definitely recommend staying here. | L15: just perfect | M15: Squeaky-clean bathroom;Pristine kitchen
A16: 20.01.2026 | B16: 2 | Orbi C 1125 | Orbi Sity | Studio | C16: HM4MZ9JZBB | D16: 5 | E16: 5 | F16: 5 | G16: 5 | H16: 5 | I16: 5 | J16: 4 | K16: it was a good winter stay. the balcony was sunny after noon, this block especially is close to various of supermarkets and traffic lights to cross to the beach. thank you | L16: gamarcoba 👋 not just this apartment but facility generally suffers from door isolation i realise; the balcony doors are whistling at windy days, and apartment doors are not sound proofed. maybe you guys can find some solutions to that. i hope i fullfill checkout steps, my flights were cancelled that weekend due to weather, i was in a hurry to keep up with some unexpected replanning for my self too. thank you for the stay, have a good day y'all ☀️☀️ | M16: Clear instructions;Easy to find
A17: 19.01.2026 | B17: 2 | Int A 2905 | Intourist | 1+1 | C17: HMPMRKHRQP | D17: 5 | E17: 5 | F17: 5 | G17: 4 | H17: 5 | I17: 5 | J17: 5 | K17: Отличное место, очень понравилось! все супер! хост очень отзывчивый! расположение превосходное! вид просто шикарный! и горы и море, вообще все видно супер!! когда была хорошая погода, даже Эверест было видно! | M17: Looked like the photos;Responsive host;Clear instructions;Easy to find;Easy to get inside;Flexible check-in;Always responsive;Considerate;Peaceful
A18: 17.01.2026 | B18: 3 | PT 2704 | Old town | Studio | C18: HMCSZPKHEP | D18: 5 | E18: 5 | F18: 5 | G18: 5 | H18: 5 | I18: 5 | J18: 5 | K18: Batum’da 2 gün boyunca bu dairede konakladık ve her şeyden gerçekten çok memnun kaldık. Daire hem çok şık hem de son derece temizdi. Ev sahipleri inanılmaz ilgiliydi; en küçük detayı bile düşünmüşler. Konfor, düzen ve misafirperverlik açısından beklentimizin çok üzerindeydi. Kendimizi evimizde gibi hissettik. Gönül rahatlığıyla tavsiye ederim, tekrar Batum’a gelirsek kesinlikle burayı tercih ederiz. Teşekkür ederiz 🙏 | M18: Free of clutter;Felt right at home
A19: 17.01.2026 | B19: 2 | Mar 1327 | Courtyard by Marriott | 1+1 | C19: HM3JFHCNAD | D19: 5 | E19: 5 | F19: 5 | G19: 5 | H19: 5 | I19: 5 | J19: 5 | K19: Отличное местоположение, отзывчивый хозяин и безупречная чистота! | M19: Pristine kitchen;Looked like the photos;Matched the description;Responsive host;Clear instructions;Easy to get inside;Always responsive;Proactive;Helpful instructions;Beautiful surroundings;Spotless furniture & linens
A20: 17.01.2026 | B20: 3 | DZ 12 | Old town | 1+1 | C20: HMA8FNN2S5 | D20: 5 | E20: 5 | F20: 5 | G20: 5 | H20: 5 | I20: 5 | J20: 5 | K20: Amazing flat and amazing location, better European street in Batumi with so many interesting places. | M20: Considerate;Great restaurants
A21: 16.01.2026 | B21: 3 | PT 2704 | Old town | Studio | C21: HMRPEQC2QF | D21: 5 | E21: 5 | F21: 5 | G21: 5 | H21: 5 | I21: 5 | J21: 5 | K21: This is a lovely studio for the Batumi winter. The space is bright and open with spectacular sunrises over the sea and mountains. The bathtub is nothing short of divine in the evenings when the city lights sparkle. Everything is clean and comfortable in the apartment, and it’s perfectly located too. Steps from the sea and the old town. Julia is a great host, so helpful and friendly. A wonderful stay – Thank you! | M21: Free of clutter;Squeaky-clean bathroom;Pristine kitchen;Looked like the photos;Matched the description;Responsive host;Clear instructions;Easy to find;Easy to get inside;Always responsive;Proactive;Helpful instructions;Considerate;Private;Great restaurants;Lots to do;Walkable;Spotless furniture & linens;Had listed amenities & services | N21: Private | O21: Great restaurants | P21: Lots to do | Q21: Walkable | R21: Spotless furniture & linens | S21: Had listed amenities & services
A22: 14.01.2026 | B22: 2 | Mar 1304 | Courtyard by Marriott | 1+1 | C22: HMHS5S85E9 | D22: 5 | E22: 5 | F22: 5 | G22: 5 | H22: 5 | I22: 5 | J22: 5 | K22: War einfach ein Traum das Zimmer Tisch war gedeckt wo wir angekommen sind man hat sich wirklich wie zuhause gefühlt. Einmal war was an der Waschmaschine defekt was passieren kann aber es würde sich sofort darum gekümmert einfach nur klasse würden sofort wieder kommen. | M22: Free of clutter;Squeaky-clean bathroom;Pristine kitchen;Looked like the photos;Matched the description;Responsive host;Clear instructions;Easy to get inside;Flexible check-in;Felt right at home;Always responsive;Helpful instructions;Considerate;Peaceful;Beautiful surroundings;Private;Great restaurants;Lots to do;Walkable;Spotless furniture & linens;Had listed amenities & services | N22: Peaceful | O22: Beautiful surroundings | P22: Private | Q22: Great restaurants | R22: Lots to do | S22: Walkable | T22: Spotless furniture & linens
A23: 13.01.2026 | B23: 2 | Mar 1606 | Courtyard by Marriott | Studio | C23: HMRZDCEPP3 | D23: 5 | E23: 5 | F23: 5 | G23: 5 | H23: 5 | I23: 5 | J23: 5 | K23: I really enjoyed my stay here. The studio had a beautiful view of the sea and sunset, and the location was perfect. The place was comfortable, clean, and had everything I needed. The host was a superhost and very responsive. Highly recommend! | L23: Thank you | M23: Looked like the photos;Flexible check-in;Considerate;Walkable
A24: 13.01.2026 | B24: 1 | BV C 137 | Batumi View | Studio | C24: HMXARAXDEA | D24: 4 | E24: 4 | F24: 4 | G24: 4 | H24: 4 | I24: 5 | J24: 4 | K24: Baya güzel ve temizdi özverileri için çok teşekkür ederim çok memnun kaldım | L24: Her şey mükemmel di çok memnun kaldım
A25: 11.01.2026 | B25: 2 | Mar 1606 | Courtyard by Marriott | Studio | C25: HMYRXPEZWK | D25: 5 | E25: 5 | F25: 5 | G25: 5 | H25: 5 | I25: 5 | J25: 5 | K25: It was great and peaceful place. | L25: We enjoyed in your apartment
A26: 11.01.2026 | B26: 2 | Mar 1327 | Courtyard by Marriott | 1+1 | C26: HM5QYNRBFX | D26: 5 | E26: 5 | F26: 5 | G26: 5 | H26: 5 | I26: 5 | J26: 5 | K26: We really enjoyed our stay at this beautiful apartment, and it was one of the most comfortable stays we've had 🌷Spotlessly clean, warm, with cozy interiors.. the hosts provided ample of amenities and snacks for our comfort. The fragrance that greeted us upon entry was our absolute favourite!The proximity to the sea gave us a picturesque view of the sea & mountains, and the prime location made our commute to lots of nearby restaurants and shops absolutely seamless. Our hosts, Mavi Guest & Julia were extremely gracious, kind and lovely to interact with. Can't recommend enough ❤️ | L26: Thank you so much for hosting us and for an amazing stay and experience. We look forward to visiting here again! 😊 | M26: Free of clutter;Squeaky-clean bathroom;Pristine kitchen;Looked like the photos;Matched the description;Responsive host;Clear instructions;Easy to find;Easy to get inside;Felt right at home;Always responsive;Helpful instructions;Considerate;Peaceful;Beautiful surroundings;Great restaurants;Lots to do;Walkable;Spotless furniture & linens;Had listed amenities & services | N26: Peaceful | O26: Beautiful surroundings | P26: Great restaurants | Q26: Lots to do | R26: Walkable | S26: Spotless furniture & linens | T26: Had listed amenities & services
A27: 11.01.2026 | B27: 1 | OBT 2908 | Orbi Beach Tower | Studio | C27: HMCFPMQ4YT | D27: 5 | E27: 5 | F27: 5 | G27: 5 | H27: 5 | I27: 5 | J27: 5 | K27: Все было отлично! Хорошее место для отдыха и отличные хозяева, быстро отвечают! Маленький минус за бойлер, который нагревается и надо немного подождать, чтобы была горячая вода, но это мелочи. 4,90 из 5.00 🔝
A28: 10.01.2026 | B28: 1 | WS E 1202 | White Sails |1+1 | C28: HMS9TM85D3 | D28: 5 | E28: 5 | F28: 5 | G28: 5 | H28: 5 | I28: 5 | J28: 5 | K28: Прекрасная квартира, чистый и зеленый район. Под домом сразу 3 Круглосуточных магазина и кафе. Квартира уютная и просторная. Никаких проблем не было за время проживания. | M28: Free of clutter;Squeaky-clean bathroom;Pristine kitchen;Looked like the photos;Matched the description;Responsive host;Clear instructions;Easy to find;Easy to get inside;Flexible check-in;Felt right at home;Always responsive;Local recommendations;Proactive;Helpful instructions;Considerate;Peaceful;Beautiful surroundings;Private;Great restaurants;Lots to do;Walkable;Spotless furniture & linens;Had listed amenities & services | N28: Proactive | O28: Helpful instructions | P28: Considerate | Q28: Peaceful | R28: Beautiful surroundings | S28: Private | T28: Great restaurants
A29: 08.01.2026 | B29: 2 | Orbi D1 3902 | Orbi Sity | 1+1 | C29: HMYY52WMDQ | D29: 5 | E29: 5 | F29: 3 | G29: 5 | H29: 4 | I29: 5 | J29: 4 | K29: Great place and owner but your team need to be more friendly and welcoming when approaching client. Yet the host is amazing I couldn’t say nothing but thanks from the deep of my heart.❤️ | L29: Your cohost needs to be more careful when treating clients especially when they are extra proactive and peaceful.Apart from that you were so supportive and I tried my best to leave as per the time 12 and I did. Much appreciate it | M29: Squeaky-clean bathroom;Looked like the photos;Matched the description;Trouble with lock;Had to wait;Beautiful surroundings;Great restaurants;Lots to do;Walkable;Spotless furniture & linens;Had listed amenities & services
A30: 07.01.2026 | B30: 1 | BV B 1318 | Batumi View | Studio | C30: HM29834JY3 | D30: 5 | E30: 5 | F30: 5 | G30: 5 | H30: 5 | I30: 5 | J30: 5 | K30: отличные апартаменты! | L30: спасибо, все было отлично! | M30: Free of clutter;Squeaky-clean bathroom;Pristine kitchen;Looked like the photos;Matched the description;Responsive host;Clear instructions;Always responsive;Considerate;Peaceful;Great restaurants;Walkable;Spotless furniture & linens;Had listed amenities & services | N30: Had listed amenities & services
A31: 07.01.2026 | B31: 2 | Mar 1606 | Courtyard by Marriott | Studio | C31: HM3AYPHTNM | D31: 5 | E31: 5 | F31: 5 | G31: 5 | H31: 5 | I31: 5 | J31: 5 | K31: Отличные аппартаменты с шикарным видом на море!Функциональная кухня, ванная комната чистая, все очень удобно и продуманно.Вид по вечерам с балкона потрясающий)Рядом много ресторанов, хороший супермаркет Карфур.Мы посетили Спа, очень достойный, баня, бассейн с теплой водой. Мы прекрасно отдохнули, рекомендуем от всей души) | M31: Squeaky-clean bathroom;Pristine kitchen;Looked like the photos;Matched the description;Proactive;Helpful instructions;Considerate;Beautiful surroundings;Great restaurants;Walkable;Spotless furniture & linens;Had listed amenities & services
A32: 05.01.2026 | B32: 7 | PR 18 D 181 | Pirosmani | 2+1 | C32: HMN5ZJ43BK | D32: 5 | E32: 5 | F32: 5 | G32: 5 | H32: 5 | I32: 5 | J32: 5 | K32: Отличные апартаменты с красивым видом на море и горы. В доме 3 лифта, поэтому не будет проблем, что бы быстро добраться на высокий этаж здания | M32: Pristine kitchen;Looked like the photos;Matched the description;Responsive host;Clear instructions;Beautiful surroundings;Walkable;Had listed amenities & services
A33: 05.01.2026 | B33: 3 | PT 2704 | Old town | Studio | C33: HM9J2T53YJ | D33: 5 | E33: 5 | F33: 5 | G33: 5 | H33: 5 | I33: 5 | J33: 5 | K33: Невероятно красивые апартаменты, я впервые за все поездки встретила такой подход в чистоте: чисто было буквально все, ни одной пылинки. Хозяева очень отзывчивые и готовы ответить на любой вопрос. В апартаментах так же было очень тепло и комфортно. Рекомендую для отдыха ❤️
A34: 04.01.2026 | B34: 1 | BV A 0514 | Batumi View | Studio | C34: HMWK23DXTZ | D34: 4 | E34: 5 | F34: 2 | G34: 5 | H34: 3 | I34: 4 | J34: 4 | K34: It’s a really beautiful accommodation, one of the best I tried with my holiday in Georgia . The bathroom was amazing with heated floors and it wasn’t a wet room style which we preferred and the room was spacious and modern . And the view was really wonderful. And it had a microwave which was great for leftovers and not many places have that. | M34: Free of clutter;Squeaky-clean bathroom;Pristine kitchen;Looked like the photos;Matched the description;Unresponsive Host;Had to wait;Slow to respond;Peaceful;Beautiful surroundings;Private;Great restaurants;Walkable;Spotless furniture & linens;Had listed amenities & services | N34: Spotless furniture & linens | O34: Had listed amenities & services
A35: 04.01.2026 | B35: 2 | Orbi D1 3902 | Orbi Sity | 1+1 | C35: HM22P5AJBQ | D35: 5 | E35: 5 | F35: 5 | G35: 5 | H35: 5 | I35: 5 | J35: 5 | K35: Beautiful apartment overlooking the Black Sea | L35: Internet at Orbi! And bedsheets need to be better
A36: 03.01.2026 | B36: 2 | Int B 2612 | Intourist | 1+1 | C36: HMR5CHJAHA | D36: 4 | E36: 5 | F36: 4 | G36: 4 | H36: 4 | I36: 5 | J36: 4 | K36: We had a great stay and really enjoyed the place — clean, cozy, and exactly as described. The host was friendly and helpful, and overall the team was very responsive.The only slightly funny (and mildly confusing) part was that the host and their team didn’t seem to communicate with each other, so I felt like a professional copy-paste manager, sending the same reply to different people one by one 😄A small “bitter slice of the cake” was that some of the radiators had air in them, but to their credit, it was fixed quickly and efficiently — well done!All in all, a very positive experience, and I’d happily stay here again. Highly recommended! | L36: Hi 🙂 You might want to improve communication within your team — otherwise guests may feel like they’re replying to the same message on repeat mode.We were happy to stay with you! | M36: Responsive host;Easy to get inside;Flexible check-in
A37: 03.01.2026 | B37: 2 | Orbi D2 3216 | Orbi Sity | 1+1 | C37: HMZ8AT3ZT8 | D37: 5 | E37: 5 | F37: 5 | G37: 4 | H37: 5 | I37: 5 | J37: 3 | K37: Güzel bir konaklama oldu teşekkür ederiz | M37: Free of clutter;Looked like the photos;Matched the description;Responsive host;Clear instructions;Easy to find;Easy to get inside;Flexible check-in;Felt right at home;Always responsive;Proactive;Considerate;Peaceful;Beautiful surroundings;Lots to do;Had listed amenities & services | N37: Beautiful surroundings | O37: Lots to do | P37: Had listed amenities & services
A38: 03.01.2026 | B38: 2 | Orbi D1 3902 | Orbi Sity | 1+1 | C38: HM3AMA85HN | D38: 4 | E38: 5 | F38: 5 | G38: 4 | H38: 5 | I38: 5 | J38: 5 | K38: Evin konumu çok güzel. Evde ısıtma sadece klima ile yapılmıştı oyüzden soğuktan hasta oldum ev sahibi daha sonra başka bir ısıtıcı getirince daha iyi oldu tavsiye ederim | M38: Looked like the photos;Responsive host;Clear instructions;Easy to get inside;Always responsive;Proactive;Beautiful surroundings;Walkable
A39: 01.01.2026 | B39: 3 | DZ 12 | Old town | 1+1 | C39: HMJZ4EPWZN | D39: 5 | E39: 5 | F39: 5 | G39: 5 | H39: 5 | I39: 5 | J39: 5 | K39: افضل سكن جلست فيه وتعامل مره جميل ومميز | L39: شقة جميلة ♥️
A40: 31.12.2025 | B40: 4 | MZ 913 | Mziuri Gardens | Studio | C40: HM9CJ294X5 | D40: 5 | E40: 5 | F40: 5 | G40: 5 | H40: 5 | I40: 4 | J40: 5 | K40: Квартира очень красивая, с новым ремонтом. Все необходимые вещи имеются. Немного далековато от центра. В целом остались довольны. | M40: Free of clutter;Pristine kitchen;Looked like the photos;Matched the description;Responsive host;Easy to find;Easy to get inside;Always responsive;Considerate;Peaceful;Spotless furniture & linens
A41: 30.12.2025 | B41: 2 | Sh8 2505 | Shartava | 1+1 | C41: HM9EBPW5RS | D41: 5 | E41: 5 | F41: 5 | G41: 5 | H41: 5 | I41: 5 | J41: 5 | K41: Minha esposa e eu tivemos ótima experiência durante as 9 semanas em que ficamos neste apartamento. O local fica em uma avenida movimentada, mas não tivemos problemas com barulhos, há um isolamento acústico muito bom. Ele fica próximo de supermercados, da orla, farmácias, praças e parques. É igual as fotos, iluminado, muito limpo, chuveiro com uma ótima pressão. A cama e travesseiros são confortáveis e as roupas de cama são de boa qualidade. A cozinha é equipada e conseguimos preparar nossas refeições com tranquilidade. A mesa para refeições tem um bom tamanho e as cadeiras são confortáveis. A internet é boa e estável. A máquina de lavar é muito boa. Julia estava sempre atenta e à disposição caso precisássemos de algo. O check-in e o check-out foram tranquilos. Achamos este apartamento uma ótima opção para passar uma curta ou longa temporada na cidade. | L41: Sugiro que você coloque cortinas blackout. Embora não atrapalhou nosso sono, Sempre havia luz vindo da rua durante toda a noite.Obrigado por tudo! | M41: Free of clutter;Squeaky-clean bathroom;Pristine kitchen;Looked like the photos;Matched the description;Clear instructions;Always responsive;Considerate;Great restaurants;Lots to do;Walkable;Spotless furniture & linens;Had listed amenities & services
A42: 28.12.2025 | B42: 3 | DZ 12 | Old town | 1+1 | C42: HMJRB42DZ9 | D42: 5 | E42: 5 | F42: 5 | G42: 5 | H42: 5 | I42: 5 | J42: 5 | K42: Все шикарно! Новая, свежая, чистая квартира. Все необходимое есть, центр города, выходишь и сразу попадаешь на площадь Европы. Общение легкое, проблем не было, шумоизоляция прекрасна, интернет работает хорошо. Рекомендую! Спасибо 😍 | M42: Looked like the photos;Matched the description;Responsive host;Clear instructions;Easy to find;Felt right at home;Always responsive;Local recommendations;Proactive;Considerate;Had listed amenities & services
A43: 28.12.2025 | B43: 1 | WS B 503 | White Sails |1+1 | C43: HMXNYSYJ3P | D43: 5 | E43: 5 | F43: 5 | G43: 5 | H43: 5 | I43: 5 | J43: 5 | K43: Отличная квартира, полностью соответствует фото в объявлении. Очень хорошая планировка, удобно работать за столом и фоном поглядывать в телевизор. Жили в декабре, боялись что будет холодно, тк нет газового отопления, но сплит-система жарит так сильно, что приходилось даже убавлять. Однозначно, рекомендую! Летом планируем в очередной раз в Батуми, будем пытаться попасть сюда же! | L43: Все было, отлично. Но если будет возможность: добавьте обувную ложку. Ее не хватало) | M43: Free of clutter;Squeaky-clean bathroom;Pristine kitchen;Looked like the photos;Matched the description;Responsive host;Clear instructions;Easy to find;Easy to get inside;Felt right at home;Always responsive;Proactive;Considerate;Peaceful;Beautiful surroundings;Walkable;Spotless furniture & linens;Had listed amenities & services
A44: 28.12.2025 | B44: 1 | WS E 1202 | White Sails |1+1 | C44: HM8F99THKC | D44: 5 | E44: 5 | F44: 5 | G44: 5 | H44: 5 | I44: 5 | J44: 5 | K44: Прекрасная светлая квартира очень близко к набережной. Внизу есть рестораны, магазины. Нас еще порадовала пешая доступность скейт-парка! Можно прям из квартиры смотреть как взлетают или садятся самолеты - это всегда вызвало неподдельный детский восторг! | M44: Squeaky-clean bathroom;Pristine kitchen;Looked like the photos;Matched the description;Responsive host;Clear instructions;Easy to find;Easy to get inside;Felt right at home;Always responsive;Proactive;Helpful instructions;Considerate;Peaceful;Beautiful surroundings;Great restaurants;Walkable;Spotless furniture & linens;Had listed amenities & services
A45: 26.12.2025 | B45: 2 | Orbi D2 1625 | Orbi Sity | 1+1 | C45: HMQ2F958YQ | D45: 5 | E45: 5 | F45: 5 | G45: 5 | H45: 5 | I45: 5 | J45: 5 | K45: בשכירת דירה ב־באטומי יש שילוב מצוין של נוחות, גמישות ותמורה גבוהה למחיר. העיר מציעה היצע רחב של דירות מודרניות, לעיתים חדשות ומאובזרות, במחירים נוחים משמעותית ביחס לערים דומות. הקרבה לים, הטיילת, השירותים והתחבורה – יחד עם קהילה בינלאומית ותשתיות מתפתחות – הופכים את ההשכרה בבאטומי לפתרון נעים, יעיל ומשתלם הן לשהייה קצרה והן למגורים לתקופה ארוכה.
A46: 25.12.2025 | B46: 4 | MZ 913 | Mziuri Gardens | Studio | C46: HM32NQACMJ | D46: 5 | E46: 5 | F46: 5 | G46: 5 | H46: 5 | I46: 5 | J46: 5 | K46: Burası şehrin merkezine çok yakında deniz manzaralı harika bir daire burda kalmaktan fazlasıyla memnuniyet duydum daire he cok güzel hemde tertemizde üstelik her şey mevcut içeride bir daha bu ülkeye gelirsem mutlaka tekrar kalmayı isteyeceğim yer teşekkür ediyorum kendilerine🙏😊 | M46: Free of clutter;Squeaky-clean bathroom;Easy to find;Felt right at home
A47: 24.12.2025 | B47: 5 | TG A8 | Tropical Garden | Studio | C47: HM3KDW2YKC | D47: 5 | E47: 5 | F47: 5 | G47: 5 | H47: 5 | I47: 5 | J47: 4 | K47: Хорошие апартаменты, главное в них - шикарный вид из окна на море в 100 метрах. Когда нужна тишина и покой - идеально.Жилье соответствует описанию, удобное самостоятельное заселение.В зоне кухни есть минимально необходимый набор посуды для приготовления.Телевизор TCL со Smart TV, есть приставка Magti.Освещение в апарте имеет несколько вариантов и зонировано.Матрас и подушки удобные.Кондиционер и отдельно отопление есть.Интернет - скорость около 10-20 mbit, периодически \падает\" | L47: для нетребовательных ситуаций ок | M47: но если вам критично стабильная связь для удаленной работы - нужно иметь запасной вариант (4G/5G). Как и иметь Powerbank - отключения эл.энергии - не редкость (везде в Грузии).Шумоизоляция между апартами невысокая
A48: 23.12.2025 | B48: 1 | WS E 1202 | White Sails |1+1 | C48: HMS8JY8W9W | D48: 4 | E48: 4 | F48: 5 | G48: 5 | H48: 4 | I48: 4 | J48: 4 | K48: .
A49: 22.12.2025 | B49: 1 | BV A 0514 | Batumi View | Studio | C49: HMSFYBFT3Z | D49: 5 | E49: 5 | F49: 5 | G49: 5 | H49: 5 | I49: 5 | J49: 5 | K49: This is the best Airbnb I've stayed in. The place is new and luxurious. You get 5 star quality for an affordable price. It's right on the beach with a great view and many shops and restaurants at your feet. The vibe is incredible. The amenities you get are outstanding. The bathroom has superb lighting and even heated shower and bathroom floors. The bath towels are XL, thick cotton, and luxurious. The bed is the most comfortable bed I've had in Georgia. The TV is a large Samsung smart TV. The elevators and lobby are very nice. Everything was immaculate. We had refreshments upon check in and everything we could need was provided. I will definitely stay here again next time I'm in Batumi. The host was also very accommodating, kind and helpful. Many thanks! 💓✨️ | L49: I just left a 5 star review. We really enjoyed our stay. I'm not sure if you're aware, but the bathroom sink spigot is loose. Someone could easily break it if it isn't tightened soon. Thank you again for everything. 💓✨️ | M49: Free of clutter;Squeaky-clean bathroom;Pristine kitchen;Looked like the photos;Matched the description;Responsive host;Clear instructions;Easy to find;Easy to get inside;Flexible check-in;Felt right at home;Always responsive;Local recommendations;Proactive;Helpful instructions;Considerate;Peaceful;Beautiful surroundings;Great restaurants;Lots to do;Walkable;Spotless furniture & linens;Had listed amenities & services
A50: 21.12.2025 | B50: 2 | Mar 1304 | Courtyard by Marriott | 1+1 | C50: HMXSCKWHMX | D50: 5 | E50: 5 | F50: 5 | G50: 5 | H50: 5 | I50: 5 | J50: 5 | K50: Gayet güzeldi konaklama
A51: 20.12.2025 | B51: 3 | DZ 12 | Old town | 1+1 | C51: HMFBY2B9AX | D51: 5 | E51: 5 | F51: 5 | G51: 5 | H51: 5 | I51: 5 | J51: 5 | K51: Batum’un kalbinde, kusursuz bir konaklama deneyimi yaşadık.Daire, tam anlamıyla merkezde yer alıyordu ve şehri hissetmek isteyen biri için konumu harika.Yürüyerek Batumi Boulevard, Europe Square ve Piazza Square gibi Batum’un ruhu olan noktalara ulaşabiliyorduk.Çevresi;çok iyi restoranlar,kafeler, mağazalar ve uzun yürüyüş yollarıyla doluydu. Şehrin dokusunu cidden yaşadık.Daireye adım attığımız anda tertemiz, ferah temizlik kokusu ilk andan doğru yerde olduğumuzu hissettirdi.Dekorasyon çok özenli,şık ve sıcak bir atmosfere sahipti. Mutfakta ihtiyaç duyulabilecek tüm ekipmanlar vardı.banyosu çok geniş rahattı. Yatak odası ferah, salon konforlu ve kullanışlıydı.En sevdiğimiz detay;yatak odası ve salondan çıkılan,çok geniş,ferah ve sigara içilebilen terastı.Ev sahibinin ilgisi harikaydı.Mekan,restoran ve gezilecek yer önerilerinde bulundu önerdiği her yer gerçekten güvenle gidilebilecek, çok kaliteli ama aynı zamanda fiyat-performans açısından çok başarılı mekanlardı.Çok teşekkürler? | M51: Free of clutter;Squeaky-clean bathroom;Pristine kitchen;Looked like the photos;Matched the description;Responsive host;Clear instructions;Easy to find;Easy to get inside;Flexible check-in;Felt right at home;Always responsive;Local recommendations;Proactive;Helpful instructions;Considerate;Peaceful;Beautiful surroundings;Private;Great restaurants;Lots to do;Walkable;Spotless furniture & linens;Had listed amenities & services
A52: 20.12.2025 | B52: 4 | MZ 913 | Mziuri Gardens | Studio | C52: HMMF338T28 | D52: 5 | E52: 5 | F52: 5 | G52: 4 | H52: 5 | I52: 4 | J52: 4 | K52: The apartment is very modern with a beautiful view of the Black Sea from the balcony. It has all the amenities you need for a stay. We stayed 5 days. You can access the sea by walking straight across the street. The bed was clean, the kitchen has pots, pans, glasses, silverware, cooking utensils, and plates. The only con is the hot water heater. For us, the shower got cold rather quickly. Other than that, I highly recommend. It's a beautiful place and the host is very accommodating and very responsive. Many thanks! 💓 | M52: Free of clutter;Looked like the photos;Matched the description;Responsive host;Clear instructions;Easy to find;Easy to get inside;Flexible check-in;Felt right at home;Always responsive;Local recommendations;Proactive;Helpful instructions;Considerate;Peaceful;Beautiful surroundings;Walkable;Spotless furniture & linens;Had listed amenities & services
A53: 19.12.2025 | B53: 2 | Mar 1604 | Courtyard by Marriott | 1+1 | C53: HM3NWW3JJ3 | D53: 5 | E53: 5 | F53: 5 | G53: 5 | H53: 5 | I53: 4 | J53: 5 | K53: The apartment was comfortable and well equipped, with a good bed, fast internet, large TVs, and a lovely sea view from the balcony. The room’s location at the end of the corridor also offered good privacy.The hosting company was excellent. Communication was smooth throughout, and Julia in particular went above and beyond to help during my stay. Any issues that came up were handled quickly and professionally by the host team.Overall, a pleasant stay with very responsive hosts. | M53: Responsive host;Clear instructions;Easy to find;Easy to get inside;Flexible check-in;Felt right at home;Beautiful surroundings;Lots to do;Walkable
A54: 19.12.2025 | B54: 1 | WS B 503 | White Sails |1+1 | C54: HM2JCP9FST | D54: 5 | E54: 5 | F54: 5 | G54: 5 | H54: 5 | I54: 5 | J54: 5 | K54: Мне очень понравилось пребывание в жильё Mavi Guest. Жильё полностью соответствует фотографиям и описанию. Было убрано и очень чисто. Хозяин очень отзывчивый. Из-за личных обстоятельств пришлось уменьшить количество дней пребывания - хозяин пошёл навстречу. Однозначно доволен, однозначно рекомендую! | L54: Всё супер! | M54: Pristine kitchen;Looked like the photos;Matched the description;Responsive host;Clear instructions;Easy to find;Easy to get inside;Felt right at home;Always responsive;Considerate;Peaceful;Beautiful surroundings;Walkable;Spotless furniture & linens;Had listed amenities & services
A55: 19.12.2025 | B55: 1 | BV A 0514 | Batumi View | Studio | C55: HMF4F2FHJZ | D55: 5 | E55: 5 | F55: 5 | G55: 5 | H55: 5 | I55: 5 | J55: 5 | K55: Лучшие апартаменты, в который когда-либо останавливались. Было уютно , как дома. С удовольствием еще бы остановились здесь! | L55: Все было замечательно, спасибо за уютные апартаменты ! | M55: Pristine kitchen;Looked like the photos;Matched the description;Easy to find;Easy to get inside;Felt right at home;Helpful instructions;Peaceful;Great restaurants;Lots to do;Spotless furniture & linens;Had listed amenities & services
A56: 19.12.2025 | B56: 2 | Orbi D1 3902 | Orbi Sity | 1+1 | C56: HMWXTJ33NT | D56: 5 | E56: 5 | F56: 5 | G56: 5 | H56: 5 | I56: 5 | J56: 5 | K56: Hands down, it is the most amazing stay I have ever lived in. The panaromic view of the Black Sea from the balcony of this 39th floor apt is just breathtaking. It is right at the centre of the city, with a lot of points at walkable distance from the apt. | L56: Everything went well. No suggestions at all. Super happy | M56: Free of clutter;Looked like the photos;Matched the description;Clear instructions;Easy to get inside;Peaceful;Beautiful surroundings;Lots to do;Spotless furniture & linens
A57: 18.12.2025 | B57: 1 | WH 176 | White House |Studio | C57: HMDSPADWPZ | D57: 5 | E57: 5 | F57: 5 | G57: 5 | H57: 5 | I57: 5 | J57: 5 | K57: Квартира новая, очень уютная, чистая, красивая. Все продумано до мелочей, красивый дизайн. Есть все, что может понадобиться. Место тихое, спать было очень удобно и спокойно. Рядом набережная, красивый парк, супермаркет, остановка транспорта. Рекомендую на все 100%! Спасибо за гостеприимство и приятный отдых!🥰 | L57: Спасибо за заботу о гостях! Квартира отличная, все удобно, чисто и красиво! Обязательно приеду к вам еще!🤗 | M57: Free of clutter;Squeaky-clean bathroom;Pristine kitchen;Looked like the photos;Matched the description;Clear instructions;Easy to get inside;Helpful instructions;Considerate;Peaceful;Beautiful surroundings;Walkable;Spotless furniture & linens;Had listed amenities & services
A58: 17.12.2025 | B58: 3 | PT 2604 | Old town | Studio | C58: HMJ9EQB4CQ | D58: 5 | E58: 5 | F58: 5 | G58: 5 | H58: 5 | I58: 5 | J58: 5 | K58: Всё прошло хорошо. Жильё соответствует описанию и фотографиям, чисто и уютно. Заселение и выезд прошли без проблем, хозяин был на связи и оперативно отвечал на вопросы. В целом остались довольны проживанием, можем рекомендовать. | M58: Free of clutter;Pristine kitchen;Looked like the photos;Matched the description;Responsive host;Clear instructions;Easy to find;Easy to get inside;Felt right at home;Always responsive;Local recommendations;Proactive;Helpful instructions;Considerate;Beautiful surroundings;Great restaurants;Lots to do;Walkable;Spotless furniture & linens;Had listed amenities & services

Sheet выгрузка заселений
A1: Confirmation code | B1: Listing | C1: Guest name | D1: Check-in | E1: Check-out | F1: Revenue | G1: Channel | H1: Accommodation | I1: Channel Commission
A2: HM3AYPHTNM | B2: 2 | Mar 1606 | Courtyard by Marriott | Studio | C2: Татьяна | D2: 02.01.2026 | E2: 07.01.2026 | F2: 203.53 | G2: Airbnb | H2: 196 | I2: 6.33
A3: HMDHKC2DNM | B3: 1 | BV A 0514 | Batumi View | Studio | C3: Anastasiia | D3: 02.01.2026 | E3: 04.01.2026 | F3: 105.14 | G3: Airbnb | H3: 90 | I3: 3.27
A4: 123466 | B4: 1 | WS B 1510 | White Sails |Studio | C4: noname1 | D4: 02.01.2026 | E4: 04.01.2026 | F4: 84.76 | G4: Direct | H4: 84.76
A5: 123492 | B5: 2 | Mar 1304 | Courtyard by Marriott | 1+1 | C5: Юлия Сопова | D5: 03.01.2026 | E5: 06.01.2026 | F5: 133.83 | G5: Direct | H5: 133.83
A6: HMCFPMQ4YT | B6: 1 | OBT 2908 | Orbi Beach Tower | Studio | C6: Albert | D6: 04.01.2026 | E6: 09.01.2026 | F6: 211.25 | G6: Airbnb | H6: 200 | I6: 6.57
A7: HMYY52WMDQ | B7: 2 | Orbi D1 3902 | Orbi Sity | 1+1 | C7: Yousef | D7: 04.01.2026 | E7: 08.01.2026 | F7: 180.38 | G7: Airbnb | H7: 162 | I7: 5.61
A8: HMKA89R5HF | B8: 5 | TG A8 | Tropical Garden | Studio | C8: Natasha Wehrli | D8: 04.01.2026 | E8: 02.02.2026 | F8: 537.31 | G8: Airbnb | H8: 542.05 | I8: 16.71
